Workbook

Sheet Overview
A1: Dates | C1: Unique Meals | F1: Meal Volumes - by country | K1: Meal Volumes
A2: Month | B2: Week | C2: Total | D2: Verden | E2: Coman | F2: BE | G2: NL | H2: SE | I2: DK | J2: DE | K2: Total | L2: Verden | M2: Coman
A3: 2026-M01 | B3: 2026-W01 | C3: {=transpose('Slot Selection'!K119:BJ119)} -> 18 | D3: {=transpose('Slot Selection'!K118:BJ118)} -> 0 | E3: =C3-D3 -> 18 | F3: {=transpose('Volume Development'!B26:BA30)} -> 10563 | G3: 13838 | H3: 6383 | I3: 6520 | J3: 13120 | K3: {=transpose('Volume Development'!B14:BA14)} -> 50424 | L3: {=TRANSPOSE('Volume Development'!B4:BA4)} -> 0 | M3: {=transpose('Volume Development'!B5:BA5)} -> 50424
A4: 2026-M01 | B4: 2026-W02 | C4: 18 | D4: 0 | E4: =C4-D4 -> 18 | F4: 15788 | G4: 19716 | H4: 9142 | I4: 9662 | J4: 18009 | K4: 72317 | L4: 0 | M4: 72317
A5: 2026-M01 | B5: 2026-W03 | C5: 18 | D5: 0 | E5: =C5-D5 -> 18 | F5: 18886 | G5: 24561 | H5: 15517 | I5: 14345 | J5: 23886 | K5: 97195 | L5: 0 | M5: 97195
A6: 2026-M01 | B6: 2026-W04 | C6: 18 | D6: 0 | E6: =C6-D6 -> 18 | F6: 19226 | G6: 26659 | H6: 17674 | I6: 15250 | J6: 26001 | K6: 104810 | L6: 0 | M6: 104810
A7: 2026-M01 | B7: 2026-W05 | C7: 18 | D7: 0 | E7: =C7-D7 -> 18 | F7: 19418 | G7: 26913 | H7: 17944 | I7: 14861 | J7: 26398 | K7: 105534 | L7: 0 | M7: 105534
A8: 2026-M02 | B8: 2026-W06 | C8: 18 | D8: 0 | E8: =C8-D8 -> 18 | F8: 20138 | G8: 31395 | H8: 19481 | I8: 15666 | J8: 28331 | K8: 115011 | L8: 0 | M8: 115011
A9: 2026-M02 | B9: 2026-W07 | C9: 18 | D9: 0 | E9: =C9-D9 -> 18 | F9: 20138 | G9: 31345 | H9: 18468 | I9: 15801 | J9: 28372 | K9: 114124 | L9: 0 | M9: 114124
A10: 2026-M02 | B10: 2026-W08 | C10: 18 | D10: 0 | E10: =C10-D10 -> 18 | F10: 18990 | G10: 31766 | H10: 19056 | I10: 15684 | J10: 27692 | K10: 113188 | L10: 0 | M10: 113188
A11: 2026-M02 | B11: 2026-W09 | C11: 18 | D11: 0 | E11: =C11-D11 -> 18 | F11: 19614 | G11: 31723 | H11: 17474 | I11: 16011 | J11: 26774 | K11: 111596 | L11: 0 | M11: 111596
A12: 2026-M03 | B12: 2026-W10 | C12: 18 | D12: 0 | E12: =C12-D12 -> 18 | F12: 20866 | G12: 32924 | H12: 16220 | I12: 14086 | J12: 27372 | K12: 111468 | L12: 0 | M12: 111468
A13: 2026-M03 | B13: 2026-W11 | C13: 18 | D13: 0 | E13: =C13-D13 -> 18 | F13: 21218 | G13: 32787 | H13: 16128 | I13: 14798 | J13: 26621 | K13: 111552 | L13: 0 | M13: 111552
A14: 2026-M03 | B14: 2026-W12 | C14: 18 | D14: 0 | E14: =C14-D14 -> 18 | F14: 20414 | G14: 32817 | H14: 15996 | I14: 14038 | J14: 25038 | K14: 108303 | L14: 0 | M14: 108303
A15: 2026-M03 | B15: 2026-W13 | C15: 18 | D15: 0 | E15: =C15-D15 -> 18 | F15: 18769 | G15: 30745 | H15: 15845 | I15: 13441 | J15: 23649 | K15: 102449 | L15: 0 | M15: 102449
... A54: 2026-M12 | B54: 2026-W52 | C54: 36 | D54: 36 | E54: =C54-D54 -> 0 | F54: 18476.948 | G54: 22374.616 | H54: 10743.873 | I54: 8341.3746 | J54: 14663.092 | K54: 74599.904 | L54: 74599.904 | M54: 0

Sheet Volume Development
A2: Month | B2: 2026-M01 | C2: 2026-M01 | D2: 2026-M01 | E2: 2026-M01 | F2: 2026-M01 | G2: 2026-M02 | H2: 2026-M02 | I2: 2026-M02 | J2: 2026-M02 | K2: 2026-M03 | L2: 2026-M03 | M2: 2026-M03 | N2: 2026-M03 | O2: 2026-M04 | P2: 2026-M04 | Q2: 2026-M04 | R2: 2026-M04 | S2: 2026-M04 | T2: 2026-M05 | U2: 2026-M05 | V2: 2026-M05 | W2: 2026-M05 | X2: 2026-M06 | Y2: 2026-M06 | Z2: 2026-M06 | AA2: 2026-M06 | AB2: 2026-M07 | AC2: 2026-M07 | AD2: 2026-M07 | AE2: 2026-M07 | AF2: 2026-M07 | AG2: 2026-M08 | AH2: 2026-M08 | AI2: 2026-M08 | AJ2: 2026-M08 | AK2: 2026-M09 | AL2: 2026-M09 | AM2: 2026-M09 | AN2: 2026-M09 | AO2: 2026-M10 | AP2: 2026-M10 | AQ2: 2026-M10 | AR2: 2026-M10 | AS2: 2026-M10 | AT2: 2026-M11 | AU2: 2026-M11 | AV2: 2026-M11 | AW2: 2026-M11 | AX2: 2026-M12 | AY2: 2026-M12 | AZ2: 2026-M12 | BA2: 2026-M12
A3: Week | B3: 2026-W01 | C3: 2026-W02 | D3: 2026-W03 | E3: 2026-W04 | F3: 2026-W05 | G3: 2026-W06 | H3: 2026-W07 | I3: 2026-W08 | J3: 2026-W09 | K3: 2026-W10 | L3: 2026-W11 | M3: 2026-W12 | N3: 2026-W13 | O3: 2026-W14 | P3: 2026-W15 | Q3: 2026-W16 | R3: 2026-W17 | S3: 2026-W18 | T3: 2026-W19 | U3: 2026-W20 | V3: 2026-W21 | W3: 2026-W22 | X3: 2026-W23 | Y3: 2026-W24 | Z3: 2026-W25 | AA3: 2026-W26 | AB3: 2026-W27 | AC3: 2026-W28 | AD3: 2026-W29 | AE3: 2026-W30 | AF3: 2026-W31 | AG3: 2026-W32 | AH3: 2026-W33 | AI3: 2026-W34 | AJ3: 2026-W35 | AK3: 2026-W36 | AL3: 2026-W37 | AM3: 2026-W38 | AN3: 2026-W39 | AO3: 2026-W40 | AP3: 2026-W41 | AQ3: 2026-W42 | AR3: 2026-W43 | AS3: 2026-W44 | AT3: 2026-W45 | AU3: 2026-W46 | AV3: 2026-W47 | AW3: 2026-W48 | AX3: 2026-W49 | AY3: 2026-W50 | AZ3: 2026-W51 | BA3: 2026-W52
A4: Verden Meal Volume | B4: =B35+B39+B43 -> 0 | C4: =C35+C39+C43 -> 0 | D4: =D35+D39+D43 -> 0 | E4: =E35+E39+E43 -> 0 | F4: =F35+F39+F43 -> 0 | G4: =G35+G39+G43 -> 0 | H4: =H35+H39+H43 -> 0 | I4: =I35+I39+I43 -> 0 | ... AB4: =AB35+AB39+AB43 -> 79459.142 | AC4: =AC11 -> 78465.319 | AD4: =AD11 -> 73275.561 | AE4: =AE11 -> 69598.196 | AF4: =AF11 -> 77290.85 | AG4: =AG11 -> 79262.829 | AH4: =AH11 -> 84794.296 | AI4: =AI11 -> 94709.683 | AJ4: =AJ11 -> 99479.923 | ... BA4: =BA11 -> 74599.904
A5: Coman Meal Volume | B5: =B36+B40+B44 -> 50424 | C5: =C36+C40+C44 -> 72317 | D5: =D36+D40+D44 -> 97195 | E5: =E36+E40+E44 -> 104810 | F5: =F36+F40+F44 -> 105534 | G5: =G36+G40+G44 -> 115011 | H5: =H36+H40+H44 -> 114124 | I5: =I36+I40+I44 -> 113188 | ... AE5: =AE36+AE40+AE44 -> 8715.2407 | AF5: =AF12 -> 0 | AG5: =AG12 -> 0 | AH5: =AH12 -> 0 | AI5: =AI12 -> 0 | AJ5: =AJ12 -> 0 | AK5: =AK12 -> 0 | AL5: =AL12 -> 0 | AM5: =AM12 -> 0 | ... BA5: =BA12 -> 0
A6: Planned Verden Share | B6: =B4/(B4+B5) -> 0 | C6: =C4/(C4+C5) -> 0 | D6: =D4/(D4+D5) -> 0 | E6: =E4/(E4+E5) -> 0 | F6: =F4/(F4+F5) -> 0 | G6: =G4/(G4+G5) -> 0 | H6: =H4/(H4+H5) -> 0 | I6: =I4/(I4+I5) -> 0 | ... AE6: =AE4/(AE4+AE5) -> 0.88871334 | AF6: =AF7 -> 1 | AG6: =AG7 -> 1 | AH6: =AH7 -> 1 | AI6: =AI7 -> 1 | AJ6: =AJ7 -> 1 | AK6: =AK7 -> 1 | AL6: =AL7 -> 1 | AM6: =AM7 -> 1 | ... BA6: =BA7 -> 1
A7: Goal Verden Share | B7: =B13 -> 0 | C7: =C13 -> 0 | D7: =D13 -> 0 | E7: =E13 -> 0 | F7: =F13 -> 0 | G7: =G13 -> 0 | H7: =H13 -> 0 | I7: =I13 -> 0 | ... BA7: =BA13 -> 1
A8: Unique Verden meals | B8: {=transpose(Overview!D3:D54)} -> 0 | C8: 0 | D8: 0 | E8: 0 | F8: 0 | G8: 0 | H8: 0 | I8: 0 | J8: 0 | K8: 0 | L8: 0 | M8: 0 | N8: 0 | O8: 0 | P8: 0 | Q8: 0 | R8: 0 | S8: 1 | T8: 3 | U8: 5 | V8: 8 | W8: 12 | X8: 17 | Y8: 19 | Z8: 20 | AA8: 21 | AB8: 24 | AC8: 24 | AD8: 24 | AE8: 25 | AF8: 30 | AG8: 30 | AH8: 30 | AI8: 30 | AJ8: 33 | AK8: 33 | AL8: 33 | AM8: 33 | AN8: 33 | AO8: 33 | AP8: 33 | AQ8: 33 | AR8: 33 | AS8: 33 | AT8: 33 | AU8: 33 | AV8: 33 | AW8: 33 | AX8: 36 | AY8: 36 | AZ8: 36 | BA8: 36
A10: Planned Split | B10: 2026-W01 | C10: 2026-W02 | D10: 2026-W03 | E10: 2026-W04 | F10: 2026-W05 | G10: 2026-W06 | H10: 2026-W07 | I10: 2026-W08 | J10: 2026-W09 | K10: 2026-W10 | L10: 2026-W11 | M10: 2026-W12 | N10: 2026-W13 | O10: 2026-W14 | P10: 2026-W15 | Q10: 2026-W16 | R10: 2026-W17 | S10: 2026-W18 | T10: 2026-W19 | U10: 2026-W20 | V10: 2026-W21 | W10: 2026-W22 | X10: 2026-W23 | Y10: 2026-W24 | Z10: 2026-W25 | AA10: 2026-W26 | AB10: 2026-W27 | AC10: 2026-W28 | AD10: 2026-W29 | AE10: 2026-W30 | AF10: 2026-W31 | AG10: 2026-W32 | AH10: 2026-W33 | AI10: 2026-W34 | AJ10: 2026-W35 | AK10: 2026-W36 | AL10: 2026-W37 | AM10: 2026-W38 | AN10: 2026-W39 | AO10: 2026-W40 | AP10: 2026-W41 | AQ10: 2026-W42 | AR10: 2026-W43 | AS10: 2026-W44 | AT10: 2026-W45 | AU10: 2026-W46 | AV10: 2026-W47 | AW10: 2026-W48 | AX10: 2026-W49 | AY10: 2026-W50 | AZ10: 2026-W51 | BA10: 2026-W52
A11: Verden Meal Volume | B11: =B32*B13 -> 0 | C11: =C32*C13 -> 0 | D11: =D32*D13 -> 0 | E11: =E32*E13 -> 0 | F11: =F32*F13 -> 0 | G11: =G32*G13 -> 0 | H11: =H32*H13 -> 0 | I11: =I32*I13 -> 0 | ... BA11: =BA32*BA13 -> 74599.904
A12: Coman Meal Volume | B12: =B32-B11 -> 50424 | C12: =C32-C11 -> 72317 | D12: =D32-D11 -> 97195 | E12: =E32-E11 -> 104810 | F12: =F32-F11 -> 105534 | G12: =G32-G11 -> 115011 | H12: =H32-H11 -> 114124 | I12: =I32-I11 -> 113188 | ... BA12: =BA32-BA11 -> 0
B13: 0 | C13: 0 | D13: 0 | E13: 0 | F13: 0 | G13: 0 | H13: 0 | I13: 0 | J13: 0 | K13: 0 | L13: 0 | M13: 0 | N13: 0 | O13: 0 | P13: 0 | Q13: 0 | R13: 0 | S13: 0 | T13: 0.08 | U13: 0.2 | V13: 0.31 | W13: 0.45 | X13: 0.6 | Y13: 0.65 | Z13: 0.75 | AA13: 0.8 | AB13: 0.85 | AC13: 0.9 | AD13: 0.9 | AE13: 0.9 | AF13: 1 | AG13: 1 | AH13: 1 | AI13: 1 | AJ13: 1 | AK13: 1 | AL13: 1 | AM13: 1 | AN13: 1 | AO13: 1 | AP13: 1 | AQ13: 1 | AR13: 1 | AS13: 1 | AT13: 1 | AU13: 1 | AV13: 1 | AW13: 1 | AX13: 1 | AY13: 1 | AZ13: 1 | BA13: 1
A14: Total Volume | B14: =B11+B12 -> 50424 | C14: =C11+C12 -> 72317 | D14: =D11+D12 -> 97195 | E14: =E11+E12 -> 104810 | F14: =F11+F12 -> 105534 | G14: =G11+G12 -> 115011 | H14: =H11+H12 -> 114124 | I14: =I11+I12 -> 113188 | ... BA14: =BA11+BA12 -> 74599.904
A16: Total Boxes | B16: 2026-W01 | C16: 2026-W02 | D16: 2026-W03 | E16: 2026-W04 | F16: 2026-W05 | G16: 2026-W06 | H16: 2026-W07 | I16: 2026-W08 | J16: 2026-W09 | K16: 2026-W10 | L16: 2026-W11 | M16: 2026-W12 | N16: 2026-W13 | O16: 2026-W14 | P16: 2026-W15 | Q16: 2026-W16 | R16: 2026-W17 | S16: 2026-W18 | T16: 2026-W19 | U16: 2026-W20 | V16: 2026-W21 | W16: 2026-W22 | X16: 2026-W23 | Y16: 2026-W24 | Z16: 2026-W25 | AA16: 2026-W26 | AB16: 2026-W27 | AC16: 2026-W28 | AD16: 2026-W29 | AE16: 2026-W30 | AF16: 2026-W31 | AG16: 2026-W32 | AH16: 2026-W33 | AI16: 2026-W34 | AJ16: 2026-W35 | AK16: 2026-W36 | AL16: 2026-W37 | AM16: 2026-W38 | AN16: 2026-W39 | AO16: 2026-W40 | AP16: 2026-W41 | AQ16: 2026-W42 | AR16: 2026-W43 | AS16: 2026-W44 | AT16: 2026-W45 | AU16: 2026-W46 | AV16: 2026-W47 | AW16: 2026-W48 | AX16: 2026-W49 | AY16: 2026-W50 | AZ16: 2026-W51 | BA16: 2026-W52
A17: BE | B17: 1712 | C17: 2563 | D17: 2910 | E17: 2967 | F17: 2992 | G17: 3127 | H17: 3127 | I17: 2958 | J17: 3084 | K17: 3240 | L17: 3305 | M17: 3198 | N17: 2940 | O17: 3127 | P17: 2577 | Q17: 2637 | R17: 2800 | S17: 2871 | T17: ='Budget Volumes'!AF4 -> 2862 | U17: ='Budget Volumes'!AG4 -> 3138 | V17: ='Budget Volumes'!AH4 -> 3043 | W17: ='Budget Volumes'!AI4 -> 3152 | X17: ='Budget Volumes'!AJ4 -> 3393 | Y17: ='Budget Volumes'!AK4 -> 3373 | Z17: ='Budget Volumes'!AL4 -> 3294 | AA17: ='Budget Volumes'!AM4 -> 3134 | ... BA17: ='Budget Volumes'!BM4 -> 2546
A18: NL | B18: 1994 | C18: 2845 | D18: 3469 | E18: 3776 | F18: 4035 | G18: 4428 | H18: 4421 | I18: 4449 | J18: 4487 | K18: 4670 | L18: 4644 | M18: 4648 | N18: 4357 | O18: 4670 | P18: 3959 | Q18: 4022 | R18: 4273 | S18: 4342 | T18: ='Budget Volumes'!AF5 -> 4238 | U18: ='Budget Volumes'!AG5 -> 4504 | V18: ='Budget Volumes'!AH5 -> 4426 | W18: ='Budget Volumes'!AI5 -> 4310 | X18: ='Budget Volumes'!AJ5 -> 4366 | Y18: ='Budget Volumes'!AK5 -> 4226 | Z18: ='Budget Volumes'!AL5 -> 4331 | AA18: ='Budget Volumes'!AM5 -> 4317 | ... BA18: ='Budget Volumes'!BM5 -> 3422
A19: SE | B19: 790 | C19: 1130 | D19: 1865 | E19: 2099 | F19: 2191 | G19: 2370 | H19: 2280 | I19: 2403 | J19: 2246 | K19: 2112 | L19: 2073 | M19: 2076 | N19: 2057 | O19: 1952 | P19: 1724 | Q19: 1748 | R19: 1830 | S19: 1897 | T19: ='Budget Volumes'!AF8 -> 1653 | U19: ='Budget Volumes'!AG8 -> 1702 | V19: ='Budget Volumes'!AH8 -> 1698 | W19: ='Budget Volumes'!AI8 -> 1715 | X19: ='Budget Volumes'!AJ8 -> 1788 | Y19: ='Budget Volumes'!AK8 -> 1740 | Z19: ='Budget Volumes'!AL8 -> 1599 | AA19: ='Budget Volumes'!AM8 -> 1591 | ... BA19: ='Budget Volumes'!BM8 -> 1322
A20: DK | B20: 1003 | C20: 1505 | D20: 2061 | E20: 2207 | F20: 2160 | G20: 2277 | H20: 2290 | I20: 2334 | J20: 2365 | K20: 2131 | L20: 2212 | M20: 2110 | N20: 2021 | O20: 1726 | P20: 1688 | Q20: 1680 | R20: 1740 | S20: 1888 | T20: ='Budget Volumes'!AF7 -> 1758 | U20: ='Budget Volumes'!AG7 -> 1759 | V20: ='Budget Volumes'!AH7 -> 1736 | W20: ='Budget Volumes'!AI7 -> 1734 | X20: ='Budget Volumes'!AJ7 -> 1826 | Y20: ='Budget Volumes'!AK7 -> 1834 | Z20: ='Budget Volumes'!AL7 -> 1779 | AA20: ='Budget Volumes'!AM7 -> 1739 | ... BA20: ='Budget Volumes'!BM7 -> 1209
A21: DE | B21: 1638 | C21: 2271 | D21: 2920 | E21: 3210 | F21: 3235 | G21: 3455 | H21: 3507 | I21: 3423 | J21: 3351 | K21: 3396 | L21: 3323 | M21: 3125 | N21: 2952 | O21: 2792 | P21: 2593 | Q21: 2590 | R21: 2775 | S21: 2798 | T21: ='Budget Volumes'!AF6 -> 2492 | U21: ='Budget Volumes'!AG6 -> 2585 | V21: ='Budget Volumes'!AH6 -> 2539 | W21: ='Budget Volumes'!AI6 -> 2357 | X21: ='Budget Volumes'!AJ6 -> 2428 | Y21: ='Budget Volumes'!AK6 -> 2304 | Z21: ='Budget Volumes'!AL6 -> 2381 | AA21: ='Budget Volumes'!AM6 -> 2292 | ... BA21: ='Budget Volumes'!BM6 -> 1804
A22: FR | B22: ='Budget Volumes'!N9 -> 0 | C22: ='Budget Volumes'!O9 -> 0 | D22: ='Budget Volumes'!P9 -> 0 | E22: ='Budget Volumes'!Q9 -> 0 | F22: ='Budget Volumes'!R9 -> 0 | G22: ='Budget Volumes'!S9 -> 0 | H22: ='Budget Volumes'!T9 -> 0 | I22: ='Budget Volumes'!U9 -> 0 | ... BA22: ='Budget Volumes'!BM9 -> 0
A23: Total | B23: =sum(B17:B22) -> 7137 | C23: =sum(C17:C22) -> 10314 | D23: =sum(D17:D22) -> 13225 | E23: =sum(E17:E22) -> 14259 | F23: =sum(F17:F22) -> 14613 | G23: =sum(G17:G22) -> 15657 | H23: =sum(H17:H22) -> 15625 | I23: =sum(I17:I22) -> 15567 | ... BA23: =sum(BA17:BA22) -> 10303
A25: Total Meals | B25: 2026-W01 | C25: 2026-W02 | D25: 2026-W03 | E25: 2026-W04 | F25: 2026-W05 | G25: 2026-W06 | H25: 2026-W07 | I25: 2026-W08 | J25: 2026-W09 | K25: 2026-W10 | L25: 2026-W11 | M25: 2026-W12 | N25: 2026-W13 | O25: 2026-W14 | P25: 2026-W15 | Q25: 2026-W16 | R25: 2026-W17 | S25: 2026-W18 | T25: 2026-W19 | U25: 2026-W20 | V25: 2026-W21 | W25: 2026-W22 | X25: 2026-W23 | Y25: 2026-W24 | Z25: 2026-W25 | AA25: 2026-W26 | AB25: 2026-W27 | AC25: 2026-W28 | AD25: 2026-W29 | AE25: 2026-W30 | AF25: 2026-W31 | AG25: 2026-W32 | AH25: 2026-W33 | AI25: 2026-W34 | AJ25: 2026-W35 | AK25: 2026-W36 | AL25: 2026-W37 | AM25: 2026-W38 | AN25: 2026-W39 | AO25: 2026-W40 | AP25: 2026-W41 | AQ25: 2026-W42 | AR25: 2026-W43 | AS25: 2026-W44 | AT25: 2026-W45 | AU25: 2026-W46 | AV25: 2026-W47 | AW25: 2026-W48 | AX25: 2026-W49 | AY25: 2026-W50 | AZ25: 2026-W51 | BA25: 2026-W52
A26: BE | B26: 10563 | C26: 15788 | D26: 18886 | E26: 19226 | F26: 19418 | G26: 20138 | H26: 20138 | I26: 18990 | J26: 19614 | K26: 20866 | L26: 21218 | M26: 20414 | N26: 18769 | O26: 19652 | P26: 16288 | Q26: 16666 | R26: 17594 | S26: 18043 | T26: ='Budget Volumes'!AF12 -> 20107.748 | U26: ='Budget Volumes'!AG12 -> 22046.86 | V26: ='Budget Volumes'!AH12 -> 21379.412 | W26: ='Budget Volumes'!AI12 -> 22145.221 | X26: ='Budget Volumes'!AJ12 -> 23838.431 | Y26: ='Budget Volumes'!AK12 -> 23697.915 | Z26: ='Budget Volumes'!AL12 -> 23142.929 | AA26: ='Budget Volumes'!AM12 -> 22019.685 | ... BA26: ='Budget Volumes'!BM12 -> 18476.948
A27: NL | B27: 13838 | C27: 19716 | D27: 24561 | E27: 26659 | F27: 26913 | G27: 31395 | H27: 31345 | I27: 31766 | J27: 31723 | K27: 32924 | L27: 32787 | M27: 32817 | N27: 30745 | O27: 32738 | P27: 27240 | Q27: 27352 | R27: 29468 | S27: 29782 | T27: ='Budget Volumes'!AF13 -> 26827.851 | U27: ='Budget Volumes'!AG13 -> 28511.714 | V27: ='Budget Volumes'!AH13 -> 28017.949 | W27: ='Budget Volumes'!AI13 -> 27283.634 | X27: ='Budget Volumes'!AJ13 -> 27638.131 | Y27: ='Budget Volumes'!AK13 -> 26751.888 | Z27: ='Budget Volumes'!AL13 -> 27416.655 | AA27: ='Budget Volumes'!AM13 -> 27328.857 | ... BA27: ='Budget Volumes'!BM13 -> 22374.616
A28: SE | B28: 6383 | C28: 9142 | D28: 15517 | E28: 17674 | F28: 17944 | G28: 19481 | H28: 18468 | I28: 19056 | J28: 17474 | K28: 16220 | L28: 16128 | M28: 15996 | N28: 15845 | O28: 14994 | P28: 13790 | Q28: 13928 | R28: 14056 | S28: 14565 | T28: ='Budget Volumes'!AF16 -> 12984.594 | U28: ='Budget Volumes'!AG16 -> 13369.498 | V28: ='Budget Volumes'!AH16 -> 13338.077 | W28: ='Budget Volumes'!AI16 -> 13471.615 | X28: ='Budget Volumes'!AJ16 -> 14045.042 | Y28: ='Budget Volumes'!AK16 -> 13667.994 | Z28: ='Budget Volumes'!AL16 -> 12560.486 | AA28: ='Budget Volumes'!AM16 -> 12498.279 | ... BA28: ='Budget Volumes'!BM16 -> 10743.873
A29: DK | B29: 6520 | C29: 9662 | D29: 14345 | E29: 15250 | F29: 14861 | G29: 15666 | H29: 15801 | I29: 15684 | J29: 16011 | K29: 14086 | L29: 14798 | M29: 14038 | N29: 13441 | O29: 11734 | P29: 11464 | Q29: 11013 | R29: 11407 | S29: 12376 | T29: ='Budget Volumes'!AF15 -> 11762.426 | U29: ='Budget Volumes'!AG15 -> 11769.117 | V29: ='Budget Volumes'!AH15 -> 11615.229 | W29: ='Budget Volumes'!AI15 -> 11601.847 | X29: ='Budget Volumes'!AJ15 -> 12217.401 | Y29: ='Budget Volumes'!AK15 -> 12270.927 | Z29: ='Budget Volumes'!AL15 -> 11902.933 | AA29: ='Budget Volumes'!AM15 -> 11635.649 | ... BA29: ='Budget Volumes'!BM15 -> 8341.3746
A30: DE | B30: 13120 | C30: 18009 | D30: 23886 | E30: 26001 | F30: 26398 | G30: 28331 | H30: 28372 | I30: 27692 | J30: 26774 | K30: 27372 | L30: 26621 | M30: 25038 | N30: 23649 | O30: 22044 | P30: 20744 | Q30: 20643 | R30: 21910 | S30: 22089 | T30: ='Budget Volumes'!AF14 -> 19881.425 | U30: ='Budget Volumes'!AG14 -> 20623.389 | V30: ='Budget Volumes'!AH14 -> 20256.396 | W30: ='Budget Volumes'!AI14 -> 18804.382 | X30: ='Budget Volumes'!AJ14 -> 19370.827 | Y30: ='Budget Volumes'!AK14 -> 18381.542 | Z30: ='Budget Volumes'!AL14 -> 18995.856 | AA30: ='Budget Volumes'!AM14 -> 18285.805 | ... BA30: ='Budget Volumes'!BM14 -> 14663.092
A31: FR | B31: ='Budget Volumes'!N17 -> 0 | C31: ='Budget Volumes'!O17 -> 0 | D31: ='Budget Volumes'!P17 -> 0 | E31: ='Budget Volumes'!Q17 -> 0 | F31: ='Budget Volumes'!R17 -> 0 | G31: ='Budget Volumes'!S17 -> 0 | H31: ='Budget Volumes'!T17 -> 0 | I31: ='Budget Volumes'!U17 -> 0 | ... BA31: ='Budget Volumes'!BM17 -> 0
A32: Total | B32: =sum(B26:B31) -> 50424 | C32: =sum(C26:C31) -> 72317 | D32: =sum(D26:D31) -> 97195 | E32: =sum(E26:E31) -> 104810 | F32: =sum(F26:F31) -> 105534 | G32: =sum(G26:G31) -> 115011 | H32: =sum(H26:H31) -> 114124 | I32: =sum(I26:I31) -> 113188 | ... BA32: =sum(BA26:BA31) -> 74599.904
A34: BENL Volume | B34: 2026-W01 | C34: 2026-W02 | D34: 2026-W03 | E34: 2026-W04 | F34: 2026-W05 | G34: 2026-W06 | H34: 2026-W07 | I34: 2026-W08 | J34: 2026-W09 | K34: 2026-W10 | L34: 2026-W11 | M34: 2026-W12 | N34: 2026-W13 | O34: 2026-W14 | P34: 2026-W15 | Q34: 2026-W16 | R34: 2026-W17 | S34: 2026-W18 | T34: 2026-W19 | U34: 2026-W20 | V34: 2026-W21 | W34: 2026-W22 | X34: 2026-W23 | Y34: 2026-W24 | Z34: 2026-W25 | AA34: 2026-W26 | AB34: 2026-W27 | AC34: 2026-W28 | AD34: 2026-W29 | AE34: 2026-W30 | AF34: 2026-W31 | AG34: 2026-W32 | AH34: 2026-W33 | AI34: 2026-W34 | AJ34: 2026-W35 | AK34: 2026-W36 | AL34: 2026-W37 | AM34: 2026-W38 | AN34: 2026-W39 | AO34: 2026-W40 | AP34: 2026-W41 | AQ34: 2026-W42 | AR34: 2026-W43 | AS34: 2026-W44 | AT34: 2026-W45 | AU34: 2026-W46 | AV34: 2026-W47 | AW34: 2026-W48 | AX34: 2026-W49 | AY34: 2026-W50 | AZ34: 2026-W51 | BA34: 2026-W52
A35: Verden Meal Volume | B35: =(B26+B27)*SUMIF('Slot Selection'!K3:K32,TRUE,'Slot Selection'!$D$3:$D$32) -> 0 | C35: =(C26+C27)*SUMIF('Slot Selection'!L3:L32,TRUE,'Slot Selection'!$D$3:$D$32) -> 0 | D35: =(D26+D27)*SUMIF('Slot Selection'!M3:M32,TRUE,'Slot Selection'!$D$3:$D$32) -> 0 | E35: =(E26+E27)*SUMIF('Slot Selection'!N3:N32,TRUE,'Slot Selection'!$D$3:$D$32) -> 0 | F35: =(F26+F27)*SUMIF('Slot Selection'!O3:O32,TRUE,'Slot Selection'!$D$3:$D$32) -> 0 | G35: =(G26+G27)*SUMIF('Slot Selection'!P3:P32,TRUE,'Slot Selection'!$D$3:$D$32) -> 0 | H35: =(H26+H27)*SUMIF('Slot Selection'!Q3:Q32,TRUE,'Slot Selection'!$D$3:$D$32) -> 0 | I35: =(I26+I27)*SUMIF('Slot Selection'!R3:R32,TRUE,'Slot Selection'!$D$3:$D$32) -> 0 | ... M35: =(M26+M27)*SUMIF('Slot Selection'!V3:V32,TRUE,'Slot Selection'!$D$3:$D$32) -> 0 | N35: =(N26+N27)*SUMIF('Slot Selection'!W3:W38,TRUE,'Slot Selection'!$D$3:$D$38) -> 0 | O35: =(O26+O27)*SUMIF('Slot Selection'!X3:X38,TRUE,'Slot Selection'!$E$3:$E$38) -> 0 | P35: =(P26+P27)*SUMIF('Slot Selection'!Y3:Y38,TRUE,'Slot Selection'!$E$3:$E$38) -> 0 | Q35: =(Q26+Q27)*SUMIF('Slot Selection'!Z3:Z38,TRUE,'Slot Selection'!$E$3:$E$38) -> 0 | R35: =(R26+R27)*SUMIF('Slot Selection'!AA3:AA38,TRUE,'Slot Selection'!$D$3:$D$38) -> 0 | S35: =(S26+S27)*SUMIF('Slot Selection'!AB3:AB38,TRUE,'Slot Selection'!$D$3:$D$38) -> 1434.75 | T35: =(T26+T27)*SUMIF('Slot Selection'!AC3:AC38,TRUE,'Slot Selection'!$E$3:$E$38) -> 0 | U35: =(U26+U27)*SUMIF('Slot Selection'!AD3:AD38,TRUE,'Slot Selection'!$E$3:$E$38) -> 10592.021 | V35: =(V26+V27)*SUMIF('Slot Selection'!AE3:AE38,TRUE,'Slot Selection'!$E$3:$E$38) -> 12122.112 | W35: =(W26+W27)*SUMIF('Slot Selection'!AF3:AF38,TRUE,'Slot Selection'!$E$3:$E$38) -> 24071.852 | X35: =(X26+X27)*SUMIF('Slot Selection'!AG3:AG38,TRUE,'Slot Selection'!$F$3:$F$38) -> 32466.267 | Y35: =(Y26+Y27)*SUMIF('Slot Selection'!AH3:AH38,TRUE,'Slot Selection'!$F$3:$F$38) -> 34840.634 | Z35: =(Z26+Z27)*SUMIF('Slot Selection'!AI3:AI38,TRUE,'Slot Selection'!$F$3:$F$38) -> 40548.786 | AA35: =(AA26+AA27)*SUMIF('Slot Selection'!AJ3:AJ38,TRUE,'Slot Selection'!$F$3:$F$38) -> 42696.358 | AB35: =(AB26+AB27)*SUMIF('Slot Selection'!AK3:AK38,TRUE,'Slot Selection'!$F$3:$F$38) -> 42472.217 | AC35: =(AC26+AC27)*SUMIF('Slot Selection'!AL3:AL38,TRUE,'Slot Selection'!$F$3:$F$38) -> 40238.767 | AD35: =(AD26+AD27)*SUMIF('Slot Selection'!AM3:AM38,TRUE,'Slot Selection'!$F$3:$F$38) -> 37431.378 | AE35: =(AE26+AE27)*SUMIF('Slot Selection'!AN3:AN38,TRUE,'Slot Selection'!$F$3:$F$38) -> 36628.379 | AF35: =(AF26+AF27) -> 40909.451 | AG35: =(AG26+AG27) -> 41336.147 | AH35: =(AH26+AH27) -> 42674.209 | AI35: =(AI26+AI27) -> 48091.944 | AJ35: =(AJ26+AJ27) -> 50209.637 | AK35: =(AK26+AK27) -> 53620.339 | AL35: =(AL26+AL27) -> 60151.874 | AM35: =(AM26+AM27) -> 65915.935 | ... BA35: =(BA26+BA27) -> 40851.564
A36: Coman Meal Volume | B36: =(B26+B27)-B35 -> 24401 | C36: =(C26+C27)-C35 -> 35504 | D36: =(D26+D27)-D35 -> 43447 | E36: =(E26+E27)-E35 -> 45885 | F36: =(F26+F27)-F35 -> 46331 | G36: =(G26+G27)-G35 -> 51533 | H36: =(H26+H27)-H35 -> 51483 | I36: =(I26+I27)-I35 -> 50756 | ... BA36: =(BA26+BA27)-BA35 -> 0
A38: DKSE Volume | B38: 2026-W01 | C38: 2026-W02 | D38: 2026-W03 | E38: 2026-W04 | F38: 2026-W05 | G38: 2026-W06 | H38: 2026-W07 | I38: 2026-W08 | J38: 2026-W09 | K38: 2026-W10 | L38: 2026-W11 | M38: 2026-W12 | N38: 2026-W13 | O38: 2026-W14 | P38: 2026-W15 | Q38: 2026-W16 | R38: 2026-W17 | S38: 2026-W18 | T38: 2026-W19 | U38: 2026-W20 | V38: 2026-W21 | W38: 2026-W22 | X38: 2026-W23 | Y38: 2026-W24 | Z38: 2026-W25 | AA38: 2026-W26 | AB38: 2026-W27 | AC38: 2026-W28 | AD38: 2026-W29 | AE38: 2026-W30 | AF38: 2026-W31 | AG38: 2026-W32 | AH38: 2026-W33 | AI38: 2026-W34 | AJ38: 2026-W35 | AK38: 2026-W36 | AL38: 2026-W37 | AM38: 2026-W38 | AN38: 2026-W39 | AO38: 2026-W40 | AP38: 2026-W41 | AQ38: 2026-W42 | AR38: 2026-W43 | AS38: 2026-W44 | AT38: 2026-W45 | AU38: 2026-W46 | AV38: 2026-W47 | AW38: 2026-W48 | AX38: 2026-W49 | AY38: 2026-W50 | AZ38: 2026-W51 | BA38: 2026-W52
A39: Verden Meal Volume | B39: =(B28+B29)*SUMIF('Slot Selection'!K81:K116,TRUE,'Slot Selection'!$D$81:$D$116) -> 0 | C39: =(C28+C29)*SUMIF('Slot Selection'!L81:L116,TRUE,'Slot Selection'!$D$81:$D$116) -> 0 | D39: =(D28+D29)*SUMIF('Slot Selection'!M81:M116,TRUE,'Slot Selection'!$D$81:$D$116) -> 0 | E39: =(E28+E29)*SUMIF('Slot Selection'!N81:N116,TRUE,'Slot Selection'!$D$81:$D$116) -> 0 | F39: =(F28+F29)*SUMIF('Slot Selection'!O81:O116,TRUE,'Slot Selection'!$D$81:$D$116) -> 0 | G39: =(G28+G29)*SUMIF('Slot Selection'!P81:P116,TRUE,'Slot Selection'!$D$81:$D$116) -> 0 | H39: =(H28+H29)*SUMIF('Slot Selection'!Q81:Q116,TRUE,'Slot Selection'!$D$81:$D$116) -> 0 | I39: =(I28+I29)*SUMIF('Slot Selection'!R81:R116,TRUE,'Slot Selection'!$D$81:$D$116) -> 0 | ... N39: =(N28+N29)*SUMIF('Slot Selection'!W81:W116,TRUE,'Slot Selection'!$D$81:$D$116) -> 0 | O39: =(O28+O29)*SUMIF('Slot Selection'!X81:X116,TRUE,'Slot Selection'!$E$81:$E$116) -> 0 | P39: =(P28+P29)*SUMIF('Slot Selection'!Y81:Y116,TRUE,'Slot Selection'!$E$81:$E$116) -> 0 | Q39: =(Q28+Q29)*SUMIF('Slot Selection'!Z81:Z116,TRUE,'Slot Selection'!$E$81:$E$116) -> 0 | R39: =(R28+R29)*SUMIF('Slot Selection'!AA81:AA116,TRUE,'Slot Selection'!$D$81:$D$116) -> 0 | S39: =(S28+S29)*SUMIF('Slot Selection'!AB81:AB116,TRUE,'Slot Selection'!$D$81:$D$116) -> 808.23 | T39: =(T28+T29)*SUMIF('Slot Selection'!AC81:AC116,TRUE,'Slot Selection'!$E$81:$E$116) -> 4402.495 | U39: =(U28+U29)*SUMIF('Slot Selection'!AD81:AD116,TRUE,'Slot Selection'!$E$81:$E$116) -> 5266.5398 | V39: =(V28+V29)*SUMIF('Slot Selection'!AE81:AE116,TRUE,'Slot Selection'!$E$81:$E$116) -> 9809.1445 | W39: =(W28+W29)*SUMIF('Slot Selection'!AF81:AF116,TRUE,'Slot Selection'!$E$81:$E$116) -> 12210.776 | X39: =(X28+X29)*SUMIF('Slot Selection'!AG81:AG116,TRUE,'Slot Selection'!$F$81:$F$116) -> 16563.723 | Y39: =(Y28+Y29)*SUMIF('Slot Selection'!AH81:AH116,TRUE,'Slot Selection'!$F$81:$F$116) -> 17913.419 | Z39: =(Z28+Z29)*SUMIF('Slot Selection'!AI81:AI116,TRUE,'Slot Selection'!$F$81:$F$116) -> 19619.662 | AA39: =(AA28+AA29)*SUMIF('Slot Selection'!AJ81:AJ116,TRUE,'Slot Selection'!$F$81:$F$116) -> 20880.674 | AB39: =(AB28+AB29)*SUMIF('Slot Selection'!AK81:AK116,TRUE,'Slot Selection'!$F$81:$F$116) -> 20320.89 | AC39: =(AC28+AC29)*SUMIF('Slot Selection'!AL81:AL116,TRUE,'Slot Selection'!$F$81:$F$116) -> 19248.718 | AD39: =(AD28+AD29)*SUMIF('Slot Selection'!AM81:AM116,TRUE,'Slot Selection'!$F$81:$F$116) -> 17504.504 | AE39: =(AE28+AE29)*SUMIF('Slot Selection'!AN81:AN116,TRUE,'Slot Selection'!$F$81:$F$116) -> 17345.784 | AF39: =(AF28+AF29) -> 19951.972 | AG39: =(AG28+AG29) -> 22107.239 | AH39: =(AH28+AH29) -> 25337.513 | AI39: =(AI28+AI29) -> 28679.406 | AJ39: =(AJ28+AJ29) -> 30681.838 | AK39: =(AK28+AK29) -> 32703.729 | AL39: =(AL28+AL29) -> 35989.591 | AM39: =(AM28+AM29) -> 38834.757 | ... BA39: =(BA28+BA29) -> 19085.247
A40: Coman Meal Volume | B40: =(B28+B29)-B39 -> 12903 | C40: =(C28+C29)-C39 -> 18804 | D40: =(D28+D29)-D39 -> 29862 | E40: =(E28+E29)-E39 -> 32924 | F40: =(F28+F29)-F39 -> 32805 | G40: =(G28+G29)-G39 -> 35147 | H40: =(H28+H29)-H39 -> 34269 | I40: =(I28+I29)-I39 -> 34740 | ... BA40: =(BA28+BA29)-BA39 -> 0
A42: DE Volume | B42: 2026-W01 | C42: 2026-W02 | D42: 2026-W03 | E42: 2026-W04 | F42: 2026-W05 | G42: 2026-W06 | H42: 2026-W07 | I42: 2026-W08 | J42: 2026-W09 | K42: 2026-W10 | L42: 2026-W11 | M42: 2026-W12 | N42: 2026-W13 | O42: 2026-W14 | P42: 2026-W15 | Q42: 2026-W16 | R42: 2026-W17 | S42: 2026-W18 | T42: 2026-W19 | U42: 2026-W20 | V42: 2026-W21 | W42: 2026-W22 | X42: 2026-W23 | Y42: 2026-W24 | Z42: 2026-W25 | AA42: 2026-W26 | AB42: 2026-W27 | AC42: 2026-W28 | AD42: 2026-W29 | AE42: 2026-W30 | AF42: 2026-W31 | AG42: 2026-W32 | AH42: 2026-W33 | AI42: 2026-W34 | AJ42: 2026-W35 | AK42: 2026-W36 | AL42: 2026-W37 | AM42: 2026-W38 | AN42: 2026-W39 | AO42: 2026-W40 | AP42: 2026-W41 | AQ42: 2026-W42 | AR42: 2026-W43 | AS42: 2026-W44 | AT42: 2026-W45 | AU42: 2026-W46 | AV42: 2026-W47 | AW42: 2026-W48 | AX42: 2026-W49 | AY42: 2026-W50 | AZ42: 2026-W51 | BA42: 2026-W52
A43: Verden Meal Volume | B43: =(B30)*SUMIF('Slot Selection'!K42:K71,TRUE,'Slot Selection'!$D$42:$D$77) -> 0 | C43: =(C30)*SUMIF('Slot Selection'!L42:L71,TRUE,'Slot Selection'!$D$42:$D$77) -> 0 | D43: =(D30)*SUMIF('Slot Selection'!M42:M71,TRUE,'Slot Selection'!$D$42:$D$77) -> 0 | E43: =(E30)*SUMIF('Slot Selection'!N42:N71,TRUE,'Slot Selection'!$D$42:$D$77) -> 0 | F43: =(F30)*SUMIF('Slot Selection'!O42:O71,TRUE,'Slot Selection'!$D$42:$D$77) -> 0 | G43: =(G30)*SUMIF('Slot Selection'!P42:P71,TRUE,'Slot Selection'!$D$42:$D$77) -> 0 | H43: =(H30)*SUMIF('Slot Selection'!Q42:Q71,TRUE,'Slot Selection'!$D$42:$D$77) -> 0 | I43: =(I30)*SUMIF('Slot Selection'!R42:R71,TRUE,'Slot Selection'!$D$42:$D$77) -> 0 | ... N43: =(N30)*SUMIF('Slot Selection'!W42:W71,TRUE,'Slot Selection'!$D$42:$D$77) -> 0 | O43: =(O30)*SUMIF('Slot Selection'!X42:X71,TRUE,'Slot Selection'!$E$42:$E$77) -> 0 | P43: =(P30)*SUMIF('Slot Selection'!Y42:Y71,TRUE,'Slot Selection'!$E$42:$E$77) -> 0 | Q43: =(Q30)*SUMIF('Slot Selection'!Z42:Z71,TRUE,'Slot Selection'!$E$42:$E$77) -> 0 | R43: =(R30)*SUMIF('Slot Selection'!AA42:AA71,TRUE,'Slot Selection'!$D$42:$D$77) -> 0 | S43: =(S30)*SUMIF('Slot Selection'!AB42:AB71,TRUE,'Slot Selection'!$D$42:$D$77) -> 662.67 | T43: =(T30)*SUMIF('Slot Selection'!AC42:AC71,TRUE,'Slot Selection'!$E$42:$E$77) -> 3536.9055 | U43: =(U30)*SUMIF('Slot Selection'!AD42:AD71,TRUE,'Slot Selection'!$E$42:$E$77) -> 4320.5999 | V43: =(V30)*SUMIF('Slot Selection'!AE42:AE71,TRUE,'Slot Selection'!$E$42:$E$77) -> 7962.7892 | W43: =(W30)*SUMIF('Slot Selection'!AF42:AF71,TRUE,'Slot Selection'!$E$42:$E$77) -> 9157.7339 | X43: =(X30)*SUMIF('Slot Selection'!AG42:AG71,TRUE,'Slot Selection'!$F$42:$F$77) -> 12217.18 | Y43: =(Y30)*SUMIF('Slot Selection'!AH42:AH71,TRUE,'Slot Selection'!$F$42:$F$77) -> 12694.293 | Z43: =(Z30)*SUMIF('Slot Selection'!AI42:AI71,TRUE,'Slot Selection'!$F$42:$F$77) -> 15234.677 | AA43: =(AA30)*SUMIF('Slot Selection'!AJ42:AJ71,TRUE,'Slot Selection'!$F$42:$F$77) -> 15820.879 | AB43: =(AB30)*SUMIF('Slot Selection'!AK42:AK71,TRUE,'Slot Selection'!$F$42:$F$77) -> 16666.036 | AC43: =(AC30)*SUMIF('Slot Selection'!AL42:AL71,TRUE,'Slot Selection'!$F$42:$F$77) -> 15943.841 | AD43: =(AD30)*SUMIF('Slot Selection'!AM42:AM71,TRUE,'Slot Selection'!$F$42:$F$77) -> 15506.358 | AE43: =(AE30)*SUMIF('Slot Selection'!AN42:AN71,TRUE,'Slot Selection'!$F$42:$F$77) -> 14641.924 | AF43: =(AF30) -> 16429.427 | AG43: =(AG30) -> 15819.443 | AH43: =(AH30) -> 16782.575 | AI43: =(AI30) -> 17938.334 | AJ43: =(AJ30) -> 18588.448 | AK43: =(AK30) -> 18805.152 | AL43: =(AL30) -> 20899.964 | AM43: =(AM30) -> 23725.152 | ... BA43: =(BA30) -> 14663.092
A44: Coman Meal Volume | B44: =B30-B43 -> 13120 | C44: =C30-C43 -> 18009 | D44: =D30-D43 -> 23886 | E44: =E30-E43 -> 26001 | F44: =F30-F43 -> 26398 | G44: =G30-G43 -> 28331 | H44: =H30-H43 -> 28372 | I44: =I30-I43 -> 27692 | ... BA44: =BA30-BA43 -> 0

Sheet Slot Selection
A1: BENL | K1: 2026-M01 | L1: 2026-M01 | M1: 2026-M01 | N1: 2026-M01 | O1: 2026-M01 | P1: 2026-M02 | Q1: 2026-M02 | R1: 2026-M02 | S1: 2026-M02 | T1: 2026-M03 | U1: 2026-M03 | V1: 2026-M03 | W1: 2026-M03 | X1: 2026-M04 | Y1: 2026-M04 | Z1: 2026-M04 | AA1: 2026-M04 | AB1: 2026-M04 | AC1: 2026-M05 | AD1: 2026-M05 | AE1: 2026-M05 | AF1: 2026-M05 | AG1: 2026-M06 | AH1: 2026-M06 | AI1: 2026-M06 | AJ1: 2026-M06 | AK1: 2026-M07 | AL1: 2026-M07 | AM1: 2026-M07 | AN1: 2026-M07 | AO1: 2026-M07 | AP1: 2026-M08 | AQ1: 2026-M08 | AR1: 2026-M08 | AS1: 2026-M08 | AT1: 2026-M09 | AU1: 2026-M09 | AV1: 2026-M09 | AW1: 2026-M09 | AX1: 2026-M10 | AY1: 2026-M10 | AZ1: 2026-M10 | BA1: 2026-M10 | BB1: 2026-M10 | BC1: 2026-M11 | BD1: 2026-M11 | BE1: 2026-M11 | BF1: 2026-M11 | BG1: 2026-M12 | BH1: 2026-M12 | BI1: 2026-M12 | BJ1: 2026-M12
A2: Slot | B2: Protein | C2: Preference | D2: 18 | E2: 21 | F2: 24 | G2: 27 | H2: 30 | I2: 33 | J2: 36 | K2: 2026-W01 | L2: 2026-W02 | M2: 2026-W03 | N2: 2026-W04 | O2: 2026-W05 | P2: 2026-W06 | Q2: 2026-W07 | R2: 2026-W08 | S2: 2026-W09 | T2: 2026-W10 | U2: 2026-W11 | V2: 2026-W12 | W2: 2026-W13 | X2: 2026-W14 | Y2: 2026-W15 | Z2: 2026-W16 | AA2: 2026-W17 | AB2: 2026-W18 | AC2: 2026-W19 | AD2: 2026-W20 | AE2: 2026-W21 | AF2: 2026-W22 | AG2: 2026-W23 | AH2: 2026-W24 | AI2: 2026-W25 | AJ2: 2026-W26 | AK2: 2026-W27 | AL2: 2026-W28 | AM2: 2026-W29 | AN2: 2026-W30 | AO2: 2026-W31 | AP2: 2026-W32 | AQ2: 2026-W33 | AR2: 2026-W34 | AS2: 2026-W35 | AT2: 2026-W36 | AU2: 2026-W37 | AV2: 2026-W38 | AW2: 2026-W39 | AX2: 2026-W40 | AY2: 2026-W41 | AZ2: 2026-W42 | BA2: 2026-W43 | BB2: 2026-W44 | BC2: 2026-W45 | BD2: 2026-W46 | BE2: 2026-W47 | BF2: 2026-W48 | BG2: 2026-W49 | BH2: 2026-W50 | BI2: 2026-W51 | BJ2: 2026-W52
A3: 1 | B3: Chicken | C3: CS/P+ | D3: 0.1193 | E3: 0.1114 | F3: 0.1114 | G3: 0.1114 | H3: 0.0798 | I3: 0.0692 | J3: 0.0602 | K3: FALSE | L3: FALSE | M3: FALSE | N3: FALSE | O3: FALSE | P3: FALSE | Q3: FALSE | R3: FALSE | S3: FALSE | T3: FALSE | U3: FALSE | V3: FALSE | W3: FALSE | X3: FALSE | Y3: FALSE | Z3: FALSE | AA3: FALSE | AB3: FALSE | AC3: FALSE | AD3: FALSE | AE3: FALSE | AF3: FALSE | AG3: FALSE | AH3: FALSE | AI3: TRUE | AJ3: TRUE | AK3: TRUE | AL3: TRUE | AM3: TRUE | AN3: TRUE | AO3: TRUE | AP3: TRUE | AQ3: TRUE | AR3: TRUE | AS3: TRUE | AT3: TRUE | AU3: TRUE | AV3: TRUE | AW3: TRUE | AX3: TRUE | AY3: TRUE | AZ3: TRUE | BA3: TRUE | BB3: TRUE | BC3: TRUE | BD3: TRUE | BE3: TRUE | BF3: TRUE | BG3: TRUE | BH3: TRUE | BI3: TRUE | BJ3: TRUE
A4: 2 | B4: Chicken | C4: CS | D4: 0.1033 | E4: 0.0964 | F4: 0.0964 | G4: 0.0964 | H4: 0.0632 | I4: 0.0574 | J4: 0.0463 | K4: FALSE | L4: FALSE | M4: FALSE | N4: FALSE | O4: FALSE | P4: FALSE | Q4: FALSE | R4: FALSE | S4: FALSE | T4: FALSE | U4: FALSE | V4: FALSE | W4: FALSE | X4: FALSE | Y4: FALSE | Z4: FALSE | AA4: FALSE | AB4: FALSE | AC4: FALSE | AD4: FALSE | AE4: TRUE | AF4: FALSE | AG4: TRUE | AH4: TRUE | AI4: TRUE | AJ4: TRUE | AK4: TRUE | AL4: TRUE | AM4: TRUE | AN4: TRUE | AO4: TRUE | AP4: TRUE | AQ4: TRUE | AR4: TRUE | AS4: TRUE | AT4: TRUE | AU4: TRUE | AV4: TRUE | AW4: TRUE | AX4: TRUE | AY4: TRUE | AZ4: TRUE | BA4: TRUE | BB4: TRUE | BC4: TRUE | BD4: TRUE | BE4: TRUE | BF4: TRUE | BG4: TRUE | BH4: TRUE | BI4: TRUE | BJ4: TRUE
A5: 3 | B5: Beef | C5: Keto | D5: 0.097 | E5: 0.0808 | F5: 0.0673 | G5: 0.0673 | H5: 0.0525 | I5: 0.0412 | J5: 0.0324 | K5: FALSE | L5: FALSE | M5: FALSE | N5: FALSE | O5: FALSE | P5: FALSE | Q5: FALSE | R5: FALSE | S5: FALSE | T5: FALSE | U5: FALSE | V5: FALSE | W5: FALSE | X5: FALSE | Y5: FALSE | Z5: FALSE | AA5: FALSE | AB5: FALSE | AC5: FALSE | AD5: FALSE | AE5: FALSE | AF5: TRUE | AG5: TRUE | AH5: TRUE | AI5: TRUE | AJ5: TRUE | AK5: TRUE | AL5: TRUE | AM5: TRUE | AN5: TRUE | AO5: TRUE | AP5: TRUE | AQ5: TRUE | AR5: TRUE | AS5: TRUE | AT5: TRUE | AU5: TRUE | AV5: TRUE | AW5: TRUE | AX5: TRUE | AY5: TRUE | AZ5: TRUE | BA5: TRUE | BB5: TRUE | BC5: TRUE | BD5: TRUE | BE5: TRUE | BF5: TRUE | BG5: TRUE | BH5: TRUE | BI5: TRUE | BJ5: TRUE
A6: 4 | B6: Fish / Seafood / Beef | C6: P+ | D6: 0.0825 | E6: 0.0632 | F6: 0.0519 | G6: 0.0366 | H6: 0.0578 | I6: 0.0435 | J6: 0.0417 | K6: FALSE | L6: FALSE | M6: FALSE | N6: FALSE | O6: FALSE | P6: FALSE | Q6: FALSE | R6: FALSE | S6: FALSE | T6: FALSE | U6: FALSE | V6: FALSE | W6: FALSE | X6: FALSE | Y6: FALSE | Z6: FALSE | AA6: FALSE | AB6: FALSE | AC6: FALSE | AD6: FALSE | AE6: FALSE | AF6: TRUE | AG6: TRUE | AH6: TRUE | AI6: TRUE | AJ6: TRUE | AK6: TRUE | AL6: TRUE | AM6: TRUE | AN6: TRUE | AO6: TRUE | AP6: TRUE | AQ6: TRUE | AR6: TRUE | AS6: TRUE | AT6: TRUE | AU6: TRUE | AV6: TRUE | AW6: TRUE | AX6: TRUE | AY6: TRUE | AZ6: TRUE | BA6: TRUE | BB6: TRUE | BC6: TRUE | BD6: TRUE | BE6: TRUE | BF6: TRUE | BG6: TRUE | BH6: TRUE | BI6: TRUE | BJ6: TRUE
A7: 5 | B7: Chicken | C7: CS | D7: 0.0976 | E7: 0.0911 | F7: 0.0911 | G7: 0.0911 | H7: 0.0592 | I7: 0.0489 | J7: 0.037 | K7: FALSE | L7: FALSE | M7: FALSE | N7: FALSE | O7: FALSE | P7: FALSE | Q7: FALSE | R7: FALSE | S7: FALSE | T7: FALSE | U7: FALSE | V7: FALSE | W7: FALSE | X7: FALSE | Y7: FALSE | Z7: FALSE | AA7: FALSE | AB7: FALSE | AC7: FALSE | AD7: FALSE | AE7: FALSE | AF7: FALSE | AG7: FALSE | AH7: FALSE | AI7: FALSE | AJ7: FALSE | AK7: FALSE | AL7: FALSE | AM7: FALSE | AN7: FALSE | AO7: TRUE | AP7: TRUE | AQ7: TRUE | AR7: TRUE | AS7: TRUE | AT7: TRUE | AU7: TRUE | AV7: TRUE | AW7: TRUE | AX7: TRUE | AY7: TRUE | AZ7: TRUE | BA7: TRUE | BB7: TRUE | BC7: TRUE | BD7: TRUE | BE7: TRUE | BF7: TRUE | BG7: TRUE | BH7: TRUE | BI7: TRUE | BJ7: TRUE
A8: 6 | B8: Fish / Seafood | C8: Keto | D8: 0.0739 | E8: 0.0566 | F8: 0.0465 | G8: 0.0328 | H8: 0.046 | I8: 0.0399 | J8: 0.037 | K8: FALSE | L8: FALSE | M8: FALSE | N8: FALSE | O8: FALSE | P8: FALSE | Q8: FALSE | R8: FALSE | S8: FALSE | T8: FALSE | U8: FALSE | V8: FALSE | W8: FALSE | X8: FALSE | Y8: FALSE | Z8: FALSE | AA8: FALSE | AB8: FALSE | AC8: FALSE | AD8: TRUE | AE8: FALSE | AF8: TRUE | AG8: TRUE | AH8: TRUE | AI8: TRUE | AJ8: TRUE | AK8: TRUE | AL8: TRUE | AM8: TRUE | AN8: TRUE | AO8: TRUE | AP8: TRUE | AQ8: TRUE | AR8: TRUE | AS8: TRUE | AT8: TRUE | AU8: TRUE | AV8: TRUE | AW8: TRUE | AX8: TRUE | AY8: TRUE | AZ8: TRUE | BA8: TRUE | BB8: TRUE | BC8: TRUE | BD8: TRUE | BE8: TRUE | BF8: TRUE | BG8: TRUE | BH8: TRUE | BI8: TRUE | BJ8: TRUE
A9: 7 | B9: Chicken | C9: Keto | D9: 0.0622 | E9: 0.0581 | F9: 0.0581 | G9: 0.0581 | H9: 0.0402 | I9: 0.0376 | J9: 0.0324 | K9: FALSE | L9: FALSE | M9: FALSE | N9: FALSE | O9: FALSE | P9: FALSE | Q9: FALSE | R9: FALSE | S9: FALSE | T9: FALSE | U9: FALSE | V9: FALSE | W9: FALSE | X9: FALSE | Y9: FALSE | Z9: FALSE | AA9: FALSE | AB9: FALSE | AC9: FALSE | AD9: TRUE | AE9: FALSE | AF9: TRUE | AG9: TRUE | AH9: TRUE | AI9: TRUE | AJ9: TRUE | AK9: TRUE | AL9: TRUE | AM9: TRUE | AN9: TRUE | AO9: TRUE | AP9: TRUE | AQ9: TRUE | AR9: TRUE | AS9: TRUE | AT9: TRUE | AU9: TRUE | AV9: TRUE | AW9: TRUE | AX9: TRUE | AY9: TRUE | AZ9: TRUE | BA9: TRUE | BB9: TRUE | BC9: TRUE | BD9: TRUE | BE9: TRUE | BF9: TRUE | BG9: TRUE | BH9: TRUE | BI9: TRUE | BJ9: TRUE
A10: 8 | B10: Chicken | C10: Keto | D10: 0.0677 | E10: 0.0632 | F10: 0.0632 | G10: 0.0632 | H10: 0.0451 | I10: 0.0388 | J10: 0.0324 | K10: FALSE | L10: FALSE | M10: FALSE | N10: FALSE | O10: FALSE | P10: FALSE | Q10: FALSE | R10: FALSE | S10: FALSE | T10: FALSE | U10: FALSE | V10: FALSE | W10: FALSE | X10: FALSE | Y10: FALSE | Z10: FALSE | AA10: FALSE | AB10: FALSE | AC10: FALSE | AD10: FALSE | AE10: FALSE | AF10: FALSE | AG10: FALSE | AH10: FALSE | AI10: FALSE | AJ10: TRUE | AK10: TRUE | AL10: TRUE | AM10: TRUE | AN10: TRUE | AO10: TRUE | AP10: TRUE | AQ10: TRUE | AR10: TRUE | AS10: TRUE | AT10: TRUE | AU10: TRUE | AV10: TRUE | AW10: TRUE | AX10: TRUE | AY10: TRUE | AZ10: TRUE | BA10: TRUE | BB10: TRUE | BC10: TRUE | BD10: TRUE | BE10: TRUE | BF10: TRUE | BG10: TRUE | BH10: TRUE | BI10: TRUE | BJ10: TRUE
A11: 9 | B11: Vegetarian | C11: Veg | D11: 0.0166 | E11: 0.0166 | F11: 0.0166 | G11: 0.0093 | H11: 0.0154 | I11: 0.0159 | J11: 0.0162 | K11: FALSE | L11: FALSE | M11: FALSE | N11: FALSE | O11: FALSE | P11: FALSE | Q11: FALSE | R11: FALSE | S11: FALSE | T11: FALSE | U11: FALSE | V11: FALSE | W11: FALSE | X11: FALSE | Y11: FALSE | Z11: FALSE | AA11: FALSE | AB11: FALSE | AC11: FALSE | AD11: FALSE | AE11: TRUE | AF11: TRUE | AG11: TRUE | AH11: TRUE | AI11: TRUE | AJ11: TRUE | AK11: TRUE | AL11: TRUE | AM11: TRUE | AN11: TRUE | AO11: TRUE | AP11: TRUE | AQ11: TRUE | AR11: TRUE | AS11: TRUE | AT11: TRUE | AU11: TRUE | AV11: TRUE | AW11: TRUE | AX11: TRUE | AY11: TRUE | AZ11: TRUE | BA11: TRUE | BB11: TRUE | BC11: TRUE | BD11: TRUE | BE11: TRUE | BF11: TRUE | BG11: TRUE | BH11: TRUE | BI11: TRUE | BJ11: TRUE
A12: 10 | B12: Vegetarian | C12: Veg | D12: 0.0211 | E12: 0.0211 | F12: 0.0211 | G12: 0.0118 | H12: 0.0162 | I12: 0.017 | J12: 0.0162 | K12: FALSE | L12: FALSE | M12: FALSE | N12: FALSE | O12: FALSE | P12: FALSE | Q12: FALSE | R12: FALSE | S12: FALSE | T12: FALSE | U12: FALSE | V12: FALSE | W12: FALSE | X12: FALSE | Y12: FALSE | Z12: FALSE | AA12: FALSE | AB12: FALSE | AC12: FALSE | AD12: FALSE | AE12: FALSE | AF12: TRUE | AG12: TRUE | AH12: TRUE | AI12: TRUE | AJ12: TRUE | AK12: TRUE | AL12: TRUE | AM12: TRUE | AN12: TRUE | AO12: TRUE | AP12: TRUE | AQ12: TRUE | AR12: TRUE | AS12: TRUE | AT12: TRUE | AU12: TRUE | AV12: TRUE | AW12: TRUE | AX12: TRUE | AY12: TRUE | AZ12: TRUE | BA12: TRUE | BB12: TRUE | BC12: TRUE | BD12: TRUE | BE12: TRUE | BF12: TRUE | BG12: TRUE | BH12: TRUE | BI12: TRUE | BJ12: TRUE
A13: 11 | B13: Pork | C13: Flexible Slot | D13: 0.0215 | E13: 0.0215 | F13: 0.0215 | G13: 0.0215 | H13: 0.0212 | I13: 0.0195 | J13: 0.0185 | K13: FALSE | L13: FALSE | M13: FALSE | N13: FALSE | O13: FALSE | P13: FALSE | Q13: FALSE | R13: FALSE | S13: FALSE | T13: FALSE | U13: FALSE | V13: FALSE | W13: FALSE | X13: FALSE | Y13: FALSE | Z13: FALSE | AA13: FALSE | AB13: FALSE | AC13: FALSE | AD13: FALSE | AE13: FALSE | AF13: FALSE | AG13: FALSE | AH13: FALSE | AI13: FALSE | AJ13: FALSE | AK13: FALSE | AL13: FALSE | AM13: FALSE | AN13: FALSE | AO13: TRUE | AP13: TRUE | AQ13: TRUE | AR13: TRUE | AS13: TRUE | AT13: TRUE | AU13: TRUE | AV13: TRUE | AW13: TRUE | AX13: TRUE | AY13: TRUE | AZ13: TRUE | BA13: TRUE | BB13: TRUE | BC13: TRUE | BD13: TRUE | BE13: TRUE | BF13: TRUE | BG13: TRUE | BH13: TRUE | BI13: TRUE | BJ13: TRUE
A14: 12 | B14: Fish / Seafood | C14: P+ | D14: 0.0478 | E14: 0.0366 | F14: 0.03 | G14: 0.0212 | H14: 0.0355 | I14: 0.0325 | J14: 0.0324 | K14: FALSE | L14: FALSE | M14: FALSE | N14: FALSE | O14: FALSE | P14: FALSE | Q14: FALSE | R14: FALSE | S14: FALSE | T14: FALSE | U14: FALSE | V14: FALSE | W14: FALSE | X14: FALSE | Y14: FALSE | Z14: FALSE | AA14: FALSE | AB14: FALSE | AC14: FALSE | AD14: TRUE | AE14: TRUE | AF14: TRUE | AG14: TRUE | AH14: TRUE | AI14: TRUE | AJ14: TRUE | AK14: TRUE | AL14: TRUE | AM14: TRUE | AN14: TRUE | AO14: TRUE | AP14: TRUE | AQ14: TRUE | AR14: TRUE | AS14: TRUE | AT14: TRUE | AU14: TRUE | AV14: TRUE | AW14: TRUE | AX14: TRUE | AY14: TRUE | AZ14: TRUE | BA14: TRUE | BB14: TRUE | BC14: TRUE | BD14: TRUE | BE14: TRUE | BF14: TRUE | BG14: TRUE | BH14: TRUE | BI14: TRUE | BJ14: TRUE
... A20: 18 | B20: Pork | C20: CS | D20: 0.0233 | E20: 0.0233 | F20: 0.0233 | G20: 0.0233 | H20: 0.0196 | I20: 0.02 | J20: 0.0185 | K20: FALSE | L20: FALSE | M20: FALSE | N20: FALSE | O20: FALSE | P20: FALSE | Q20: FALSE | R20: FALSE | S20: FALSE | T20: FALSE | U20: FALSE | V20: FALSE | W20: FALSE | X20: FALSE | Y20: FALSE | Z20: FALSE | AA20: FALSE | AB20: FALSE | AC20: FALSE | AD20: FALSE | AE20: FALSE | AF20: FALSE | AG20: TRUE | AH20: TRUE | AI20: TRUE | AJ20: TRUE | AK20: TRUE | AL20: TRUE | AM20: TRUE | AN20: TRUE | AO20: TRUE | AP20: TRUE | AQ20: TRUE | AR20: TRUE | AS20: TRUE | AT20: TRUE | AU20: TRUE | AV20: TRUE | AW20: TRUE | AX20: TRUE | AY20: TRUE | AZ20: TRUE | BA20: TRUE | BB20: TRUE | BC20: TRUE | BD20: TRUE | BE20: TRUE | BF20: TRUE | BG20: TRUE | BH20: TRUE | BI20: TRUE | BJ20: TRUE
A21: 19 | B21: Fish / Seafood | C21: Athlete | E21: 0.0478 | F21: 0.042 | G21: 0.0277 | H21: 0.0338 | I21: 0.0346 | J21: 0.0324 | AC21: FALSE | AD21: FALSE | AE21: TRUE | AF21: TRUE | AG21: FALSE | AH21: TRUE | AI21: TRUE | AJ21: TRUE | AK21: TRUE | AL21: TRUE | AM21: TRUE | AN21: TRUE | AO21: TRUE | AP21: TRUE | AQ21: TRUE | AR21: TRUE | AS21: TRUE | AT21: TRUE | AU21: TRUE | AV21: TRUE | AW21: TRUE | AX21: TRUE | AY21: TRUE | AZ21: TRUE | BA21: TRUE | BB21: TRUE | BC21: TRUE | BD21: TRUE | BE21: TRUE | BF21: TRUE | BG21: TRUE | BH21: TRUE | BI21: TRUE | BJ21: TRUE
A22: 20 | B22: Beef | C22: Athlete | E22: 0.0215 | F22: 0.0179 | G22: 0.0179 | H22: 0.0208 | I22: 0.0224 | J22: 0.0231 | AC22: FALSE | AD22: FALSE | AE22: TRUE | AF22: FALSE | AG22: FALSE | AH22: TRUE | AI22: TRUE | AJ22: TRUE | AK22: TRUE | AL22: TRUE | AM22: TRUE | AN22: TRUE | AO22: TRUE | AP22: TRUE | AQ22: TRUE | AR22: TRUE | AS22: TRUE | AT22: TRUE | AU22: TRUE | AV22: TRUE | AW22: TRUE | AX22: TRUE | AY22: TRUE | AZ22: TRUE | BA22: TRUE | BB22: TRUE | BC22: TRUE | BD22: TRUE | BE22: TRUE | BF22: TRUE | BG22: TRUE | BH22: TRUE | BI22: TRUE | BJ22: TRUE
A23: 21 | B23: Chicken | C23: Athlete | E23: 0.03 | F23: 0.03 | G23: 0.03 | H23: 0.0301 | I23: 0.0334 | J23: 0.037 | AC23: FALSE | AD23: FALSE | AE23: FALSE | AF23: TRUE | AG23: TRUE | AH23: TRUE | AI23: TRUE | AJ23: TRUE | AK23: TRUE | AL23: TRUE | AM23: TRUE | AN23: TRUE | AO23: TRUE | AP23: TRUE | AQ23: TRUE | AR23: TRUE | AS23: TRUE | AT23: TRUE | AU23: TRUE | AV23: TRUE | AW23: TRUE | AX23: TRUE | AY23: TRUE | AZ23: TRUE | BA23: TRUE | BB23: TRUE | BC23: TRUE | BD23: TRUE | BE23: TRUE | BF23: TRUE | BG23: TRUE | BH23: TRUE | BI23: TRUE | BJ23: TRUE
A24: 22 | B24: Beef | C24: CS | F24: 0.0215 | G24: 0.0215 | H24: 0.0231 | I24: 0.0255 | J24: 0.0278 | AG24: TRUE | AH24: TRUE | AI24: TRUE | AJ24: TRUE | AK24: TRUE | AL24: TRUE | AM24: TRUE | AN24: TRUE | AO24: TRUE | AP24: TRUE | AQ24: TRUE | AR24: TRUE | AS24: TRUE | AT24: TRUE | AU24: TRUE | AV24: TRUE | AW24: TRUE | AX24: TRUE | AY24: TRUE | AZ24: TRUE | BA24: TRUE | BB24: TRUE | BC24: TRUE | BD24: TRUE | BE24: TRUE | BF24: TRUE | BG24: TRUE | BH24: TRUE | BI24: TRUE | BJ24: TRUE
A25: 23 | B25: Flexible Slot | C25: Mediterranean | F25: 0.03 | G25: 0.03 | H25: 0.0278 | I25: 0.0288 | J25: 0.0278 | AG25: TRUE | AH25: TRUE | AI25: TRUE | AJ25: TRUE | AK25: TRUE | AL25: TRUE | AM25: TRUE | AN25: TRUE | AO25: TRUE | AP25: TRUE | AQ25: TRUE | AR25: TRUE | AS25: TRUE | AT25: TRUE | AU25: TRUE | AV25: TRUE | AW25: TRUE | AX25: TRUE | AY25: TRUE | AZ25: TRUE | BA25: TRUE | BB25: TRUE | BC25: TRUE | BD25: TRUE | BE25: TRUE | BF25: TRUE | BG25: TRUE | BH25: TRUE | BI25: TRUE | BJ25: TRUE
A26: 24 | B26: Shrimp | C26: Mediterranean | F26: 0.0336 | G26: 0.0258 | H26: 0.0329 | I26: 0.034 | J26: 0.0324 | AG26: TRUE | AH26: TRUE | AI26: TRUE | AJ26: TRUE | AK26: TRUE | AL26: TRUE | AM26: TRUE | AN26: TRUE | AO26: TRUE | AP26: TRUE | AQ26: TRUE | AR26: TRUE | AS26: TRUE | AT26: TRUE | AU26: TRUE | AV26: TRUE | AW26: TRUE | AX26: TRUE | AY26: TRUE | AZ26: TRUE | BA26: TRUE | BB26: TRUE | BC26: TRUE | BD26: TRUE | BE26: TRUE | BF26: TRUE | BG26: TRUE | BH26: TRUE | BI26: TRUE | BJ26: TRUE
A27: 25 | B27: Fish / Seafood | C27: Mediterranean | G27: 0.03 | H27: 0.0319 | I27: 0.0325 | J27: 0.0324 | AK27: TRUE | AL27: TRUE | AM27: TRUE | AN27: TRUE | AO27: TRUE | AP27: TRUE | AQ27: TRUE | AR27: TRUE | AS27: TRUE | AT27: TRUE | AU27: TRUE | AV27: TRUE | AW27: TRUE | AX27: TRUE | AY27: TRUE | AZ27: TRUE | BA27: TRUE | BB27: TRUE | BC27: TRUE | BD27: TRUE | BE27: TRUE | BF27: TRUE | BG27: TRUE | BH27: TRUE | BI27: TRUE | BJ27: TRUE
A28: 26 | B28: Fish / Seafood | C28: Mediterranean | G28: 0.03 | H28: 0.0319 | I28: 0.0325 | J28: 0.0324 | AK28: TRUE | AL28: TRUE | AM28: TRUE | AN28: TRUE | AO28: TRUE | AP28: TRUE | AQ28: TRUE | AR28: TRUE | AS28: TRUE | AT28: TRUE | AU28: TRUE | AV28: TRUE | AW28: TRUE | AX28: TRUE | AY28: TRUE | AZ28: TRUE | BA28: TRUE | BB28: TRUE | BC28: TRUE | BD28: TRUE | BE28: TRUE | BF28: TRUE | BG28: TRUE | BH28: TRUE | BI28: TRUE | BJ28: TRUE
A29: 27 | B29: Vegetarian | C29: CS | G29: 0.0166 | H29: 0.0125 | I29: 0.0127 | J29: 0.0162 | AK29: TRUE | AL29: TRUE | AM29: TRUE | AN29: TRUE | AO29: TRUE | AP29: TRUE | AQ29: TRUE | AR29: TRUE | AS29: TRUE | AT29: TRUE | AU29: TRUE | AV29: TRUE | AW29: TRUE | AX29: TRUE | AY29: TRUE | AZ29: TRUE | BA29: TRUE | BB29: TRUE | BC29: TRUE | BD29: TRUE | BE29: TRUE | BF29: TRUE | BG29: TRUE | BH29: TRUE | BI29: TRUE | BJ29: TRUE
A30: 28 | B30: Shrimp | C30: Mediterranean | H30: 0.0319 | I30: 0.0325 | J30: 0.0324 | AO30: TRUE | AP30: TRUE | AQ30: TRUE | AR30: TRUE | AS30: TRUE | AT30: TRUE | AU30: TRUE | AV30: TRUE | AW30: TRUE | AX30: TRUE | AY30: TRUE | AZ30: TRUE | BA30: TRUE | BB30: TRUE | BC30: TRUE | BD30: TRUE | BE30: TRUE | BF30: TRUE | BG30: TRUE | BH30: TRUE | BI30: TRUE | BJ30: TRUE
A31: 29 | B31: Lamb | C31: Athlete | H31: 0.0273 | I31: 0.0278 | J31: 0.0278 | AO31: TRUE | AP31: TRUE | AQ31: TRUE | AR31: TRUE | AS31: TRUE | AT31: TRUE | AU31: TRUE | AV31: TRUE | AW31: TRUE | AX31: TRUE | AY31: TRUE | AZ31: TRUE | BA31: TRUE | BB31: TRUE | BC31: TRUE | BD31: TRUE | BE31: TRUE | BF31: TRUE | BG31: TRUE | BH31: TRUE | BI31: TRUE | BJ31: TRUE
A32: 30 | B32: Lamb | C32: Mediterranean | H32: 0.0273 | I32: 0.0278 | J32: 0.0278 | AO32: TRUE | AP32: TRUE | AQ32: TRUE | AR32: TRUE | AS32: TRUE | AT32: TRUE | AU32: TRUE | AV32: TRUE | AW32: TRUE | AX32: TRUE | AY32: TRUE | AZ32: TRUE | BA32: TRUE | BB32: TRUE | BC32: TRUE | BD32: TRUE | BE32: TRUE | BF32: TRUE | BG32: TRUE | BH32: TRUE | BI32: TRUE | BJ32: TRUE
A33: 31 | B33: Beef | I33: 0.0249 | J33: 0.0231 | AS33: TRUE | AT33: TRUE | AU33: TRUE | AV33: TRUE | AW33: TRUE | AX33: TRUE | AY33: TRUE | AZ33: TRUE | BA33: TRUE | BB33: TRUE | BC33: TRUE | BD33: TRUE | BE33: TRUE | BF33: TRUE | BG33: TRUE | BH33: TRUE | BI33: TRUE | BJ33: TRUE
A34: 32 | B34: Beef | I34: 0.0249 | J34: 0.0231 | AS34: TRUE | AT34: TRUE | AU34: TRUE | AV34: TRUE | AW34: TRUE | AX34: TRUE | AY34: TRUE | AZ34: TRUE | BA34: TRUE | BB34: TRUE | BC34: TRUE | BD34: TRUE | BE34: TRUE | BF34: TRUE | BG34: TRUE | BH34: TRUE | BI34: TRUE | BJ34: TRUE
A35: 33 | B35: Vegetarian | I35: 0.015 | J35: 0.0162 | AS35: TRUE | AT35: TRUE | AU35: TRUE | AV35: TRUE | AW35: TRUE | AX35: TRUE | AY35: TRUE | AZ35: TRUE | BA35: TRUE | BB35: TRUE | BC35: TRUE | BD35: TRUE | BE35: TRUE | BF35: TRUE | BG35: TRUE | BH35: TRUE | BI35: TRUE | BJ35: TRUE
A36: 34 | B36: Vegetarian | J36: 0.0162 | BG36: TRUE | BH36: TRUE | BI36: TRUE | BJ36: TRUE
A37: 35 | B37: Vegetarian | J37: 0.0162 | BG37: TRUE | BH37: TRUE | BI37: TRUE | BJ37: TRUE
A38: 36 | B38: White Fish | J38: 0.0324 | BG38: TRUE | BH38: TRUE | BI38: TRUE | BJ38: TRUE
K39: =countif(K2:K20,FALSE) -> 18 | L39: =countif(L2:L20,FALSE) -> 18 | M39: =countif(M2:M20,FALSE) -> 18 | N39: =countif(N2:N20,FALSE) -> 18 | O39: =countif(O2:O20,FALSE) -> 18 | P39: =countif(P2:P20,FALSE) -> 18 | Q39: =countif(Q2:Q20,FALSE) -> 18 | R39: =countif(R2:R20,FALSE) -> 18 | S39: =countif(S2:S23,FALSE) -> 18 | T39: =countif(T2:T23,FALSE) -> 18 | U39: =countif(U2:U23,FALSE) -> 18 | V39: =countif(V$2:V$26,FALSE) -> 18
A40: DE | K40: 2026-M01 | L40: 2026-M01 | M40: 2026-M01 | N40: 2026-M01 | O40: 2026-M01 | P40: 2026-M02 | Q40: 2026-M02 | R40: 2026-M02 | S40: 2026-M02 | T40: 2026-M03 | U40: 2026-M03 | V40: 2026-M03 | W40: 2026-M03 | X40: 2026-M04 | Y40: 2026-M04 | Z40: 2026-M04 | AA40: 2026-M04 | AB40: 2026-M04 | AC40: 2026-M05 | AD40: 2026-M05 | AE40: 2026-M05 | AF40: 2026-M05 | AG40: 2026-M06 | AH40: 2026-M06 | AI40: 2026-M06 | AJ40: 2026-M06 | AK40: 2026-M07 | AL40: 2026-M07 | AM40: 2026-M07 | AN40: 2026-M07 | AO40: 2026-M07 | AP40: 2026-M08 | AQ40: 2026-M08 | AR40: 2026-M08 | AS40: 2026-M08 | AT40: 2026-M09 | AU40: 2026-M09 | AV40: 2026-M09 | AW40: 2026-M09 | AX40: 2026-M10 | AY40: 2026-M10 | AZ40: 2026-M10 | BA40: 2026-M10 | BB40: 2026-M10 | BC40: 2026-M11 | BD40: 2026-M11 | BE40: 2026-M11 | BF40: 2026-M11 | BG40: 2026-M12 | BH40: 2026-M12 | BI40: 2026-M12 | BJ40: 2026-M12
A41: Slot | B41: Protein | C41: Preference | D41: 18 | E41: 21 | F41: 24 | G41: 27 | H41: 30 | I41: 33 | J41: 36 | K41: 2026-W01 | L41: 2026-W02 | M41: 2026-W03 | N41: 2026-W04 | O41: 2026-W05 | P41: 2026-W06 | Q41: 2026-W07 | R41: 2026-W08 | S41: 2026-W09 | T41: 2026-W10 | U41: 2026-W11 | V41: 2026-W12 | W41: 2026-W13 | X41: 2026-W14 | Y41: 2026-W15 | Z41: 2026-W16 | AA41: 2026-W17 | AB41: 2026-W18 | AC41: 2026-W19 | AD41: 2026-W20 | AE41: 2026-W21 | AF41: 2026-W22 | AG41: 2026-W23 | AH41: 2026-W24 | AI41: 2026-W25 | AJ41: 2026-W26 | AK41: 2026-W27 | AL41: 2026-W28 | AM41: 2026-W29 | AN41: 2026-W30 | AO41: 2026-W31 | AP41: 2026-W32 | AQ41: 2026-W33 | AR41: 2026-W34 | AS41: 2026-W35 | AT41: 2026-W36 | AU41: 2026-W37 | AV41: 2026-W38 | AW41: 2026-W39 | AX41: 2026-W40 | AY41: 2026-W41 | AZ41: 2026-W42 | BA41: 2026-W43 | BB41: 2026-W44 | BC41: 2026-W45 | BD41: 2026-W46 | BE41: 2026-W47 | BF41: 2026-W48 | BG41: 2026-W49 | BH41: 2026-W50 | BI41: 2026-W51 | BJ41: 2026-W52
A42: 1 | B42: Chicken | C42: CS/P+ | D42: 0.1193 | E42: 0.1114 | F42: 0.1114 | G42: 0.1114 | H42: 0.0798 | I42: 0.0692 | J42: 0.0602 | K42: FALSE | L42: FALSE | M42: FALSE | N42: FALSE | O42: FALSE | P42: FALSE | Q42: FALSE | R42: FALSE | S42: FALSE | T42: FALSE | U42: FALSE | V42: FALSE | W42: FALSE | X42: FALSE | Y42: FALSE | Z42: FALSE | AA42: FALSE | AB42: FALSE | AC42: FALSE | AD42: FALSE | AE42: FALSE | AF42: FALSE | AG42: FALSE | AH42: FALSE | AI42: TRUE | AJ42: TRUE | AK42: TRUE | AL42: TRUE | AM42: TRUE | AN42: TRUE | AO42: TRUE | AP42: TRUE | AQ42: TRUE | AR42: TRUE | AS42: TRUE | AT42: TRUE | AU42: TRUE | AV42: TRUE | AW42: TRUE | AX42: TRUE | AY42: TRUE | AZ42: TRUE | BA42: TRUE | BB42: TRUE | BC42: TRUE | BD42: TRUE | BE42: TRUE | BF42: TRUE | BG42: TRUE | BH42: TRUE | BI42: TRUE | BJ42: TRUE
A43: 2 | B43: Chicken | C43: CS | D43: 0.1033 | E43: 0.0964 | F43: 0.0964 | G43: 0.0964 | H43: 0.0632 | I43: 0.0574 | J43: 0.0463 | K43: FALSE | L43: FALSE | M43: FALSE | N43: FALSE | O43: FALSE | P43: FALSE | Q43: FALSE | R43: FALSE | S43: FALSE | T43: FALSE | U43: FALSE | V43: FALSE | W43: FALSE | X43: FALSE | Y43: FALSE | Z43: FALSE | AA43: FALSE | AB43: FALSE | AC43: FALSE | AD43: FALSE | AE43: TRUE | AF43: FALSE | AG43: TRUE | AH43: TRUE | AI43: TRUE | AJ43: TRUE | AK43: TRUE | AL43: TRUE | AM43: TRUE | AN43: TRUE | AO43: TRUE | AP43: TRUE | AQ43: TRUE | AR43: TRUE | AS43: TRUE | AT43: TRUE | AU43: TRUE | AV43: TRUE | AW43: TRUE | AX43: TRUE | AY43: TRUE | AZ43: TRUE | BA43: TRUE | BB43: TRUE | BC43: TRUE | BD43: TRUE | BE43: TRUE | BF43: TRUE | BG43: TRUE | BH43: TRUE | BI43: TRUE | BJ43: TRUE
A44: 3 | B44: Beef | C44: Keto | D44: 0.097 | E44: 0.0808 | F44: 0.0673 | G44: 0.0673 | H44: 0.0525 | I44: 0.0412 | J44: 0.0324 | K44: FALSE | L44: FALSE | M44: FALSE | N44: FALSE | O44: FALSE | P44: FALSE | Q44: FALSE | R44: FALSE | S44: FALSE | T44: FALSE | U44: FALSE | V44: FALSE | W44: FALSE | X44: FALSE | Y44: FALSE | Z44: FALSE | AA44: FALSE | AB44: FALSE | AC44: FALSE | AD44: FALSE | AE44: FALSE | AF44: TRUE | AG44: TRUE | AH44: TRUE | AI44: TRUE | AJ44: TRUE | AK44: TRUE | AL44: TRUE | AM44: TRUE | AN44: TRUE | AO44: TRUE | AP44: TRUE | AQ44: TRUE | AR44: TRUE | AS44: TRUE | AT44: TRUE | AU44: TRUE | AV44: TRUE | AW44: TRUE | AX44: TRUE | AY44: TRUE | AZ44: TRUE | BA44: TRUE | BB44: TRUE | BC44: TRUE | BD44: TRUE | BE44: TRUE | BF44: TRUE | BG44: TRUE | BH44: TRUE | BI44: TRUE | BJ44: TRUE
A45: 4 | B45: Fish / Seafood / Beef | C45: P+ | D45: 0.0825 | E45: 0.0632 | F45: 0.0519 | G45: 0.0366 | H45: 0.0578 | I45: 0.0435 | J45: 0.0417 | K45: FALSE | L45: FALSE | M45: FALSE | N45: FALSE | O45: FALSE | P45: FALSE | Q45: FALSE | R45: FALSE | S45: FALSE | T45: FALSE | U45: FALSE | V45: FALSE | W45: FALSE | X45: FALSE | Y45: FALSE | Z45: FALSE | AA45: FALSE | AB45: FALSE | AC45: TRUE | AD45: FALSE | AE45: FALSE | AF45: TRUE | AG45: TRUE | AH45: TRUE | AI45: TRUE | AJ45: TRUE | AK45: TRUE | AL45: TRUE | AM45: TRUE | AN45: TRUE | AO45: TRUE | AP45: TRUE | AQ45: TRUE | AR45: TRUE | AS45: TRUE | AT45: TRUE | AU45: TRUE | AV45: TRUE | AW45: TRUE | AX45: TRUE | AY45: TRUE | AZ45: TRUE | BA45: TRUE | BB45: TRUE | BC45: TRUE | BD45: TRUE | BE45: TRUE | BF45: TRUE | BG45: TRUE | BH45: TRUE | BI45: TRUE | BJ45: TRUE
A46: 5 | B46: Chicken | C46: CS | D46: 0.0976 | E46: 0.0911 | F46: 0.0911 | G46: 0.0911 | H46: 0.0592 | I46: 0.0489 | J46: 0.037 | K46: FALSE | L46: FALSE | M46: FALSE | N46: FALSE | O46: FALSE | P46: FALSE | Q46: FALSE | R46: FALSE | S46: FALSE | T46: FALSE | U46: FALSE | V46: FALSE | W46: FALSE | X46: FALSE | Y46: FALSE | Z46: FALSE | AA46: FALSE | AB46: FALSE | AC46: FALSE | AD46: FALSE | AE46: TRUE | AF46: FALSE | AG46: FALSE | AH46: FALSE | AI46: FALSE | AJ46: FALSE | AK46: FALSE | AL46: FALSE | AM46: FALSE | AN46: FALSE | AO46: TRUE | AP46: TRUE | AQ46: TRUE | AR46: TRUE | AS46: TRUE | AT46: TRUE | AU46: TRUE | AV46: TRUE | AW46: TRUE | AX46: TRUE | AY46: TRUE | AZ46: TRUE | BA46: TRUE | BB46: TRUE | BC46: TRUE | BD46: TRUE | BE46: TRUE | BF46: TRUE | BG46: TRUE | BH46: TRUE | BI46: TRUE | BJ46: TRUE
A47: 6 | B47: Fish / Seafood | C47: Keto | D47: 0.0739 | E47: 0.0566 | F47: 0.0465 | G47: 0.0328 | H47: 0.046 | I47: 0.0399 | J47: 0.037 | K47: FALSE | L47: FALSE | M47: FALSE | N47: FALSE | O47: FALSE | P47: FALSE | Q47: FALSE | R47: FALSE | S47: FALSE | T47: FALSE | U47: FALSE | V47: FALSE | W47: FALSE | X47: FALSE | Y47: FALSE | Z47: FALSE | AA47: FALSE | AB47: FALSE | AC47: TRUE | AD47: TRUE | AE47: TRUE | AF47: TRUE | AG47: TRUE | AH47: TRUE | AI47: TRUE | AJ47: TRUE | AK47: TRUE | AL47: TRUE | AM47: TRUE | AN47: TRUE | AO47: TRUE | AP47: TRUE | AQ47: TRUE | AR47: TRUE | AS47: TRUE | AT47: TRUE | AU47: TRUE | AV47: TRUE | AW47: TRUE | AX47: TRUE | AY47: TRUE | AZ47: TRUE | BA47: TRUE | BB47: TRUE | BC47: TRUE | BD47: TRUE | BE47: TRUE | BF47: TRUE | BG47: TRUE | BH47: TRUE | BI47: TRUE | BJ47: TRUE
A48: 7 | B48: Chicken | C48: Keto | D48: 0.0622 | E48: 0.0581 | F48: 0.0581 | G48: 0.0581 | H48: 0.0402 | I48: 0.0376 | J48: 0.0324 | K48: FALSE | L48: FALSE | M48: FALSE | N48: FALSE | O48: FALSE | P48: FALSE | Q48: FALSE | R48: FALSE | S48: FALSE | T48: FALSE | U48: FALSE | V48: FALSE | W48: FALSE | X48: FALSE | Y48: FALSE | Z48: FALSE | AA48: FALSE | AB48: FALSE | AC48: TRUE | AD48: TRUE | AE48: FALSE | AF48: TRUE | AG48: TRUE | AH48: TRUE | AI48: TRUE | AJ48: TRUE | AK48: TRUE | AL48: TRUE | AM48: TRUE | AN48: TRUE | AO48: TRUE | AP48: TRUE | AQ48: TRUE | AR48: TRUE | AS48: TRUE | AT48: TRUE | AU48: TRUE | AV48: TRUE | AW48: TRUE | AX48: TRUE | AY48: TRUE | AZ48: TRUE | BA48: TRUE | BB48: TRUE | BC48: TRUE | BD48: TRUE | BE48: TRUE | BF48: TRUE | BG48: TRUE | BH48: TRUE | BI48: TRUE | BJ48: TRUE
A49: 8 | B49: Chicken | C49: Keto | D49: 0.0677 | E49: 0.0632 | F49: 0.0632 | G49: 0.0632 | H49: 0.0451 | I49: 0.0388 | J49: 0.0324 | K49: FALSE | L49: FALSE | M49: FALSE | N49: FALSE | O49: FALSE | P49: FALSE | Q49: FALSE | R49: FALSE | S49: FALSE | T49: FALSE | U49: FALSE | V49: FALSE | W49: FALSE | X49: FALSE | Y49: FALSE | Z49: FALSE | AA49: FALSE | AB49: FALSE | AC49: FALSE | AD49: FALSE | AE49: FALSE | AF49: FALSE | AG49: FALSE | AH49: FALSE | AI49: FALSE | AJ49: TRUE | AK49: TRUE | AL49: TRUE | AM49: TRUE | AN49: TRUE | AO49: TRUE | AP49: TRUE | AQ49: TRUE | AR49: TRUE | AS49: TRUE | AT49: TRUE | AU49: TRUE | AV49: TRUE | AW49: TRUE | AX49: TRUE | AY49: TRUE | AZ49: TRUE | BA49: TRUE | BB49: TRUE | BC49: TRUE | BD49: TRUE | BE49: TRUE | BF49: TRUE | BG49: TRUE | BH49: TRUE | BI49: TRUE | BJ49: TRUE
A50: 9 | B50: Vegetarian | C50: Veg | D50: 0.0166 | E50: 0.0166 | F50: 0.0166 | G50: 0.0093 | H50: 0.0154 | I50: 0.0159 | J50: 0.0162 | K50: FALSE | L50: FALSE | M50: FALSE | N50: FALSE | O50: FALSE | P50: FALSE | Q50: FALSE | R50: FALSE | S50: FALSE | T50: FALSE | U50: FALSE | V50: FALSE | W50: FALSE | X50: FALSE | Y50: FALSE | Z50: FALSE | AA50: FALSE | AB50: FALSE | AC50: FALSE | AD50: FALSE | AE50: TRUE | AF50: TRUE | AG50: TRUE | AH50: TRUE | AI50: TRUE | AJ50: TRUE | AK50: TRUE | AL50: TRUE | AM50: TRUE | AN50: TRUE | AO50: TRUE | AP50: TRUE | AQ50: TRUE | AR50: TRUE | AS50: TRUE | AT50: TRUE | AU50: TRUE | AV50: TRUE | AW50: TRUE | AX50: TRUE | AY50: TRUE | AZ50: TRUE | BA50: TRUE | BB50: TRUE | BC50: TRUE | BD50: TRUE | BE50: TRUE | BF50: TRUE | BG50: TRUE | BH50: TRUE | BI50: TRUE | BJ50: TRUE
A51: 10 | B51: Vegetarian | C51: Veg | D51: 0.0211 | E51: 0.0211 | F51: 0.0211 | G51: 0.0118 | H51: 0.0162 | I51: 0.017 | J51: 0.0162 | K51: FALSE | L51: FALSE | M51: FALSE | N51: FALSE | O51: FALSE | P51: FALSE | Q51: FALSE | R51: FALSE | S51: FALSE | T51: FALSE | U51: FALSE | V51: FALSE | W51: FALSE | X51: FALSE | Y51: FALSE | Z51: FALSE | AA51: FALSE | AB51: FALSE | AC51: FALSE | AD51: FALSE | AE51: FALSE | AF51: TRUE | AG51: TRUE | AH51: TRUE | AI51: TRUE | AJ51: TRUE | AK51: TRUE | AL51: TRUE | AM51: TRUE | AN51: TRUE | AO51: TRUE | AP51: TRUE | AQ51: TRUE | AR51: TRUE | AS51: TRUE | AT51: TRUE | AU51: TRUE | AV51: TRUE | AW51: TRUE | AX51: TRUE | AY51: TRUE | AZ51: TRUE | BA51: TRUE | BB51: TRUE | BC51: TRUE | BD51: TRUE | BE51: TRUE | BF51: TRUE | BG51: TRUE | BH51: TRUE | BI51: TRUE | BJ51: TRUE
A52: 11 | B52: Pork | C52: Flexible Slot | D52: 0.0215 | E52: 0.0215 | F52: 0.0215 | G52: 0.0215 | H52: 0.0212 | I52: 0.0195 | J52: 0.0185 | K52: FALSE | L52: FALSE | M52: FALSE | N52: FALSE | O52: FALSE | P52: FALSE | Q52: FALSE | R52: FALSE | S52: FALSE | T52: FALSE | U52: FALSE | V52: FALSE | W52: FALSE | X52: FALSE | Y52: FALSE | Z52: FALSE | AA52: FALSE | AB52: FALSE | AC52: FALSE | AD52: FALSE | AE52: FALSE | AF52: FALSE | AG52: FALSE | AH52: FALSE | AI52: FALSE | AJ52: FALSE | AK52: FALSE | AL52: FALSE | AM52: FALSE | AN52: FALSE | AO52: TRUE | AP52: TRUE | AQ52: TRUE | AR52: TRUE | AS52: TRUE | AT52: TRUE | AU52: TRUE | AV52: TRUE | AW52: TRUE | AX52: TRUE | AY52: TRUE | AZ52: TRUE | BA52: TRUE | BB52: TRUE | BC52: TRUE | BD52: TRUE | BE52: TRUE | BF52: TRUE | BG52: TRUE | BH52: TRUE | BI52: TRUE | BJ52: TRUE
A53: 12 | B53: Fish / Seafood | C53: P+ | D53: 0.0478 | E53: 0.0366 | F53: 0.03 | G53: 0.0212 | H53: 0.0355 | I53: 0.0325 | J53: 0.0324 | K53: FALSE | L53: FALSE | M53: FALSE | N53: FALSE | O53: FALSE | P53: FALSE | Q53: FALSE | R53: FALSE | S53: FALSE | T53: FALSE | U53: FALSE | V53: FALSE | W53: FALSE | X53: FALSE | Y53: FALSE | Z53: FALSE | AA53: FALSE | AB53: FALSE | AC53: FALSE | AD53: TRUE | AE53: TRUE | AF53: TRUE | AG53: TRUE | AH53: TRUE | AI53: TRUE | AJ53: TRUE | AK53: TRUE | AL53: TRUE | AM53: TRUE | AN53: TRUE | AO53: TRUE | AP53: TRUE | AQ53: TRUE | AR53: TRUE | AS53: TRUE | AT53: TRUE | AU53: TRUE | AV53: TRUE | AW53: TRUE | AX53: TRUE | AY53: TRUE | AZ53: TRUE | BA53: TRUE | BB53: TRUE | BC53: TRUE | BD53: TRUE | BE53: TRUE | BF53: TRUE | BG53: TRUE | BH53: TRUE | BI53: TRUE | BJ53: TRUE
... A59: 18 | B59: Pork | C59: CS | D59: 0.0233 | E59: 0.0233 | F59: 0.0233 | G59: 0.0233 | H59: 0.0196 | I59: 0.02 | J59: 0.0185 | K59: FALSE | L59: FALSE | M59: FALSE | N59: FALSE | O59: FALSE | P59: FALSE | Q59: FALSE | R59: FALSE | S59: FALSE | T59: FALSE | U59: FALSE | V59: FALSE | W59: FALSE | X59: FALSE | Y59: FALSE | Z59: FALSE | AA59: FALSE | AB59: FALSE | AC59: FALSE | AD59: FALSE | AE59: FALSE | AF59: FALSE | AG59: TRUE | AH59: TRUE | AI59: TRUE | AJ59: TRUE | AK59: TRUE | AL59: TRUE | AM59: TRUE | AN59: TRUE | AO59: TRUE | AP59: TRUE | AQ59: TRUE | AR59: TRUE | AS59: TRUE | AT59: TRUE | AU59: TRUE | AV59: TRUE | AW59: TRUE | AX59: TRUE | AY59: TRUE | AZ59: TRUE | BA59: TRUE | BB59: TRUE | BC59: TRUE | BD59: TRUE | BE59: TRUE | BF59: TRUE | BG59: TRUE | BH59: TRUE | BI59: TRUE | BJ59: TRUE
A60: 19 | B60: Fish / Seafood | C60: Athlete | E60: 0.0478 | F60: 0.042 | G60: 0.0277 | H60: 0.0338 | I60: 0.0346 | J60: 0.0324 | K60: FALSE | L60: FALSE | M60: FALSE | N60: FALSE | O60: FALSE | P60: FALSE | Q60: FALSE | AC60: FALSE | AD60: FALSE | AE60: TRUE | AF60: TRUE | AG60: FALSE | AH60: TRUE | AI60: TRUE | AJ60: TRUE | AK60: TRUE | AL60: TRUE | AM60: TRUE | AN60: TRUE | AO60: TRUE | AP60: TRUE | AQ60: TRUE | AR60: TRUE | AS60: TRUE | AT60: TRUE | AU60: TRUE | AV60: TRUE | AW60: TRUE | AX60: TRUE | AY60: TRUE | AZ60: TRUE | BA60: TRUE | BB60: TRUE | BC60: TRUE | BD60: TRUE | BE60: TRUE | BF60: TRUE | BG60: TRUE | BH60: TRUE | BI60: TRUE | BJ60: TRUE
A61: 20 | B61: Beef | C61: Athlete | E61: 0.0215 | F61: 0.0179 | G61: 0.0179 | H61: 0.0208 | I61: 0.0224 | J61: 0.0231 | K61: FALSE | L61: FALSE | M61: FALSE | N61: FALSE | O61: FALSE | P61: FALSE | Q61: FALSE | AC61: FALSE | AD61: FALSE | AE61: TRUE | AF61: FALSE | AG61: FALSE | AH61: TRUE | AI61: TRUE | AJ61: TRUE | AK61: TRUE | AL61: TRUE | AM61: TRUE | AN61: TRUE | AO61: TRUE | AP61: TRUE | AQ61: TRUE | AR61: TRUE | AS61: TRUE | AT61: TRUE | AU61: TRUE | AV61: TRUE | AW61: TRUE | AX61: TRUE | AY61: TRUE | AZ61: TRUE | BA61: TRUE | BB61: TRUE | BC61: TRUE | BD61: TRUE | BE61: TRUE | BF61: TRUE | BG61: TRUE | BH61: TRUE | BI61: TRUE | BJ61: TRUE
A62: 21 | B62: Chicken | C62: Athlete | E62: 0.03 | F62: 0.03 | G62: 0.03 | H62: 0.0301 | I62: 0.0334 | J62: 0.037 | K62: FALSE | L62: FALSE | M62: FALSE | N62: FALSE | O62: FALSE | P62: FALSE | Q62: FALSE | AC62: FALSE | AD62: FALSE | AE62: FALSE | AF62: TRUE | AG62: TRUE | AH62: TRUE | AI62: TRUE | AJ62: TRUE | AK62: TRUE | AL62: TRUE | AM62: TRUE | AN62: TRUE | AO62: TRUE | AP62: TRUE | AQ62: TRUE | AR62: TRUE | AS62: TRUE | AT62: TRUE | AU62: TRUE | AV62: TRUE | AW62: TRUE | AX62: TRUE | AY62: TRUE | AZ62: TRUE | BA62: TRUE | BB62: TRUE | BC62: TRUE | BD62: TRUE | BE62: TRUE | BF62: TRUE | BG62: TRUE | BH62: TRUE | BI62: TRUE | BJ62: TRUE
A63: 22 | B63: Beef | C63: CS | F63: 0.0215 | G63: 0.0215 | H63: 0.0231 | I63: 0.0255 | J63: 0.0278 | K63: FALSE | L63: FALSE | M63: FALSE | N63: FALSE | O63: FALSE | P63: FALSE | Q63: FALSE | AG63: TRUE | AH63: TRUE | AI63: TRUE | AJ63: TRUE | AK63: TRUE | AL63: TRUE | AM63: TRUE | AN63: TRUE | AO63: TRUE | AP63: TRUE | AQ63: TRUE | AR63: TRUE | AS63: TRUE | AT63: TRUE | AU63: TRUE | AV63: TRUE | AW63: TRUE | AX63: TRUE | AY63: TRUE | AZ63: TRUE | BA63: TRUE | BB63: TRUE | BC63: TRUE | BD63: TRUE | BE63: TRUE | BF63: TRUE | BG63: TRUE | BH63: TRUE | BI63: TRUE | BJ63: TRUE
A64: 23 | B64: Flexible Slot | C64: Mediterranean | F64: 0.03 | G64: 0.03 | H64: 0.0278 | I64: 0.0288 | J64: 0.0278 | K64: FALSE | L64: FALSE | M64: FALSE | N64: FALSE | O64: FALSE | P64: FALSE | Q64: FALSE | AG64: TRUE | AH64: TRUE | AI64: TRUE | AJ64: TRUE | AK64: TRUE | AL64: TRUE | AM64: TRUE | AN64: TRUE | AO64: TRUE | AP64: TRUE | AQ64: TRUE | AR64: TRUE | AS64: TRUE | AT64: TRUE | AU64: TRUE | AV64: TRUE | AW64: TRUE | AX64: TRUE | AY64: TRUE | AZ64: TRUE | BA64: TRUE | BB64: TRUE | BC64: TRUE | BD64: TRUE | BE64: TRUE | BF64: TRUE | BG64: TRUE | BH64: TRUE | BI64: TRUE | BJ64: TRUE
A65: 24 | B65: Shrimp | C65: Mediterranean | F65: 0.0336 | G65: 0.0258 | H65: 0.0329 | I65: 0.034 | J65: 0.0324 | K65: FALSE | L65: FALSE | M65: FALSE | N65: FALSE | O65: FALSE | P65: FALSE | Q65: FALSE | AG65: TRUE | AH65: TRUE | AI65: TRUE | AJ65: TRUE | AK65: TRUE | AL65: TRUE | AM65: TRUE | AN65: TRUE | AO65: TRUE | AP65: TRUE | AQ65: TRUE | AR65: TRUE | AS65: TRUE | AT65: TRUE | AU65: TRUE | AV65: TRUE | AW65: TRUE | AX65: TRUE | AY65: TRUE | AZ65: TRUE | BA65: TRUE | BB65: TRUE | BC65: TRUE | BD65: TRUE | BE65: TRUE | BF65: TRUE | BG65: TRUE | BH65: TRUE | BI65: TRUE | BJ65: TRUE
A66: 25 | B66: Fish / Seafood | C66: Mediterranean | G66: 0.03 | H66: 0.0319 | I66: 0.0325 | J66: 0.0324 | K66: FALSE | L66: FALSE | M66: FALSE | N66: FALSE | O66: FALSE | P66: FALSE | Q66: FALSE | AK66: TRUE | AL66: TRUE | AM66: TRUE | AN66: TRUE | AO66: TRUE | AP66: TRUE | AQ66: TRUE | AR66: TRUE | AS66: TRUE | AT66: TRUE | AU66: TRUE | AV66: TRUE | AW66: TRUE | AX66: TRUE | AY66: TRUE | AZ66: TRUE | BA66: TRUE | BB66: TRUE | BC66: TRUE | BD66: TRUE | BE66: TRUE | BF66: TRUE | BG66: TRUE | BH66: TRUE | BI66: TRUE | BJ66: TRUE
A67: 26 | B67: Fish / Seafood | C67: Mediterranean | G67: 0.03 | H67: 0.0319 | I67: 0.0325 | J67: 0.0324 | K67: FALSE | L67: FALSE | M67: FALSE | N67: FALSE | O67: FALSE | P67: FALSE | Q67: FALSE | AK67: TRUE | AL67: TRUE | AM67: TRUE | AN67: TRUE | AO67: TRUE | AP67: TRUE | AQ67: TRUE | AR67: TRUE | AS67: TRUE | AT67: TRUE | AU67: TRUE | AV67: TRUE | AW67: TRUE | AX67: TRUE | AY67: TRUE | AZ67: TRUE | BA67: TRUE | BB67: TRUE | BC67: TRUE | BD67: TRUE | BE67: TRUE | BF67: TRUE | BG67: TRUE | BH67: TRUE | BI67: TRUE | BJ67: TRUE
A68: 27 | B68: Vegetarian | C68: CS | G68: 0.0166 | H68: 0.0125 | I68: 0.0127 | J68: 0.0162 | K68: FALSE | L68: FALSE | M68: FALSE | N68: FALSE | O68: FALSE | P68: FALSE | Q68: FALSE | AK68: TRUE | AL68: TRUE | AM68: TRUE | AN68: TRUE | AO68: TRUE | AP68: TRUE | AQ68: TRUE | AR68: TRUE | AS68: TRUE | AT68: TRUE | AU68: TRUE | AV68: TRUE | AW68: TRUE | AX68: TRUE | AY68: TRUE | AZ68: TRUE | BA68: TRUE | BB68: TRUE | BC68: TRUE | BD68: TRUE | BE68: TRUE | BF68: TRUE | BG68: TRUE | BH68: TRUE | BI68: TRUE | BJ68: TRUE
A69: 28 | B69: Shrimp | C69: Mediterranean | H69: 0.0319 | I69: 0.0325 | J69: 0.0324 | K69: FALSE | L69: FALSE | M69: FALSE | N69: FALSE | O69: FALSE | P69: FALSE | Q69: FALSE | AO69: TRUE | AP69: TRUE | AQ69: TRUE | AR69: TRUE | AS69: TRUE | AT69: TRUE | AU69: TRUE | AV69: TRUE | AW69: TRUE | AX69: TRUE | AY69: TRUE | AZ69: TRUE | BA69: TRUE | BB69: TRUE | BC69: TRUE | BD69: TRUE | BE69: TRUE | BF69: TRUE | BG69: TRUE | BH69: TRUE | BI69: TRUE | BJ69: TRUE
A70: 29 | B70: Lamb | C70: Athlete | H70: 0.0273 | I70: 0.0278 | J70: 0.0278 | K70: FALSE | L70: FALSE | M70: FALSE | N70: FALSE | O70: FALSE | P70: FALSE | Q70: FALSE | AO70: TRUE | AP70: TRUE | AQ70: TRUE | AR70: TRUE | AS70: TRUE | AT70: TRUE | AU70: TRUE | AV70: TRUE | AW70: TRUE | AX70: TRUE | AY70: TRUE | AZ70: TRUE | BA70: TRUE | BB70: TRUE | BC70: TRUE | BD70: TRUE | BE70: TRUE | BF70: TRUE | BG70: TRUE | BH70: TRUE | BI70: TRUE | BJ70: TRUE
A71: 30 | B71: Lamb | C71: Mediterranean | H71: 0.0273 | I71: 0.0278 | J71: 0.0278 | K71: FALSE | L71: FALSE | M71: FALSE | N71: FALSE | O71: FALSE | P71: FALSE | Q71: FALSE | AO71: TRUE | AP71: TRUE | AQ71: TRUE | AR71: TRUE | AS71: TRUE | AT71: TRUE | AU71: TRUE | AV71: TRUE | AW71: TRUE | AX71: TRUE | AY71: TRUE | AZ71: TRUE | BA71: TRUE | BB71: TRUE | BC71: TRUE | BD71: TRUE | BE71: TRUE | BF71: TRUE | BG71: TRUE | BH71: TRUE | BI71: TRUE | BJ71: TRUE
A72: 31 | B72: Beef | I72: 0.0249 | J72: 0.0231 | K72: FALSE | L72: FALSE | M72: FALSE | N72: FALSE | O72: FALSE | P72: FALSE | Q72: FALSE | AS72: TRUE | AT72: TRUE | AU72: TRUE | AV72: TRUE | AW72: TRUE | AX72: TRUE | AY72: TRUE | AZ72: TRUE | BA72: TRUE | BB72: TRUE | BC72: TRUE | BD72: TRUE | BE72: TRUE | BF72: TRUE | BG72: TRUE | BH72: TRUE | BI72: TRUE | BJ72: TRUE
A73: 32 | B73: Beef | I73: 0.0249 | J73: 0.0231 | K73: FALSE | L73: FALSE | M73: FALSE | N73: FALSE | O73: FALSE | P73: FALSE | Q73: FALSE | AS73: TRUE | AT73: TRUE | AU73: TRUE | AV73: TRUE | AW73: TRUE | AX73: TRUE | AY73: TRUE | AZ73: TRUE | BA73: TRUE | BB73: TRUE | BC73: TRUE | BD73: TRUE | BE73: TRUE | BF73: TRUE | BG73: TRUE | BH73: TRUE | BI73: TRUE | BJ73: TRUE
A74: 33 | B74: Vegetarian | I74: 0.015 | J74: 0.0162 | K74: FALSE | L74: FALSE | M74: FALSE | N74: FALSE | O74: FALSE | P74: FALSE | Q74: FALSE | AS74: TRUE | AT74: TRUE | AU74: TRUE | AV74: TRUE | AW74: TRUE | AX74: TRUE | AY74: TRUE | AZ74: TRUE | BA74: TRUE | BB74: TRUE | BC74: TRUE | BD74: TRUE | BE74: TRUE | BF74: TRUE | BG74: TRUE | BH74: TRUE | BI74: TRUE | BJ74: TRUE
A75: 34 | B75: Vegetarian | J75: 0.0162 | K75: FALSE | L75: FALSE | M75: FALSE | N75: FALSE | O75: FALSE | P75: FALSE | Q75: FALSE | BG75: TRUE | BH75: TRUE | BI75: TRUE | BJ75: TRUE
A76: 35 | B76: Vegetarian | J76: 0.0162 | K76: FALSE | L76: FALSE | M76: FALSE | N76: FALSE | O76: FALSE | P76: FALSE | Q76: FALSE | BG76: TRUE | BH76: TRUE | BI76: TRUE | BJ76: TRUE
A77: 36 | B77: White Fish | J77: 0.0324 | K77: FALSE | L77: FALSE | M77: FALSE | N77: FALSE | O77: FALSE | P77: FALSE | Q77: FALSE | BG77: TRUE | BH77: TRUE | BI77: TRUE | BJ77: TRUE
A79: DKSE | K79: 2026-M01 | L79: 2026-M01 | M79: 2026-M01 | N79: 2026-M01 | O79: 2026-M01 | P79: 2026-M02 | Q79: 2026-M02 | R79: 2026-M02 | S79: 2026-M02 | T79: 2026-M03 | U79: 2026-M03 | V79: 2026-M03 | W79: 2026-M03 | X79: 2026-M04 | Y79: 2026-M04 | Z79: 2026-M04 | AA79: 2026-M04 | AB79: 2026-M04 | AC79: 2026-M05 | AD79: 2026-M05 | AE79: 2026-M05 | AF79: 2026-M05 | AG79: 2026-M06 | AH79: 2026-M06 | AI79: 2026-M06 | AJ79: 2026-M06 | AK79: 2026-M07 | AL79: 2026-M07 | AM79: 2026-M07 | AN79: 2026-M07 | AO79: 2026-M07 | AP79: 2026-M08 | AQ79: 2026-M08 | AR79: 2026-M08 | AS79: 2026-M08 | AT79: 2026-M09 | AU79: 2026-M09 | AV79: 2026-M09 | AW79: 2026-M09 | AX79: 2026-M10 | AY79: 2026-M10 | AZ79: 2026-M10 | BA79: 2026-M10 | BB79: 2026-M10 | BC79: 2026-M11 | BD79: 2026-M11 | BE79: 2026-M11 | BF79: 2026-M11 | BG79: 2026-M12 | BH79: 2026-M12 | BI79: 2026-M12 | BJ79: 2026-M12
A80: Slot | B80: Protein | C80: Preference | D80: 18 | E80: 21 | F80: 24 | G80: 27 | H80: 30 | I80: 33 | J80: 36 | K80: 2026-W01 | L80: 2026-W02 | M80: 2026-W03 | N80: 2026-W04 | O80: 2026-W05 | P80: 2026-W06 | Q80: 2026-W07 | R80: 2026-W08 | S80: 2026-W09 | T80: 2026-W10 | U80: 2026-W11 | V80: 2026-W12 | W80: 2026-W13 | X80: 2026-W14 | Y80: 2026-W15 | Z80: 2026-W16 | AA80: 2026-W17 | AB80: 2026-W18 | AC80: 2026-W19 | AD80: 2026-W20 | AE80: 2026-W21 | AF80: 2026-W22 | AG80: 2026-W23 | AH80: 2026-W24 | AI80: 2026-W25 | AJ80: 2026-W26 | AK80: 2026-W27 | AL80: 2026-W28 | AM80: 2026-W29 | AN80: 2026-W30 | AO80: 2026-W31 | AP80: 2026-W32 | AQ80: 2026-W33 | AR80: 2026-W34 | AS80: 2026-W35 | AT80: 2026-W36 | AU80: 2026-W37 | AV80: 2026-W38 | AW80: 2026-W39 | AX80: 2026-W40 | AY80: 2026-W41 | AZ80: 2026-W42 | BA80: 2026-W43 | BB80: 2026-W44 | BC80: 2026-W45 | BD80: 2026-W46 | BE80: 2026-W47 | BF80: 2026-W48 | BG80: 2026-W49 | BH80: 2026-W50 | BI80: 2026-W51 | BJ80: 2026-W52
A81: 1 | B81: Chicken | C81: CSP+ | D81: 0.1193 | E81: 0.1114 | F81: 0.1114 | G81: 0.1114 | H81: 0.0798 | I81: 0.0692 | J81: 0.0602 | K81: FALSE | L81: FALSE | M81: FALSE | N81: FALSE | O81: FALSE | P81: FALSE | Q81: FALSE | R81: FALSE | S81: FALSE | T81: FALSE | U81: FALSE | V81: FALSE | W81: FALSE | X81: FALSE | Y81: FALSE | Z81: FALSE | AA81: FALSE | AB81: FALSE | AC81: FALSE | AD81: FALSE | AE81: FALSE | AF81: FALSE | AG81: FALSE | AH81: FALSE | AI81: TRUE | AJ81: TRUE | AK81: TRUE | AL81: TRUE | AM81: TRUE | AN81: TRUE | AO81: TRUE | AP81: TRUE | AQ81: TRUE | AR81: TRUE | AS81: TRUE | AT81: TRUE | AU81: TRUE | AV81: TRUE | AW81: TRUE | AX81: TRUE | AY81: TRUE | AZ81: TRUE | BA81: TRUE | BB81: TRUE | BC81: TRUE | BD81: TRUE | BE81: TRUE | BF81: TRUE | BG81: TRUE | BH81: TRUE | BI81: TRUE | BJ81: TRUE
A82: 2 | B82: Chicken | C82: CS | D82: 0.1033 | E82: 0.0964 | F82: 0.0964 | G82: 0.0964 | H82: 0.0632 | I82: 0.0574 | J82: 0.0463 | K82: FALSE | L82: FALSE | M82: FALSE | N82: FALSE | O82: FALSE | P82: FALSE | Q82: FALSE | R82: FALSE | S82: FALSE | T82: FALSE | U82: FALSE | V82: FALSE | W82: FALSE | X82: FALSE | Y82: FALSE | Z82: FALSE | AA82: FALSE | AB82: FALSE | AC82: FALSE | AD82: FALSE | AE82: TRUE | AF82: FALSE | AG82: TRUE | AH82: TRUE | AI82: TRUE | AJ82: TRUE | AK82: TRUE | AL82: TRUE | AM82: TRUE | AN82: TRUE | AO82: TRUE | AP82: TRUE | AQ82: TRUE | AR82: TRUE | AS82: TRUE | AT82: TRUE | AU82: TRUE | AV82: TRUE | AW82: TRUE | AX82: TRUE | AY82: TRUE | AZ82: TRUE | BA82: TRUE | BB82: TRUE | BC82: TRUE | BD82: TRUE | BE82: TRUE | BF82: TRUE | BG82: TRUE | BH82: TRUE | BI82: TRUE | BJ82: TRUE
A83: 3 | B83: Beef | C83: Keto | D83: 0.097 | E83: 0.0808 | F83: 0.0673 | G83: 0.0673 | H83: 0.0525 | I83: 0.0412 | J83: 0.0324 | K83: FALSE | L83: FALSE | M83: FALSE | N83: FALSE | O83: FALSE | P83: FALSE | Q83: FALSE | R83: FALSE | S83: FALSE | T83: FALSE | U83: FALSE | V83: FALSE | W83: FALSE | X83: FALSE | Y83: FALSE | Z83: FALSE | AA83: FALSE | AB83: FALSE | AC83: FALSE | AD83: FALSE | AE83: FALSE | AF83: TRUE | AG83: TRUE | AH83: TRUE | AI83: TRUE | AJ83: TRUE | AK83: TRUE | AL83: TRUE | AM83: TRUE | AN83: TRUE | AO83: TRUE | AP83: TRUE | AQ83: TRUE | AR83: TRUE | AS83: TRUE | AT83: TRUE | AU83: TRUE | AV83: TRUE | AW83: TRUE | AX83: TRUE | AY83: TRUE | AZ83: TRUE | BA83: TRUE | BB83: TRUE | BC83: TRUE | BD83: TRUE | BE83: TRUE | BF83: TRUE | BG83: TRUE | BH83: TRUE | BI83: TRUE | BJ83: TRUE
A84: 4 | B84: Fish / Seafood / Beef | C84: P+ | D84: 0.0825 | E84: 0.0632 | F84: 0.0519 | G84: 0.0366 | H84: 0.0578 | I84: 0.0435 | J84: 0.0417 | K84: FALSE | L84: FALSE | M84: FALSE | N84: FALSE | O84: FALSE | P84: FALSE | Q84: FALSE | R84: FALSE | S84: FALSE | T84: FALSE | U84: FALSE | V84: FALSE | W84: FALSE | X84: FALSE | Y84: FALSE | Z84: FALSE | AA84: FALSE | AB84: FALSE | AC84: TRUE | AD84: FALSE | AE84: FALSE | AF84: TRUE | AG84: TRUE | AH84: TRUE | AI84: TRUE | AJ84: TRUE | AK84: TRUE | AL84: TRUE | AM84: TRUE | AN84: TRUE | AO84: TRUE | AP84: TRUE | AQ84: TRUE | AR84: TRUE | AS84: TRUE | AT84: TRUE | AU84: TRUE | AV84: TRUE | AW84: TRUE | AX84: TRUE | AY84: TRUE | AZ84: TRUE | BA84: TRUE | BB84: TRUE | BC84: TRUE | BD84: TRUE | BE84: TRUE | BF84: TRUE | BG84: TRUE | BH84: TRUE | BI84: TRUE | BJ84: TRUE
A85: 5 | B85: Chicken | C85: CS | D85: 0.0976 | E85: 0.0911 | F85: 0.0911 | G85: 0.0911 | H85: 0.0592 | I85: 0.0489 | J85: 0.037 | K85: FALSE | L85: FALSE | M85: FALSE | N85: FALSE | O85: FALSE | P85: FALSE | Q85: FALSE | R85: FALSE | S85: FALSE | T85: FALSE | U85: FALSE | V85: FALSE | W85: FALSE | X85: FALSE | Y85: FALSE | Z85: FALSE | AA85: FALSE | AB85: FALSE | AC85: FALSE | AD85: FALSE | AE85: TRUE | AF85: FALSE | AG85: FALSE | AH85: FALSE | AI85: FALSE | AJ85: FALSE | AK85: FALSE | AL85: FALSE | AM85: FALSE | AN85: FALSE | AO85: TRUE | AP85: TRUE | AQ85: TRUE | AR85: TRUE | AS85: TRUE | AT85: TRUE | AU85: TRUE | AV85: TRUE | AW85: TRUE | AX85: TRUE | AY85: TRUE | AZ85: TRUE | BA85: TRUE | BB85: TRUE | BC85: TRUE | BD85: TRUE | BE85: TRUE | BF85: TRUE | BG85: TRUE | BH85: TRUE | BI85: TRUE | BJ85: TRUE
A86: 6 | B86: Fish / Seafood | C86: Keto | D86: 0.0739 | E86: 0.0566 | F86: 0.0465 | G86: 0.0328 | H86: 0.046 | I86: 0.0399 | J86: 0.037 | K86: FALSE | L86: FALSE | M86: FALSE | N86: FALSE | O86: FALSE | P86: FALSE | Q86: FALSE | R86: FALSE | S86: FALSE | T86: FALSE | U86: FALSE | V86: FALSE | W86: FALSE | X86: FALSE | Y86: FALSE | Z86: FALSE | AA86: FALSE | AB86: FALSE | AC86: TRUE | AD86: TRUE | AE86: TRUE | AF86: TRUE | AG86: TRUE | AH86: TRUE | AI86: TRUE | AJ86: TRUE | AK86: TRUE | AL86: TRUE | AM86: TRUE | AN86: TRUE | AO86: TRUE | AP86: TRUE | AQ86: TRUE | AR86: TRUE | AS86: TRUE | AT86: TRUE | AU86: TRUE | AV86: TRUE | AW86: TRUE | AX86: TRUE | AY86: TRUE | AZ86: TRUE | BA86: TRUE | BB86: TRUE | BC86: TRUE | BD86: TRUE | BE86: TRUE | BF86: TRUE | BG86: TRUE | BH86: TRUE | BI86: TRUE | BJ86: TRUE
A87: 7 | B87: Chicken | C87: Keto | D87: 0.0622 | E87: 0.0581 | F87: 0.0581 | G87: 0.0581 | H87: 0.0402 | I87: 0.0376 | J87: 0.0324 | K87: FALSE | L87: FALSE | M87: FALSE | N87: FALSE | O87: FALSE | P87: FALSE | Q87: FALSE | R87: FALSE | S87: FALSE | T87: FALSE | U87: FALSE | V87: FALSE | W87: FALSE | X87: FALSE | Y87: FALSE | Z87: FALSE | AA87: FALSE | AB87: FALSE | AC87: TRUE | AD87: TRUE | AE87: FALSE | AF87: TRUE | AG87: TRUE | AH87: TRUE | AI87: TRUE | AJ87: TRUE | AK87: TRUE | AL87: TRUE | AM87: TRUE | AN87: TRUE | AO87: TRUE | AP87: TRUE | AQ87: TRUE | AR87: TRUE | AS87: TRUE | AT87: TRUE | AU87: TRUE | AV87: TRUE | AW87: TRUE | AX87: TRUE | AY87: TRUE | AZ87: TRUE | BA87: TRUE | BB87: TRUE | BC87: TRUE | BD87: TRUE | BE87: TRUE | BF87: TRUE | BG87: TRUE | BH87: TRUE | BI87: TRUE | BJ87: TRUE
A88: 8 | B88: Chicken | C88: Keto | D88: 0.0677 | E88: 0.0632 | F88: 0.0632 | G88: 0.0632 | H88: 0.0451 | I88: 0.0388 | J88: 0.0324 | K88: FALSE | L88: FALSE | M88: FALSE | N88: FALSE | O88: FALSE | P88: FALSE | Q88: FALSE | R88: FALSE | S88: FALSE | T88: FALSE | U88: FALSE | V88: FALSE | W88: FALSE | X88: FALSE | Y88: FALSE | Z88: FALSE | AA88: FALSE | AB88: FALSE | AC88: FALSE | AD88: FALSE | AE88: FALSE | AF88: FALSE | AG88: FALSE | AH88: FALSE | AI88: FALSE | AJ88: TRUE | AK88: TRUE | AL88: TRUE | AM88: TRUE | AN88: TRUE | AO88: TRUE | AP88: TRUE | AQ88: TRUE | AR88: TRUE | AS88: TRUE | AT88: TRUE | AU88: TRUE | AV88: TRUE | AW88: TRUE | AX88: TRUE | AY88: TRUE | AZ88: TRUE | BA88: TRUE | BB88: TRUE | BC88: TRUE | BD88: TRUE | BE88: TRUE | BF88: TRUE | BG88: TRUE | BH88: TRUE | BI88: TRUE | BJ88: TRUE
A89: 9 | B89: Vegetarian | C89: Veg | D89: 0.0166 | E89: 0.0166 | F89: 0.0166 | G89: 0.0093 | H89: 0.0154 | I89: 0.0159 | J89: 0.0162 | K89: FALSE | L89: FALSE | M89: FALSE | N89: FALSE | O89: FALSE | P89: FALSE | Q89: FALSE | R89: FALSE | S89: FALSE | T89: FALSE | U89: FALSE | V89: FALSE | W89: FALSE | X89: FALSE | Y89: FALSE | Z89: FALSE | AA89: FALSE | AB89: FALSE | AC89: FALSE | AD89: FALSE | AE89: TRUE | AF89: TRUE | AG89: TRUE | AH89: TRUE | AI89: TRUE | AJ89: TRUE | AK89: TRUE | AL89: TRUE | AM89: TRUE | AN89: TRUE | AO89: TRUE | AP89: TRUE | AQ89: TRUE | AR89: TRUE | AS89: TRUE | AT89: TRUE | AU89: TRUE | AV89: TRUE | AW89: TRUE | AX89: TRUE | AY89: TRUE | AZ89: TRUE | BA89: TRUE | BB89: TRUE | BC89: TRUE | BD89: TRUE | BE89: TRUE | BF89: TRUE | BG89: TRUE | BH89: TRUE | BI89: TRUE | BJ89: TRUE
A90: 10 | B90: Vegetarian | C90: Veg | D90: 0.0211 | E90: 0.0211 | F90: 0.0211 | G90: 0.0118 | H90: 0.0162 | I90: 0.017 | J90: 0.0162 | K90: FALSE | L90: FALSE | M90: FALSE | N90: FALSE | O90: FALSE | P90: FALSE | Q90: FALSE | R90: FALSE | S90: FALSE | T90: FALSE | U90: FALSE | V90: FALSE | W90: FALSE | X90: FALSE | Y90: FALSE | Z90: FALSE | AA90: FALSE | AB90: FALSE | AC90: FALSE | AD90: FALSE | AE90: FALSE | AF90: TRUE | AG90: TRUE | AH90: TRUE | AI90: TRUE | AJ90: TRUE | AK90: TRUE | AL90: TRUE | AM90: TRUE | AN90: TRUE | AO90: TRUE | AP90: TRUE | AQ90: TRUE | AR90: TRUE | AS90: TRUE | AT90: TRUE | AU90: TRUE | AV90: TRUE | AW90: TRUE | AX90: TRUE | AY90: TRUE | AZ90: TRUE | BA90: TRUE | BB90: TRUE | BC90: TRUE | BD90: TRUE | BE90: TRUE | BF90: TRUE | BG90: TRUE | BH90: TRUE | BI90: TRUE | BJ90: TRUE
A91: 11 | B91: Pork | C91: Flexible Slot | D91: 0.0215 | E91: 0.0215 | F91: 0.0215 | G91: 0.0215 | H91: 0.0212 | I91: 0.0195 | J91: 0.0185 | K91: FALSE | L91: FALSE | M91: FALSE | N91: FALSE | O91: FALSE | P91: FALSE | Q91: FALSE | R91: FALSE | S91: FALSE | T91: FALSE | U91: FALSE | V91: FALSE | W91: FALSE | X91: FALSE | Y91: FALSE | Z91: FALSE | AA91: FALSE | AB91: FALSE | AC91: FALSE | AD91: FALSE | AE91: FALSE | AF91: FALSE | AG91: FALSE | AH91: FALSE | AI91: FALSE | AJ91: FALSE | AK91: FALSE | AL91: FALSE | AM91: FALSE | AN91: FALSE | AO91: TRUE | AP91: TRUE | AQ91: TRUE | AR91: TRUE | AS91: TRUE | AT91: TRUE | AU91: TRUE | AV91: TRUE | AW91: TRUE | AX91: TRUE | AY91: TRUE | AZ91: TRUE | BA91: TRUE | BB91: TRUE | BC91: TRUE | BD91: TRUE | BE91: TRUE | BF91: TRUE | BG91: TRUE | BH91: TRUE | BI91: TRUE | BJ91: TRUE
A92: 12 | B92: Fish / Seafood | C92: P+ | D92: 0.0478 | E92: 0.0366 | F92: 0.03 | G92: 0.0212 | H92: 0.0355 | I92: 0.0325 | J92: 0.0324 | K92: FALSE | L92: FALSE | M92: FALSE | N92: FALSE | O92: FALSE | P92: FALSE | Q92: FALSE | R92: FALSE | S92: FALSE | T92: FALSE | U92: FALSE | V92: FALSE | W92: FALSE | X92: FALSE | Y92: FALSE | Z92: FALSE | AA92: FALSE | AB92: FALSE | AC92: FALSE | AD92: TRUE | AE92: TRUE | AF92: TRUE | AG92: TRUE | AH92: TRUE | AI92: TRUE | AJ92: TRUE | AK92: TRUE | AL92: TRUE | AM92: TRUE | AN92: TRUE | AO92: TRUE | AP92: TRUE | AQ92: TRUE | AR92: TRUE | AS92: TRUE | AT92: TRUE | AU92: TRUE | AV92: TRUE | AW92: TRUE | AX92: TRUE | AY92: TRUE | AZ92: TRUE | BA92: TRUE | BB92: TRUE | BC92: TRUE | BD92: TRUE | BE92: TRUE | BF92: TRUE | BG92: TRUE | BH92: TRUE | BI92: TRUE | BJ92: TRUE
... A98: 18 | B98: Pork | C98: CS | D98: 0.0233 | E98: 0.0233 | F98: 0.0233 | G98: 0.0233 | H98: 0.0196 | I98: 0.02 | J98: 0.0185 | K98: FALSE | L98: FALSE | M98: FALSE | N98: FALSE | O98: FALSE | P98: FALSE | Q98: FALSE | R98: FALSE | S98: FALSE | T98: FALSE | U98: FALSE | V98: FALSE | W98: FALSE | X98: FALSE | Y98: FALSE | Z98: FALSE | AA98: FALSE | AB98: FALSE | AC98: FALSE | AD98: FALSE | AE98: FALSE | AF98: FALSE | AG98: TRUE | AH98: TRUE | AI98: TRUE | AJ98: TRUE | AK98: TRUE | AL98: TRUE | AM98: TRUE | AN98: TRUE | AO98: TRUE | AP98: TRUE | AQ98: TRUE | AR98: TRUE | AS98: TRUE | AT98: TRUE | AU98: TRUE | AV98: TRUE | AW98: TRUE | AX98: TRUE | AY98: TRUE | AZ98: TRUE | BA98: TRUE | BB98: TRUE | BC98: TRUE | BD98: TRUE | BE98: TRUE | BF98: TRUE | BG98: TRUE | BH98: TRUE | BI98: TRUE | BJ98: TRUE
A99: 19 | B99: Fish / Seafood | C99: Athlete | E99: 0.0478 | F99: 0.042 | G99: 0.0277 | H99: 0.0338 | I99: 0.0346 | J99: 0.0324 | AC99: FALSE | AD99: FALSE | AE99: TRUE | AF99: TRUE | AG99: FALSE | AH99: TRUE | AI99: TRUE | AJ99: TRUE | AK99: TRUE | AL99: TRUE | AM99: TRUE | AN99: TRUE | AO99: TRUE | AP99: TRUE | AQ99: TRUE | AR99: TRUE | AS99: TRUE | AT99: TRUE | AU99: TRUE | AV99: TRUE | AW99: TRUE | AX99: TRUE | AY99: TRUE | AZ99: TRUE | BA99: TRUE | BB99: TRUE | BC99: TRUE | BD99: TRUE | BE99: TRUE | BF99: TRUE | BG99: TRUE | BH99: TRUE | BI99: TRUE | BJ99: TRUE
A100: 20 | B100: Beef | C100: Athlete | E100: 0.0215 | F100: 0.0179 | G100: 0.0179 | H100: 0.0208 | I100: 0.0224 | J100: 0.0231 | AC100: FALSE | AD100: FALSE | AE100: TRUE | AF100: FALSE | AG100: FALSE | AH100: TRUE | AI100: TRUE | AJ100: TRUE | AK100: TRUE | AL100: TRUE | AM100: TRUE | AN100: TRUE | AO100: TRUE | AP100: TRUE | AQ100: TRUE | AR100: TRUE | AS100: TRUE | AT100: TRUE | AU100: TRUE | AV100: TRUE | AW100: TRUE | AX100: TRUE | AY100: TRUE | AZ100: TRUE | BA100: TRUE | BB100: TRUE | BC100: TRUE | BD100: TRUE | BE100: TRUE | BF100: TRUE | BG100: TRUE | BH100: TRUE | BI100: TRUE | BJ100: TRUE
A101: 21 | B101: Chicken | C101: Athlete | E101: 0.03 | F101: 0.03 | G101: 0.03 | H101: 0.0301 | I101: 0.0334 | J101: 0.037 | AC101: FALSE | AD101: FALSE | AE101: FALSE | AF101: TRUE | AG101: TRUE | AH101: TRUE | AI101: TRUE | AJ101: TRUE | AK101: TRUE | AL101: TRUE | AM101: TRUE | AN101: TRUE | AO101: TRUE | AP101: TRUE | AQ101: TRUE | AR101: TRUE | AS101: TRUE | AT101: TRUE | AU101: TRUE | AV101: TRUE | AW101: TRUE | AX101: TRUE | AY101: TRUE | AZ101: TRUE | BA101: TRUE | BB101: TRUE | BC101: TRUE | BD101: TRUE | BE101: TRUE | BF101: TRUE | BG101: TRUE | BH101: TRUE | BI101: TRUE | BJ101: TRUE
A102: 22 | B102: Beef | C102: CS | F102: 0.0215 | G102: 0.0215 | H102: 0.0231 | I102: 0.0255 | J102: 0.0278 | AG102: TRUE | AH102: TRUE | AI102: TRUE | AJ102: TRUE | AK102: TRUE | AL102: TRUE | AM102: TRUE | AN102: TRUE | AO102: TRUE | AP102: TRUE | AQ102: TRUE | AR102: TRUE | AS102: TRUE | AT102: TRUE | AU102: TRUE | AV102: TRUE | AW102: TRUE | AX102: TRUE | AY102: TRUE | AZ102: TRUE | BA102: TRUE | BB102: TRUE | BC102: TRUE | BD102: TRUE | BE102: TRUE | BF102: TRUE | BG102: TRUE | BH102: TRUE | BI102: TRUE | BJ102: TRUE
A103: 23 | B103: Flexible Slot | C103: Mediterranean | F103: 0.03 | G103: 0.03 | H103: 0.0278 | I103: 0.0288 | J103: 0.0278 | AG103: TRUE | AH103: TRUE | AI103: TRUE | AJ103: TRUE | AK103: TRUE | AL103: TRUE | AM103: TRUE | AN103: TRUE | AO103: TRUE | AP103: TRUE | AQ103: TRUE | AR103: TRUE | AS103: TRUE | AT103: TRUE | AU103: TRUE | AV103: TRUE | AW103: TRUE | AX103: TRUE | AY103: TRUE | AZ103: TRUE | BA103: TRUE | BB103: TRUE | BC103: TRUE | BD103: TRUE | BE103: TRUE | BF103: TRUE | BG103: TRUE | BH103: TRUE | BI103: TRUE | BJ103: TRUE
A104: 24 | B104: Shrimp | C104: Mediterranean | F104: 0.0336 | G104: 0.0258 | H104: 0.0329 | I104: 0.034 | J104: 0.0324 | AG104: TRUE | AH104: TRUE | AI104: TRUE | AJ104: TRUE | AK104: TRUE | AL104: TRUE | AM104: TRUE | AN104: TRUE | AO104: TRUE | AP104: TRUE | AQ104: TRUE | AR104: TRUE | AS104: TRUE | AT104: TRUE | AU104: TRUE | AV104: TRUE | AW104: TRUE | AX104: TRUE | AY104: TRUE | AZ104: TRUE | BA104: TRUE | BB104: TRUE | BC104: TRUE | BD104: TRUE | BE104: TRUE | BF104: TRUE | BG104: TRUE | BH104: TRUE | BI104: TRUE | BJ104: TRUE
A105: 25 | B105: Fish / Seafood | C105: Mediterranean | G105: 0.03 | H105: 0.0319 | I105: 0.0325 | J105: 0.0324 | AK105: TRUE | AL105: TRUE | AM105: TRUE | AN105: TRUE | AO105: TRUE | AP105: TRUE | AQ105: TRUE | AR105: TRUE | AS105: TRUE | AT105: TRUE | AU105: TRUE | AV105: TRUE | AW105: TRUE | AX105: TRUE | AY105: TRUE | AZ105: TRUE | BA105: TRUE | BB105: TRUE | BC105: TRUE | BD105: TRUE | BE105: TRUE | BF105: TRUE | BG105: TRUE | BH105: TRUE | BI105: TRUE | BJ105: TRUE
A106: 26 | B106: Fish / Seafood | C106: Mediterranean | G106: 0.03 | H106: 0.0319 | I106: 0.0325 | J106: 0.0324 | AK106: TRUE | AL106: TRUE | AM106: TRUE | AN106: TRUE | AO106: TRUE | AP106: TRUE | AQ106: TRUE | AR106: TRUE | AS106: TRUE | AT106: TRUE | AU106: TRUE | AV106: TRUE | AW106: TRUE | AX106: TRUE | AY106: TRUE | AZ106: TRUE | BA106: TRUE | BB106: TRUE | BC106: TRUE | BD106: TRUE | BE106: TRUE | BF106: TRUE | BG106: TRUE | BH106: TRUE | BI106: TRUE | BJ106: TRUE
A107: 27 | B107: Vegetarian | C107: CS | G107: 0.0166 | H107: 0.0125 | I107: 0.0127 | J107: 0.0162 | AK107: TRUE | AL107: TRUE | AM107: TRUE | AN107: TRUE | AO107: TRUE | AP107: TRUE | AQ107: TRUE | AR107: TRUE | AS107: TRUE | AT107: TRUE | AU107: TRUE | AV107: TRUE | AW107: TRUE | AX107: TRUE | AY107: TRUE | AZ107: TRUE | BA107: TRUE | BB107: TRUE | BC107: TRUE | BD107: TRUE | BE107: TRUE | BF107: TRUE | BG107: TRUE | BH107: TRUE | BI107: TRUE | BJ107: TRUE
A108: 28 | B108: Shrimp | C108: Mediterranean | H108: 0.0319 | I108: 0.0325 | J108: 0.0324 | AO108: TRUE | AP108: TRUE | AQ108: TRUE | AR108: TRUE | AS108: TRUE | AT108: TRUE | AU108: TRUE | AV108: TRUE | AW108: TRUE | AX108: TRUE | AY108: TRUE | AZ108: TRUE | BA108: TRUE | BB108: TRUE | BC108: TRUE | BD108: TRUE | BE108: TRUE | BF108: TRUE | BG108: TRUE | BH108: TRUE | BI108: TRUE | BJ108: TRUE
A109: 29 | B109: Lamb | C109: Athlete | H109: 0.0273 | I109: 0.0278 | J109: 0.0278 | AO109: TRUE | AP109: TRUE | AQ109: TRUE | AR109: TRUE | AS109: TRUE | AT109: TRUE | AU109: TRUE | AV109: TRUE | AW109: TRUE | AX109: TRUE | AY109: TRUE | AZ109: TRUE | BA109: TRUE | BB109: TRUE | BC109: TRUE | BD109: TRUE | BE109: TRUE | BF109: TRUE | BG109: TRUE | BH109: TRUE | BI109: TRUE | BJ109: TRUE
A110: 30 | B110: Lamb | C110: Mediterranean | H110: 0.0273 | I110: 0.0278 | J110: 0.0278 | AO110: TRUE | AP110: TRUE | AQ110: TRUE | AR110: TRUE | AS110: TRUE | AT110: TRUE | AU110: TRUE | AV110: TRUE | AW110: TRUE | AX110: TRUE | AY110: TRUE | AZ110: TRUE | BA110: TRUE | BB110: TRUE | BC110: TRUE | BD110: TRUE | BE110: TRUE | BF110: TRUE | BG110: TRUE | BH110: TRUE | BI110: TRUE | BJ110: TRUE
A111: 31 | B111: Beef | I111: 0.0249 | J111: 0.0231 | AS111: TRUE | AT111: TRUE | AU111: TRUE | AV111: TRUE | AW111: TRUE | AX111: TRUE | AY111: TRUE | AZ111: TRUE | BA111: TRUE | BB111: TRUE | BC111: TRUE | BD111: TRUE | BE111: TRUE | BF111: TRUE | BG111: TRUE | BH111: TRUE | BI111: TRUE | BJ111: TRUE
A112: 32 | B112: Beef | I112: 0.0249 | J112: 0.0231 | AS112: TRUE | AT112: TRUE | AU112: TRUE | AV112: TRUE | AW112: TRUE | AX112: TRUE | AY112: TRUE | AZ112: TRUE | BA112: TRUE | BB112: TRUE | BC112: TRUE | BD112: TRUE | BE112: TRUE | BF112: TRUE | BG112: TRUE | BH112: TRUE | BI112: TRUE | BJ112: TRUE
A113: 33 | B113: Vegetarian | I113: 0.015 | J113: 0.0162 | AS113: TRUE | AT113: TRUE | AU113: TRUE | AV113: TRUE | AW113: TRUE | AX113: TRUE | AY113: TRUE | AZ113: TRUE | BA113: TRUE | BB113: TRUE | BC113: TRUE | BD113: TRUE | BE113: TRUE | BF113: TRUE | BG113: TRUE | BH113: TRUE | BI113: TRUE | BJ113: TRUE
A114: 34 | B114: Vegetarian | J114: 0.0162 | BG114: TRUE | BH114: TRUE | BI114: TRUE | BJ114: TRUE
A115: 35 | B115: Vegetarian | J115: 0.0162 | BG115: TRUE | BH115: TRUE | BI115: TRUE | BJ115: TRUE
A116: 36 | B116: White Fish | J116: 0.0324 | BG116: TRUE | BH116: TRUE | BI116: TRUE | BJ116: TRUE
...

Sheet ARCHIVED - Meal Selection
L1: DKSE | O1: DE | R1: BENL
A2: Week | B2: Code | C2: NEW Code | D2: Name | E2: Protein | F2: Preference | G2: Slot | H2: Slot Volume | I2: Total Verden Volume | J2: Safety Stock | K2: Total Volume DKSE | L2: Slot Volume Assumptions | M2: Share | N2: Total Volume DE | O2: Slot Volume Assumptions | P2: DE | Q2: Total Volume BENL | R2: Slot Volume Assumptions | S2: BENL
A3: 2026-W17 | B3: FE1346B | C3: FV1346A | D3: Parmesan & Garlic Cream Shredded Beef | E3: Fish / Seafood / Beef | F3: =vlookup(G3,'Slot Selection'!A:C,3,false) -> P+ | G3: 4 | H3: =vlookup(G3,'Slot Selection'!A:D,4,false) -> 0.0825 | I3: 4931 | K3: =vlookup(A3,Overview!B:J,7,false)+vlookup(A3,Overview!B:J,8,false) -> 25463 | L3: =K3*H3*M3 -> 1890.6278 | M3: 0.9 | N3: =vlookup(A3,Overview!B:J,9,false) -> 21910 | O3: =N3*H3*P3 -> 1626.8175 | P3: 0.9 | Q3: =vlookup(A3,Overview!B:G,5,false)+vlookup(A3,Overview!B:G,6,false) -> 47062 | R3: =Q3*H3*S3 -> 0 | S3: 0
A4: 2026-W17 | B4: FE0035F | C4: FV0035A | D4: Salmon with pesto | E4: =vlookup(G4,'Slot Selection'!A:B,2,false) -> Fish / Seafood | F4: =vlookup(G4,'Slot Selection'!A:C,3,false) -> Keto | G4: 6 | H4: =vlookup(G4,'Slot Selection'!A:D,4,false) -> 0.0739 | I4: 3005 | K4: =vlookup(A4,Overview!B:J,7,false)+vlookup(A4,Overview!B:J,8,false) -> 25463 | L4: =K4*H4*M4 -> 1693.5441 | M4: 0.9 | N4: =vlookup(A4,Overview!B:J,9,false) -> 21910 | O4: =N4*H4*P4 -> 1457.2341 | P4: 0.9 | Q4: =vlookup(A4,Overview!B:G,5,false)+vlookup(A4,Overview!B:G,6,false) -> 47062 | R4: =Q4*H4*S4 -> 0 | S4: 0
A5: 2026-W17 | B5: FE4053A | C5: FV4053A | D5: Gochugaru Chicken | E5: =vlookup(G5,'Slot Selection'!A:B,2,false) -> Chicken | F5: =vlookup(G5,'Slot Selection'!A:C,3,false) -> Keto | G5: 7 | H5: =vlookup(G5,'Slot Selection'!A:D,4,false) -> 0.0622 | I5: 2675 | K5: =vlookup(A5,Overview!B:J,7,false)+vlookup(A5,Overview!B:J,8,false) -> 25463 | L5: =K5*H5*M5 -> 1425.4187 | M5: 0.9 | N5: =vlookup(A5,Overview!B:J,9,false) -> 21910 | O5: =N5*H5*P5 -> 1226.5218 | P5: 0.9 | Q5: =vlookup(A5,Overview!B:G,5,false)+vlookup(A5,Overview!B:G,6,false) -> 47062 | R5: =Q5*H5*S5 -> 0 | S5: 0
A6: 2026-W17 | B6: FE4064A | C6: FV4064A | D6: Ginger Garlic Grilled Chicken | E6: =vlookup(G6,'Slot Selection'!A:B,2,false) -> Flexible Slot | F6: =vlookup(G6,'Slot Selection'!A:C,3,false) -> Flexible Slot | G6: 14 | H6: =vlookup(G6,'Slot Selection'!A:D,4,false) -> 0.0317 | I6: 863 | K6: =vlookup(A6,Overview!B:J,7,false)+vlookup(A6,Overview!B:J,8,false) -> 25463 | L6: =K6*H6*M6 -> 726.45939 | M6: 0.9 | N6: =vlookup(A6,Overview!B:J,9,false) -> 21910 | O6: =N6*H6*P6 -> 625.0923 | P6: 0.9 | Q6: =vlookup(A6,Overview!B:G,5,false)+vlookup(A6,Overview!B:G,6,false) -> 47062 | R6: =Q6*H6*S6 -> 0 | S6: 0
A7: 2026-W17 | B7: FE0472A | C7: FV0472A | D7: Indian Butter Chicken | E7: =vlookup(G7,'Slot Selection'!A:B,2,false) -> Flexible Slot | F7: =vlookup(G7,'Slot Selection'!A:C,3,false) -> Flexible Slot | G7: 16 | H7: =vlookup(G7,'Slot Selection'!A:D,4,false) -> 0.03 | I7: 938 | K7: =vlookup(A7,Overview!B:J,7,false)+vlookup(A7,Overview!B:J,8,false) -> 25463 | L7: =K7*H7*M7 -> 687.501 | M7: 0.9 | N7: =vlookup(A7,Overview!B:J,9,false) -> 21910 | O7: =N7*H7*P7 -> 591.57 | P7: 0.9 | Q7: =vlookup(A7,Overview!B:G,5,false)+vlookup(A7,Overview!B:G,6,false) -> 47062 | R7: =Q7*H7*S7 -> 0 | S7: 0
A8: 2026-W18 | B8: FE4063A | C8: FV4063A | D8: Cheddar pulled beef | E8: =vlookup(G8,'Slot Selection'!A:B,2,false) -> Beef | F8: =vlookup(G8,'Slot Selection'!A:C,3,false) -> Keto | G8: 3 | H8: =vlookup(G8,'Slot Selection'!A:E,4,false) -> 0.097 | I8: =1206+600 -> 1806 | J8: 600 | K8: =vlookup(A8,Overview!B:J,7,false)+vlookup(A8,Overview!B:J,8,false) -> 26941 | L8: =K8*H8*M8 -> 783.9831 | M8: 0.3 | N8: =vlookup(A8,Overview!B:J,9,false) -> 22089 | O8: =N8*H8*P8 -> 642.7899 | P8: 0.3 | Q8: =vlookup(A8,Overview!B:G,5,false)+vlookup(A8,Overview!B:G,6,false) -> 47825 | R8: =Q8*H8*S8 -> 0 | S8: 0
A9: 2026-W18 | B9: FE4039A | C9: FV4039A | D9: Salmon in creamy gochugaru sauce | E9: =vlookup(G9,'Slot Selection'!A:B,2,false) -> Fish / Seafood | F9: =vlookup(G9,'Slot Selection'!A:C,3,false) -> Keto | G9: 6 | H9: =vlookup(G9,'Slot Selection'!A:E,4,false) -> 0.0739 | I9: =1711+600 -> 2311 | J9: 600 | K9: =vlookup(A9,Overview!B:J,7,false)+vlookup(A9,Overview!B:J,8,false) -> 26941 | L9: =K9*H9*M9 -> 995.46995 | M9: 0.5 | N9: =vlookup(A9,Overview!B:J,9,false) -> 22089 | O9: =N9*H9*P9 -> 816.18855 | P9: 0.5 | Q9: =vlookup(A9,Overview!B:G,5,false)+vlookup(A9,Overview!B:G,6,false) -> 47825 | R9: =Q9*H9*S9 -> 0 | S9: 0
A10: 2026-W18 | B10: FE0601B | C10: FV0601A | D10: Mozzarella Burger & Roasted Potatoes | E10: =vlookup(G10,'Slot Selection'!A:B,2,false) -> Flexible Slot | F10: =vlookup(G10,'Slot Selection'!A:C,3,false) -> Flexible Slot | G10: 16 | H10: =vlookup(G10,'Slot Selection'!A:E,4,false) -> 0.03 | I10: =3508+600 -> 4108 | J10: 600 | K10: =vlookup(A10,Overview!B:J,7,false)+vlookup(A10,Overview!B:J,8,false) -> 26941 | L10: =K10*H10*M10 -> 808.23 | M10: 1 | N10: =vlookup(A10,Overview!B:J,9,false) -> 22089 | O10: =N10*H10*P10 -> 662.67 | P10: 1 | Q10: =vlookup(A10,Overview!B:G,5,false)+vlookup(A10,Overview!B:G,6,false) -> 47825 | R10: =Q10*H10*S10 -> 1434.75 | S10: 1
A11: 2026-W19 | B11: FE0413F | C11: FV0413A | D11: Braised beef in herby jus | E11: =vlookup(G11,'Slot Selection'!A:B,2,false) -> Beef | F11: =vlookup(G11,'Slot Selection'!A:C,3,false) -> Keto | G11: 3 | H11: =vlookup(G11,'Slot Selection'!A:E,5,false) -> 0.0808 | I11: 3692 | K11: =vlookup(A11,Overview!B:J,7,false)+vlookup(A11,Overview!B:J,8,false) -> 24747.021 | L11: =K11*H11*M11 -> 1999.5593 | M11: 1 | N11: =vlookup(A11,Overview!B:J,9,false) -> 19881.425 | O11: =N11*H11*P11 -> 1606.4192 | P11: 1 | Q11: =vlookup(A11,Overview!B:G,5,false)+vlookup(A11,Overview!B:G,6,false) -> 46935.599 | R11: =Q11*H11*S11 -> 0 | S11: 0
A12: 2026-W19 | B12: FE4009A | C12: FV4009A | D12: Salmon with a mustard dill sauce | E12: =vlookup(G12,'Slot Selection'!A:B,2,false) -> Fish / Seafood / Beef | F12: =vlookup(G12,'Slot Selection'!A:C,3,false) -> P+ | G12: 4 | H12: =vlookup(G12,'Slot Selection'!A:E,5,false) -> 0.0632 | I12: 5410 | K12: =vlookup(A12,Overview!B:J,7,false)+vlookup(A12,Overview!B:J,8,false) -> 24747.021 | L12: =K12*H12*M12 -> 1564.0117 | M12: 1 | N12: =vlookup(A12,Overview!B:J,9,false) -> 19881.425 | O12: =N12*H12*P12 -> 1256.5061 | P12: 1 | Q12: =vlookup(A12,Overview!B:G,5,false)+vlookup(A12,Overview!B:G,6,false) -> 46935.599 | R12: =Q12*H12*S12 -> 0 | S12: 0
A13: 2026-W19 | B13: FE0972B | C13: FV0972A | D13: Salmon Piccata | E13: =vlookup(G13,'Slot Selection'!A:B,2,false) -> Fish / Seafood | F13: =vlookup(G13,'Slot Selection'!A:C,3,false) -> Keto | G13: 6 | H13: =vlookup(G13,'Slot Selection'!A:E,5,false) -> 0.0566 | I13: 3605 | K13: =vlookup(A13,Overview!B:J,7,false)+vlookup(A13,Overview!B:J,8,false) -> 24747.021 | L13: =K13*H13*M13 -> 1400.6814 | M13: 1 | N13: =vlookup(A13,Overview!B:J,9,false) -> 19881.425 | O13: =N13*H13*P13 -> 1125.2887 | P13: 1 | Q13: =vlookup(A13,Overview!B:G,5,false)+vlookup(A13,Overview!B:G,6,false) -> 46935.599 | R13: =Q13*H13*S13 -> 0 | S13: 0
A14: 2026-W19 | B14: FE0970B | C14: FV0970A | D14: Caramelized Onion & Emmental Fondue Chicken | E14: =vlookup(G14,'Slot Selection'!A:B,2,false) -> Chicken | F14: =vlookup(G14,'Slot Selection'!A:C,3,false) -> Keto | G14: 7 | H14: =vlookup(G14,'Slot Selection'!A:E,5,false) -> 0.0581 | I14: 3192 | K14: =vlookup(A14,Overview!B:J,7,false)+vlookup(A14,Overview!B:J,8,false) -> 24747.021 | L14: =K14*H14*M14 -> 1437.8019 | M14: 1 | N14: =vlookup(A14,Overview!B:J,9,false) -> 19881.425 | O14: =N14*H14*P14 -> 1155.1108 | P14: 1 | Q14: =vlookup(A14,Overview!B:G,5,false)+vlookup(A14,Overview!B:G,6,false) -> 46935.599 | R14: =Q14*H14*S14 -> 0 | S14: 0
A15: 2026-W20 | B15: FE0035F | C15: FV0035A | D15: Salmon with pesto | E15: =vlookup(G15,'Slot Selection'!A:B,2,false) -> Fish / Seafood | F15: =vlookup(G15,'Slot Selection'!A:C,3,false) -> Keto | G15: 6 | H15: =vlookup(G15,'Slot Selection'!A:E,5,false) -> 0.0566 | I15: 6106 | K15: =vlookup(A15,Overview!B:J,7,false)+vlookup(A15,Overview!B:J,8,false) -> 25138.615 | L15: =K15*H15*M15 -> 1422.8456 | M15: 1 | N15: =vlookup(A15,Overview!B:J,9,false) -> 20623.389 | O15: =N15*H15*P15 -> 1167.2838 | P15: 1 | Q15: =vlookup(A15,Overview!B:G,5,false)+vlookup(A15,Overview!B:G,6,false) -> 50558.574 | R15: =Q15*H15*S15 -> 2861.6153 | S15: 1
A16: 2026-W20 | B16: FE0472A | C16: FV0472A | D16: Indian Butter Chicken | E16: =vlookup(G16,'Slot Selection'!A:B,2,false) -> Chicken | F16: =vlookup(G16,'Slot Selection'!A:C,3,false) -> Keto | G16: 7 | H16: =vlookup(G16,'Slot Selection'!A:E,5,false) -> 0.0581 | I16: 5453 | K16: =vlookup(A16,Overview!B:J,7,false)+vlookup(A16,Overview!B:J,8,false) -> 25138.615 | L16: =K16*H16*M16 -> 1460.5535 | M16: 1 | N16: =vlookup(A16,Overview!B:J,9,false) -> 20623.389 | O16: =N16*H16*P16 -> 1198.2189 | P16: 1 | Q16: =vlookup(A16,Overview!B:G,5,false)+vlookup(A16,Overview!B:G,6,false) -> 50558.574 | R16: =Q16*H16*S16 -> 2937.4531 | S16: 1
A17: 2026-W20 | B17: FE0024E | C17: FE0024A | D17: Chicken in tomato cream sauce | E17: =vlookup(G17,'Slot Selection'!A:B,2,false) -> Chicken | F17: =vlookup(G17,'Slot Selection'!A:C,3,false) -> Keto | G17: 8 | H17: =vlookup(G17,'Slot Selection'!A:E,5,false) -> 0.0632 | I17: 2110 | K17: =vlookup(A17,Overview!B:J,7,false)+vlookup(A17,Overview!B:J,8,false) -> 25138.615 | L17: =K17*H17*M17 -> 1588.7605 | M17: 1 | N17: =vlookup(A17,Overview!B:J,9,false) -> 20623.389 | O17: =N17*H17*P17 -> 1303.3982 | P17: 1 | Q17: =vlookup(A17,Overview!B:G,5,false)+vlookup(A17,Overview!B:G,6,false) -> 50558.574 | R17: =Q17*H17*S17 -> 0 | S17: 0
A18: 2026-W20 | B18: FE4006A | C18: FV4006A | D18: Pork tenderloin in sundried tomato sauce | E18: =vlookup(G18,'Slot Selection'!A:B,2,false) -> Pork | F18: =vlookup(G18,'Slot Selection'!A:C,3,false) -> Flexible Slot | G18: 11 | H18: =vlookup(G18,'Slot Selection'!A:E,5,false) -> 0.0215 | I18: 754 | K18: =vlookup(A18,Overview!B:J,7,false)+vlookup(A18,Overview!B:J,8,false) -> 25138.615 | L18: =K18*H18*M18 -> 540.48022 | M18: 1 | N18: =vlookup(A18,Overview!B:J,9,false) -> 20623.389 | O18: =N18*H18*P18 -> 443.40285 | P18: 1 | Q18: =vlookup(A18,Overview!B:G,5,false)+vlookup(A18,Overview!B:G,6,false) -> 50558.574 | R18: =Q18*H18*S18 -> 0 | S18: 0
A19: 2026-W20 | B19: FE0281E | C19: FV0281A | D19: Spicy citrus salmon | E19: =vlookup(G19,'Slot Selection'!A:B,2,false) -> Fish / Seafood | F19: =vlookup(G19,'Slot Selection'!A:C,3,false) -> P+ | G19: 12 | H19: =vlookup(G19,'Slot Selection'!A:E,5,false) -> 0.0366 | I19: 6087 | K19: =vlookup(A19,Overview!B:J,7,false)+vlookup(A19,Overview!B:J,8,false) -> 25138.615 | L19: =K19*H19*M19 -> 920.0733 | M19: 1 | N19: =vlookup(A19,Overview!B:J,9,false) -> 20623.389 | O19: =N19*H19*P19 -> 754.81602 | P19: 1 | Q19: =vlookup(A19,Overview!B:G,5,false)+vlookup(A19,Overview!B:G,6,false) -> 50558.574 | R19: =Q19*H19*S19 -> 1850.4438 | S19: 1
A20: 2026-W20 | B20: FE1404A | C20: FV1404A | D20: Bulgogi Shredded Beef Bowl | E20: =vlookup(G20,'Slot Selection'!A:B,2,false) -> Flexible Slot | F20: =vlookup(G20,'Slot Selection'!A:C,3,false) -> P+ | G20: 13 | H20: =vlookup(G20,'Slot Selection'!A:E,5,false) -> 0.0547 | I20: 7004 | K20: =vlookup(A20,Overview!B:J,7,false)+vlookup(A20,Overview!B:J,8,false) -> 25138.615 | L20: =K20*H20*M20 -> 1375.0822 | M20: 1 | N20: =vlookup(A20,Overview!B:J,9,false) -> 20623.389 | O20: =N20*H20*P20 -> 1128.0994 | P20: 1 | Q20: =vlookup(A20,Overview!B:G,5,false)+vlookup(A20,Overview!B:G,6,false) -> 50558.574 | R20: =Q20*H20*S20 -> 2765.554 | S20: 1
A21: 2026-W20 | B21: FE1646A | C21: FV1646A | D21: Shrimp with Lemon Garlic Sauce & Spanakopita Style Rice | E21: =vlookup(G21,'Slot Selection'!A:B,2,false) -> Flexible Slot | F21: =vlookup(G21,'Slot Selection'!A:C,3,false) -> Flexible Slot | G21: 14 | H21: =vlookup(G21,'Slot Selection'!A:E,5,false) -> 0.0317 | I21: 2574 | K21: =vlookup(A21,Overview!B:J,7,false)+vlookup(A21,Overview!B:J,8,false) -> 25138.615 | L21: =K21*H21*M21 -> 796.89409 | M21: 1 | N21: =vlookup(A21,Overview!B:J,9,false) -> 20623.389 | O21: =N21*H21*P21 -> 653.76142 | P21: 1 | Q21: =vlookup(A21,Overview!B:G,5,false)+vlookup(A21,Overview!B:G,6,false) -> 50558.574 | R21: =Q21*H21*S21 -> 1602.7068 | S21: 1
A22: 2026-W21 | B22: FE0224D | C22: FV0224A | D22: Chicken à la Florentine | E22: =vlookup(G22,'Slot Selection'!A:B,2,false) -> Chicken | F22: =vlookup(G22,'Slot Selection'!A:C,3,false) -> CS | G22: 2 | H22: =vlookup(G22,'Slot Selection'!A:E,5,false) -> 0.0964 | I22: 7543 | K22: =vlookup(A22,Overview!B:J,7,false)+vlookup(A22,Overview!B:J,8,false) -> 24953.306 | L22: =K22*H22*M22 -> 2405.4987 | M22: 1 | N22: =vlookup(A22,Overview!B:J,9,false) -> 20256.396 | O22: =N22*H22*P22 -> 1952.7166 | P22: 1 | Q22: =vlookup(A22,Overview!B:G,5,false)+vlookup(A22,Overview!B:G,6,false) -> 49397.361 | R22: =Q22*H22*S22 -> 4761.9056 | S22: 1
... A32: 2026-W21 | B32: xxx | C32: xxx | D32: Crusted Protein Placeholder | E32: =vlookup(G32,'Slot Selection'!A:B,2,false) -> Beef | F32: =vlookup(G32,'Slot Selection'!A:C,3,false) -> Athlete | G32: 20 | H32: =vlookup(G32,'Slot Selection'!A:E,5,false) -> 0.0215 | I32: 2171 | K32: =vlookup(A32,Overview!B:J,7,false)+vlookup(A32,Overview!B:J,8,false) -> 24953.306 | L32: =K32*H32*M32 -> 536.49607 | M32: 1 | N32: =vlookup(A32,Overview!B:J,9,false) -> 20256.396 | O32: =N32*H32*P32 -> 435.51251 | P32: 1 | Q32: =vlookup(A32,Overview!B:G,5,false)+vlookup(A32,Overview!B:G,6,false) -> 49397.361 | R32: =Q32*H32*S32 -> 1062.0433 | S32: 1
E33: =vlookup(G33,'Slot Selection'!A:B,2,false) -> #N/A | F33: =vlookup(G33,'Slot Selection'!A:C,3,false) -> #N/A | H33: =vlookup(G33,'Slot Selection'!A:E,5,false) -> #N/A | I33: =L33+O33+R33 -> #N/A | K33: =vlookup(A33,Overview!B:J,7,false)+vlookup(A33,Overview!B:J,8,false) -> #N/A | L33: =K33*H33*M33 -> #N/A | M33: 1 | N33: =vlookup(A33,Overview!B:J,9,false) -> #N/A | O33: =N33*H33*P33 -> #N/A | P33: 1 | Q33: =vlookup(A33,Overview!B:G,5,false)+vlookup(A33,Overview!B:G,6,false) -> #N/A | R33: =Q33*H33*S33 -> #N/A | S33: 1
E34: =vlookup(G34,'Slot Selection'!A:B,2,false) -> #N/A | F34: =vlookup(G34,'Slot Selection'!A:C,3,false) -> #N/A | H34: =vlookup(G34,'Slot Selection'!A:E,5,false) -> #N/A | I34: =L34+O34+R34 -> #N/A | K34: =vlookup(A34,Overview!B:J,7,false)+vlookup(A34,Overview!B:J,8,false) -> #N/A | L34: =K34*H34*M34 -> #N/A | M34: 1 | N34: =vlookup(A34,Overview!B:J,9,false) -> #N/A | O34: =N34*H34*P34 -> #N/A | P34: 1 | Q34: =vlookup(A34,Overview!B:G,5,false)+vlookup(A34,Overview!B:G,6,false) -> #N/A | R34: =Q34*H34*S34 -> #N/A | S34: 1
E35: =vlookup(G35,'Slot Selection'!A:B,2,false) -> #N/A | F35: =vlookup(G35,'Slot Selection'!A:C,3,false) -> #N/A | H35: =vlookup(G35,'Slot Selection'!A:E,5,false) -> #N/A | I35: =L35+O35+R35 -> #N/A | K35: =vlookup(A35,Overview!B:J,7,false)+vlookup(A35,Overview!B:J,8,false) -> #N/A | L35: =K35*H35*M35 -> #N/A | M35: 1 | N35: =vlookup(A35,Overview!B:J,9,false) -> #N/A | O35: =N35*H35*P35 -> #N/A | P35: 1 | Q35: =vlookup(A35,Overview!B:G,5,false)+vlookup(A35,Overview!B:G,6,false) -> #N/A | R35: =Q35*H35*S35 -> #N/A | S35: 1
E36: =vlookup(G36,'Slot Selection'!A:B,2,false) -> #N/A | F36: =vlookup(G36,'Slot Selection'!A:C,3,false) -> #N/A | H36: =vlookup(G36,'Slot Selection'!A:E,5,false) -> #N/A | I36: =L36+O36+R36 -> #N/A | K36: =vlookup(A36,Overview!B:J,7,false)+vlookup(A36,Overview!B:J,8,false) -> #N/A | L36: =K36*H36*M36 -> #N/A | M36: 1 | N36: =vlookup(A36,Overview!B:J,9,false) -> #N/A | O36: =N36*H36*P36 -> #N/A | P36: 1 | Q36: =vlookup(A36,Overview!B:G,5,false)+vlookup(A36,Overview!B:G,6,false) -> #N/A | R36: =Q36*H36*S36 -> #N/A | S36: 1
E37: =vlookup(G37,'Slot Selection'!A:B,2,false) -> #N/A | F37: =vlookup(G37,'Slot Selection'!A:C,3,false) -> #N/A | H37: =vlookup(G37,'Slot Selection'!A:E,5,false) -> #N/A | I37: =L37+O37+R37 -> #N/A | K37: =vlookup(A37,Overview!B:J,7,false)+vlookup(A37,Overview!B:J,8,false) -> #N/A | L37: =K37*H37*M37 -> #N/A | M37: 1 | N37: =vlookup(A37,Overview!B:J,9,false) -> #N/A | O37: =N37*H37*P37 -> #N/A | P37: 1 | Q37: =vlookup(A37,Overview!B:G,5,false)+vlookup(A37,Overview!B:G,6,false) -> #N/A | R37: =Q37*H37*S37 -> #N/A | S37: 1
E38: =vlookup(G38,'Slot Selection'!A:B,2,false) -> #N/A | F38: =vlookup(G38,'Slot Selection'!A:C,3,false) -> #N/A | H38: =vlookup(G38,'Slot Selection'!A:E,5,false) -> #N/A | I38: =L38+O38+R38 -> #N/A | K38: =vlookup(A38,Overview!B:J,7,false)+vlookup(A38,Overview!B:J,8,false) -> #N/A | L38: =K38*H38*M38 -> #N/A | M38: 1 | N38: =vlookup(A38,Overview!B:J,9,false) -> #N/A | O38: =N38*H38*P38 -> #N/A | P38: 1 | Q38: =vlookup(A38,Overview!B:G,5,false)+vlookup(A38,Overview!B:G,6,false) -> #N/A | R38: =Q38*H38*S38 -> #N/A | S38: 1
E39: =vlookup(G39,'Slot Selection'!A:B,2,false) -> #N/A | F39: =vlookup(G39,'Slot Selection'!A:C,3,false) -> #N/A | H39: =vlookup(G39,'Slot Selection'!A:E,5,false) -> #N/A | I39: =L39+O39+R39 -> #N/A | K39: =vlookup(A39,Overview!B:J,7,false)+vlookup(A39,Overview!B:J,8,false) -> #N/A | L39: =K39*H39*M39 -> #N/A | M39: 1 | N39: =vlookup(A39,Overview!B:J,9,false) -> #N/A | O39: =N39*H39*P39 -> #N/A | P39: 1 | Q39: =vlookup(A39,Overview!B:G,5,false)+vlookup(A39,Overview!B:G,6,false) -> #N/A | R39: =Q39*H39*S39 -> #N/A | S39: 1
E40: =vlookup(G40,'Slot Selection'!A:B,2,false) -> #N/A | F40: =vlookup(G40,'Slot Selection'!A:C,3,false) -> #N/A | H40: =vlookup(G40,'Slot Selection'!A:E,5,false) -> #N/A | I40: =L40+O40+R40 -> #N/A | K40: =vlookup(A40,Overview!B:J,7,false)+vlookup(A40,Overview!B:J,8,false) -> #N/A | L40: =K40*H40*M40 -> #N/A | M40: 1 | N40: =vlookup(A40,Overview!B:J,9,false) -> #N/A | O40: =N40*H40*P40 -> #N/A | P40: 1 | Q40: =vlookup(A40,Overview!B:G,5,false)+vlookup(A40,Overview!B:G,6,false) -> #N/A | R40: =Q40*H40*S40 -> #N/A | S40: 1
E41: =vlookup(G41,'Slot Selection'!A:B,2,false) -> #N/A | F41: =vlookup(G41,'Slot Selection'!A:C,3,false) -> #N/A | H41: =vlookup(G41,'Slot Selection'!A:E,5,false) -> #N/A | I41: =L41+O41+R41 -> #N/A | K41: =vlookup(A41,Overview!B:J,7,false)+vlookup(A41,Overview!B:J,8,false) -> #N/A | L41: =K41*H41*M41 -> #N/A | M41: 1 | N41: =vlookup(A41,Overview!B:J,9,false) -> #N/A | O41: =N41*H41*P41 -> #N/A | P41: 1 | Q41: =vlookup(A41,Overview!B:G,5,false)+vlookup(A41,Overview!B:G,6,false) -> #N/A | R41: =Q41*H41*S41 -> #N/A | S41: 1
E42: =vlookup(G42,'Slot Selection'!A:B,2,false) -> #N/A | F42: =vlookup(G42,'Slot Selection'!A:C,3,false) -> #N/A | H42: =vlookup(G42,'Slot Selection'!A:E,5,false) -> #N/A | I42: =L42+O42+R42 -> #N/A | K42: =vlookup(A42,Overview!B:J,7,false)+vlookup(A42,Overview!B:J,8,false) -> #N/A | L42: =K42*H42*M42 -> #N/A | M42: 1 | N42: =vlookup(A42,Overview!B:J,9,false) -> #N/A | O42: =N42*H42*P42 -> #N/A | P42: 1 | Q42: =vlookup(A42,Overview!B:G,5,false)+vlookup(A42,Overview!B:G,6,false) -> #N/A | R42: =Q42*H42*S42 -> #N/A | S42: 1
E43: =vlookup(G43,'Slot Selection'!A:B,2,false) -> #N/A | F43: =vlookup(G43,'Slot Selection'!A:C,3,false) -> #N/A | H43: =vlookup(G43,'Slot Selection'!A:E,5,false) -> #N/A | I43: =L43+O43+R43 -> #N/A | K43: =vlookup(A43,Overview!B:J,7,false)+vlookup(A43,Overview!B:J,8,false) -> #N/A | L43: =K43*H43*M43 -> #N/A | M43: 1 | N43: =vlookup(A43,Overview!B:J,9,false) -> #N/A | O43: =N43*H43*P43 -> #N/A | P43: 1 | Q43: =vlookup(A43,Overview!B:G,5,false)+vlookup(A43,Overview!B:G,6,false) -> #N/A | R43: =Q43*H43*S43 -> #N/A | S43: 1
E44: =vlookup(G44,'Slot Selection'!A:B,2,false) -> #N/A | F44: =vlookup(G44,'Slot Selection'!A:C,3,false) -> #N/A | H44: =vlookup(G44,'Slot Selection'!A:E,5,false) -> #N/A | I44: =L44+O44+R44 -> #N/A | K44: =vlookup(A44,Overview!B:J,7,false)+vlookup(A44,Overview!B:J,8,false) -> #N/A | L44: =K44*H44*M44 -> #N/A | M44: 1 | N44: =vlookup(A44,Overview!B:J,9,false) -> #N/A | O44: =N44*H44*P44 -> #N/A | P44: 1 | Q44: =vlookup(A44,Overview!B:G,5,false)+vlookup(A44,Overview!B:G,6,false) -> #N/A | R44: =Q44*H44*S44 -> #N/A | S44: 1
... E51: =vlookup(G51,'Slot Selection'!A:B,2,false) -> #N/A | F51: =vlookup(G51,'Slot Selection'!A:C,3,false) -> #N/A | H51: =vlookup(G51,'Slot Selection'!A:E,5,false) -> #N/A | I51: =L51+O51+R51 -> #N/A | K51: =vlookup(A51,Overview!B:J,7,false)+vlookup(A51,Overview!B:J,8,false) -> #N/A | L51: =K51*H51*M51 -> #N/A | M51: 1 | N51: =vlookup(A51,Overview!B:J,9,false) -> #N/A | O51: =N51*H51*P51 -> #N/A | P51: 1 | Q51: =vlookup(A51,Overview!B:G,5,false)+vlookup(A51,Overview!B:G,6,false) -> #N/A | R51: =Q51*H51*S51 -> #N/A | S51: 1

Sheet Meal Selection
P1: Verden Share | S1: Verden Absolute
A2: HF Week | B2: Code | C2: Preference | D2: Recipe Name | E2: Week | F2: Slot BENL | G2: Slot DKSE | H2: Slot DE | I2: BENL Vol | J2: NORD Vol | K2: DE Vol | L2: Convini DE | M2: Total Volume BNL | N2: Total Volume NORD | O2: Total Volume DE | P2: BENL | Q2: DKSE | R2: DE | S2: BENL | T2: NORD | U2: DE | V2: Total Verden Volume | W2: Locked Values | X2: Production Buffer
A3: =if(E3="","", CONCAT("2026-",E3)) -> 2026-W17 | B3: =IFERROR(__xludf.DUMMYFUNCTION("FILTER('Volume Split Up-To-Date'!$A$3:$T1000, ('Volume Split Up-To-Date'!$O$3:$O1000 + 'Volume Split Up-To-Date'!$P$3:P1000 + 'Volume Split Up-To-Date'!$Q$3:$Q1000) > 0)"),"FE1346B") -> FE1346B | C3: =IFERROR(__xludf.DUMMYFUNCTION("""COMPUTED_VALUE"""),"P+") -> P+ | D3: =IFERROR(__xludf.DUMMYFUNCTION("""COMPUTED_VALUE"""),"Parmesan & Garlic Cream Pulled Beef") -> Parmesan & Garlic Cream Pulled Beef | E3: =IFERROR(__xludf.DUMMYFUNCTION("""COMPUTED_VALUE"""),"W17") -> W17 | F3: =IFERROR(__xludf.DUMMYFUNCTION("""COMPUTED_VALUE"""),404.0) -> 404 | G3: =IFERROR(__xludf.DUMMYFUNCTION("""COMPUTED_VALUE"""),604.0) -> 604 | H3: =IFERROR(__xludf.DUMMYFUNCTION("""COMPUTED_VALUE"""),304.0) -> 304 | I3: =IFERROR(__xludf.DUMMYFUNCTION("""COMPUTED_VALUE"""),6272.0) -> 6272 | J3: =IFERROR(__xludf.DUMMYFUNCTION("""COMPUTED_VALUE"""),3388.0) -> 3388 | K3: =IFERROR(__xludf.DUMMYFUNCTION("""COMPUTED_VALUE"""),2796.0) -> 2796 | M3: =IFERROR(__xludf.DUMMYFUNCTION("""COMPUTED_VALUE"""),6292.0) -> 6292 | N3: =IFERROR(__xludf.DUMMYFUNCTION("""COMPUTED_VALUE"""),3408.0) -> 3408 | O3: =IFERROR(__xludf.DUMMYFUNCTION("""COMPUTED_VALUE"""),2816.0) -> 2816 | P3: =IFERROR(__xludf.DUMMYFUNCTION("""COMPUTED_VALUE"""),0.0) -> 0 | Q3: =IFERROR(__xludf.DUMMYFUNCTION("""COMPUTED_VALUE"""),0.9) -> 0.9 | R3: =IFERROR(__xludf.DUMMYFUNCTION("""COMPUTED_VALUE"""),0.9) -> 0.9 | S3: =IFERROR(__xludf.DUMMYFUNCTION("""COMPUTED_VALUE"""),0.0) -> 0 | T3: =IFERROR(__xludf.DUMMYFUNCTION("""COMPUTED_VALUE"""),3067.2000000000003) -> 3067.2 | U3: =IFERROR(__xludf.DUMMYFUNCTION("""COMPUTED_VALUE"""),2534.4) -> 2534.4 | V3: =if(W3>0,W3,SUM(R3:T3)+X3) -> 4931 | W3: 4931
A4: =if(E4="","", CONCAT("2026-",E4)) -> 2026-W17 | B4: =IFERROR(__xludf.DUMMYFUNCTION("""COMPUTED_VALUE"""),"FE0035F") -> FE0035F | C4: =IFERROR(__xludf.DUMMYFUNCTION("""COMPUTED_VALUE"""),"Keto") -> Keto | D4: =IFERROR(__xludf.DUMMYFUNCTION("""COMPUTED_VALUE"""),"Salmon with pesto") -> Salmon with pesto | E4: =IFERROR(__xludf.DUMMYFUNCTION("""COMPUTED_VALUE"""),"W17") -> W17 | F4: =IFERROR(__xludf.DUMMYFUNCTION("""COMPUTED_VALUE"""),406.0) -> 406 | G4: =IFERROR(__xludf.DUMMYFUNCTION("""COMPUTED_VALUE"""),606.0) -> 606 | H4: =IFERROR(__xludf.DUMMYFUNCTION("""COMPUTED_VALUE"""),306.0) -> 306 | I4: =IFERROR(__xludf.DUMMYFUNCTION("""COMPUTED_VALUE"""),2991.0) -> 2991 | J4: =IFERROR(__xludf.DUMMYFUNCTION("""COMPUTED_VALUE"""),1672.0) -> 1672 | K4: =IFERROR(__xludf.DUMMYFUNCTION("""COMPUTED_VALUE"""),1791.0) -> 1791 | M4: =IFERROR(__xludf.DUMMYFUNCTION("""COMPUTED_VALUE"""),3011.0) -> 3011 | N4: =IFERROR(__xludf.DUMMYFUNCTION("""COMPUTED_VALUE"""),1692.0) -> 1692 | O4: =IFERROR(__xludf.DUMMYFUNCTION("""COMPUTED_VALUE"""),1811.0) -> 1811 | P4: =IFERROR(__xludf.DUMMYFUNCTION("""COMPUTED_VALUE"""),0.0) -> 0 | Q4: =IFERROR(__xludf.DUMMYFUNCTION("""COMPUTED_VALUE"""),0.9) -> 0.9 | R4: =IFERROR(__xludf.DUMMYFUNCTION("""COMPUTED_VALUE"""),0.9) -> 0.9 | S4: =IFERROR(__xludf.DUMMYFUNCTION("""COMPUTED_VALUE"""),0.0) -> 0 | T4: =IFERROR(__xludf.DUMMYFUNCTION("""COMPUTED_VALUE"""),1522.8) -> 1522.8 | U4: =IFERROR(__xludf.DUMMYFUNCTION("""COMPUTED_VALUE"""),1629.9) -> 1629.9 | V4: =if(W4>0,W4,SUM(R4:T4)+X4) -> 3005 | W4: 3005
A5: =if(E5="","", CONCAT("2026-",E5)) -> 2026-W17 | B5: =IFERROR(__xludf.DUMMYFUNCTION("""COMPUTED_VALUE"""),"FE4053A") -> FE4053A | C5: =IFERROR(__xludf.DUMMYFUNCTION("""COMPUTED_VALUE"""),"Keto") -> Keto | D5: =IFERROR(__xludf.DUMMYFUNCTION("""COMPUTED_VALUE"""),"Gochugaru Chicken") -> Gochugaru Chicken | E5: =IFERROR(__xludf.DUMMYFUNCTION("""COMPUTED_VALUE"""),"W17") -> W17 | F5: =IFERROR(__xludf.DUMMYFUNCTION("""COMPUTED_VALUE"""),407.0) -> 407 | G5: =IFERROR(__xludf.DUMMYFUNCTION("""COMPUTED_VALUE"""),607.0) -> 607 | H5: =IFERROR(__xludf.DUMMYFUNCTION("""COMPUTED_VALUE"""),307.0) -> 307 | I5: =IFERROR(__xludf.DUMMYFUNCTION("""COMPUTED_VALUE"""),2527.0) -> 2527 | J5: =IFERROR(__xludf.DUMMYFUNCTION("""COMPUTED_VALUE"""),1535.0) -> 1535 | K5: =IFERROR(__xludf.DUMMYFUNCTION("""COMPUTED_VALUE"""),1438.0) -> 1438 | L5: =IFERROR(__xludf.DUMMYFUNCTION("""COMPUTED_VALUE"""),32.0) -> 32 | M5: =IFERROR(__xludf.DUMMYFUNCTION("""COMPUTED_VALUE"""),2547.0) -> 2547 | N5: =IFERROR(__xludf.DUMMYFUNCTION("""COMPUTED_VALUE"""),1555.0) -> 1555 | O5: =IFERROR(__xludf.DUMMYFUNCTION("""COMPUTED_VALUE"""),1490.0) -> 1490 | P5: =IFERROR(__xludf.DUMMYFUNCTION("""COMPUTED_VALUE"""),0.0) -> 0 | Q5: =IFERROR(__xludf.DUMMYFUNCTION("""COMPUTED_VALUE"""),0.9) -> 0.9 | R5: =IFERROR(__xludf.DUMMYFUNCTION("""COMPUTED_VALUE"""),0.9) -> 0.9 | S5: =IFERROR(__xludf.DUMMYFUNCTION("""COMPUTED_VALUE"""),0.0) -> 0 | T5: =IFERROR(__xludf.DUMMYFUNCTION("""COMPUTED_VALUE"""),1399.5) -> 1399.5 | U5: =IFERROR(__xludf.DUMMYFUNCTION("""COMPUTED_VALUE"""),1341.0) -> 1341 | V5: =if(W5>0,W5,SUM(R5:T5)+X5) -> 2675 | W5: 2675
A6: =if(E6="","", CONCAT("2026-",E6)) -> 2026-W17 | B6: =IFERROR(__xludf.DUMMYFUNCTION("""COMPUTED_VALUE"""),"FE4064A") -> FE4064A | C6: =IFERROR(__xludf.DUMMYFUNCTION("""COMPUTED_VALUE"""),"Flexible") -> Flexible | D6: =IFERROR(__xludf.DUMMYFUNCTION("""COMPUTED_VALUE"""),"Ginger Garlic Grilled Chicken") -> Ginger Garlic Grilled Chicken | E6: =IFERROR(__xludf.DUMMYFUNCTION("""COMPUTED_VALUE"""),"W17") -> W17 | F6: =IFERROR(__xludf.DUMMYFUNCTION("""COMPUTED_VALUE"""),414.0) -> 414 | G6: =IFERROR(__xludf.DUMMYFUNCTION("""COMPUTED_VALUE"""),614.0) -> 614 | H6: =IFERROR(__xludf.DUMMYFUNCTION("""COMPUTED_VALUE"""),314.0) -> 314 | I6: =IFERROR(__xludf.DUMMYFUNCTION("""COMPUTED_VALUE"""),1249.0) -> 1249 | J6: =IFERROR(__xludf.DUMMYFUNCTION("""COMPUTED_VALUE"""),737.0) -> 737 | K6: =IFERROR(__xludf.DUMMYFUNCTION("""COMPUTED_VALUE"""),681.0) -> 681 | M6: =IFERROR(__xludf.DUMMYFUNCTION("""COMPUTED_VALUE"""),1269.0) -> 1269 | N6: =IFERROR(__xludf.DUMMYFUNCTION("""COMPUTED_VALUE"""),757.0) -> 757 | O6: =IFERROR(__xludf.DUMMYFUNCTION("""COMPUTED_VALUE"""),701.0) -> 701 | P6: =IFERROR(__xludf.DUMMYFUNCTION("""COMPUTED_VALUE"""),0.0) -> 0 | Q6: =IFERROR(__xludf.DUMMYFUNCTION("""COMPUTED_VALUE"""),0.9) -> 0.9 | R6: =IFERROR(__xludf.DUMMYFUNCTION("""COMPUTED_VALUE"""),0.9) -> 0.9 | S6: =IFERROR(__xludf.DUMMYFUNCTION("""COMPUTED_VALUE"""),0.0) -> 0 | T6: =IFERROR(__xludf.DUMMYFUNCTION("""COMPUTED_VALUE"""),681.3000000000001) -> 681.3 | U6: =IFERROR(__xludf.DUMMYFUNCTION("""COMPUTED_VALUE"""),630.9) -> 630.9 | V6: =if(W6>0,W6,SUM(R6:T6)+X6) -> 863 | W6: 863
A7: =if(E7="","", CONCAT("2026-",E7)) -> 2026-W17 | B7: =IFERROR(__xludf.DUMMYFUNCTION("""COMPUTED_VALUE"""),"FE0472B") -> FE0472B | C7: =IFERROR(__xludf.DUMMYFUNCTION("""COMPUTED_VALUE"""),"Flexible") -> Flexible | D7: =IFERROR(__xludf.DUMMYFUNCTION("""COMPUTED_VALUE"""),"Indian style butter chicken") -> Indian style butter chicken | E7: =IFERROR(__xludf.DUMMYFUNCTION("""COMPUTED_VALUE"""),"W17") -> W17 | F7: =IFERROR(__xludf.DUMMYFUNCTION("""COMPUTED_VALUE"""),416.0) -> 416 | G7: =IFERROR(__xludf.DUMMYFUNCTION("""COMPUTED_VALUE"""),616.0) -> 616 | H7: =IFERROR(__xludf.DUMMYFUNCTION("""COMPUTED_VALUE"""),316.0) -> 316 | I7: =IFERROR(__xludf.DUMMYFUNCTION("""COMPUTED_VALUE"""),1331.0) -> 1331 | J7: =IFERROR(__xludf.DUMMYFUNCTION("""COMPUTED_VALUE"""),661.0) -> 661 | K7: =IFERROR(__xludf.DUMMYFUNCTION("""COMPUTED_VALUE"""),762.0) -> 762 | M7: =IFERROR(__xludf.DUMMYFUNCTION("""COMPUTED_VALUE"""),1351.0) -> 1351 | N7: =IFERROR(__xludf.DUMMYFUNCTION("""COMPUTED_VALUE"""),681.0) -> 681 | O7: =IFERROR(__xludf.DUMMYFUNCTION("""COMPUTED_VALUE"""),782.0) -> 782 | P7: =IFERROR(__xludf.DUMMYFUNCTION("""COMPUTED_VALUE"""),0.0) -> 0 | Q7: =IFERROR(__xludf.DUMMYFUNCTION("""COMPUTED_VALUE"""),0.9) -> 0.9 | R7: =IFERROR(__xludf.DUMMYFUNCTION("""COMPUTED_VALUE"""),0.9) -> 0.9 | S7: =IFERROR(__xludf.DUMMYFUNCTION("""COMPUTED_VALUE"""),0.0) -> 0 | T7: =IFERROR(__xludf.DUMMYFUNCTION("""COMPUTED_VALUE"""),612.9) -> 612.9 | U7: =IFERROR(__xludf.DUMMYFUNCTION("""COMPUTED_VALUE"""),703.8000000000001) -> 703.8 | V7: =if(W7>0,W7,SUM(R7:T7)+X7) -> 938 | W7: 938
A8: =if(E8="","", CONCAT("2026-",E8)) -> 2026-W18 | B8: =IFERROR(__xludf.DUMMYFUNCTION("""COMPUTED_VALUE"""),"FV0601A") -> FV0601A | C8: =IFERROR(__xludf.DUMMYFUNCTION("""COMPUTED_VALUE"""),"Flexible") -> Flexible | D8: =IFERROR(__xludf.DUMMYFUNCTION("""COMPUTED_VALUE"""),"Mozzarella Burger & Roasted Potatoes") -> Mozzarella Burger & Roasted Potatoes | E8: =IFERROR(__xludf.DUMMYFUNCTION("""COMPUTED_VALUE"""),"W18") -> W18 | F8: =IFERROR(__xludf.DUMMYFUNCTION("""COMPUTED_VALUE"""),416.0) -> 416 | G8: =IFERROR(__xludf.DUMMYFUNCTION("""COMPUTED_VALUE"""),616.0) -> 616 | H8: =IFERROR(__xludf.DUMMYFUNCTION("""COMPUTED_VALUE"""),316.0) -> 316 | I8: =IFERROR(__xludf.DUMMYFUNCTION("""COMPUTED_VALUE"""),0.0) -> 0 | J8: =IFERROR(__xludf.DUMMYFUNCTION("""COMPUTED_VALUE"""),0.0) -> 0 | K8: =IFERROR(__xludf.DUMMYFUNCTION("""COMPUTED_VALUE"""),0.0) -> 0 | M8: =IFERROR(__xludf.DUMMYFUNCTION("""COMPUTED_VALUE"""),20.0) -> 20 | N8: =IFERROR(__xludf.DUMMYFUNCTION("""COMPUTED_VALUE"""),20.0) -> 20 | O8: =IFERROR(__xludf.DUMMYFUNCTION("""COMPUTED_VALUE"""),20.0) -> 20 | P8: =IFERROR(__xludf.DUMMYFUNCTION("""COMPUTED_VALUE"""),1.0) -> 1 | Q8: =IFERROR(__xludf.DUMMYFUNCTION("""COMPUTED_VALUE"""),1.0) -> 1 | R8: =IFERROR(__xludf.DUMMYFUNCTION("""COMPUTED_VALUE"""),1.0) -> 1 | S8: =IFERROR(__xludf.DUMMYFUNCTION("""COMPUTED_VALUE"""),20.0) -> 20 | T8: =IFERROR(__xludf.DUMMYFUNCTION("""COMPUTED_VALUE"""),20.0) -> 20 | U8: =IFERROR(__xludf.DUMMYFUNCTION("""COMPUTED_VALUE"""),20.0) -> 20 | V8: =if(W8>0,W8,SUM(R8:T8)+X8) -> 641 | X8: 600
A9: =if(E9="","", CONCAT("2026-",E9)) -> 2026-W19 | B9: =IFERROR(__xludf.DUMMYFUNCTION("""COMPUTED_VALUE"""),"FE4009A") -> FE4009A | C9: =IFERROR(__xludf.DUMMYFUNCTION("""COMPUTED_VALUE"""),"P+") -> P+ | D9: =IFERROR(__xludf.DUMMYFUNCTION("""COMPUTED_VALUE"""),"Salmon in mustard-dill sauce") -> Salmon in mustard-dill sauce | E9: =IFERROR(__xludf.DUMMYFUNCTION("""COMPUTED_VALUE"""),"W19") -> W19 | F9: =IFERROR(__xludf.DUMMYFUNCTION("""COMPUTED_VALUE"""),404.0) -> 404 | G9: =IFERROR(__xludf.DUMMYFUNCTION("""COMPUTED_VALUE"""),604.0) -> 604 | H9: =IFERROR(__xludf.DUMMYFUNCTION("""COMPUTED_VALUE"""),304.0) -> 304 | I9: =IFERROR(__xludf.DUMMYFUNCTION("""COMPUTED_VALUE"""),5769.0) -> 5769 | J9: =IFERROR(__xludf.DUMMYFUNCTION("""COMPUTED_VALUE"""),2905.0) -> 2905 | K9: =IFERROR(__xludf.DUMMYFUNCTION("""COMPUTED_VALUE"""),2346.0) -> 2346 | M9: =IFERROR(__xludf.DUMMYFUNCTION("""COMPUTED_VALUE"""),5789.0) -> 5789 | N9: =IFERROR(__xludf.DUMMYFUNCTION("""COMPUTED_VALUE"""),2925.0) -> 2925 | O9: =IFERROR(__xludf.DUMMYFUNCTION("""COMPUTED_VALUE"""),2366.0) -> 2366 | P9: =IFERROR(__xludf.DUMMYFUNCTION("""COMPUTED_VALUE"""),0.0) -> 0 | Q9: =IFERROR(__xludf.DUMMYFUNCTION("""COMPUTED_VALUE"""),1.0) -> 1 | R9: =IFERROR(__xludf.DUMMYFUNCTION("""COMPUTED_VALUE"""),1.0) -> 1 | S9: =IFERROR(__xludf.DUMMYFUNCTION("""COMPUTED_VALUE"""),0.0) -> 0 | T9: =IFERROR(__xludf.DUMMYFUNCTION("""COMPUTED_VALUE"""),2925.0) -> 2925 | U9: =IFERROR(__xludf.DUMMYFUNCTION("""COMPUTED_VALUE"""),2366.0) -> 2366 | V9: =if(W9>0,W9,SUM(R9:T9)+X9) -> 2926
A10: =if(E10="","", CONCAT("2026-",E10)) -> 2026-W19 | B10: =IFERROR(__xludf.DUMMYFUNCTION("""COMPUTED_VALUE"""),"FE0972B") -> FE0972B | C10: =IFERROR(__xludf.DUMMYFUNCTION("""COMPUTED_VALUE"""),"Keto") -> Keto | D10: =IFERROR(__xludf.DUMMYFUNCTION("""COMPUTED_VALUE"""),"Salmon Piccata") -> Salmon Piccata | E10: =IFERROR(__xludf.DUMMYFUNCTION("""COMPUTED_VALUE"""),"W19") -> W19 | F10: =IFERROR(__xludf.DUMMYFUNCTION("""COMPUTED_VALUE"""),406.0) -> 406 | G10: =IFERROR(__xludf.DUMMYFUNCTION("""COMPUTED_VALUE"""),606.0) -> 606 | H10: =IFERROR(__xludf.DUMMYFUNCTION("""COMPUTED_VALUE"""),306.0) -> 306 | I10: =IFERROR(__xludf.DUMMYFUNCTION("""COMPUTED_VALUE"""),2837.0) -> 2837 | J10: =IFERROR(__xludf.DUMMYFUNCTION("""COMPUTED_VALUE"""),1686.0) -> 1686 | K10: =IFERROR(__xludf.DUMMYFUNCTION("""COMPUTED_VALUE"""),1728.0) -> 1728 | M10: =IFERROR(__xludf.DUMMYFUNCTION("""COMPUTED_VALUE"""),2857.0) -> 2857 | N10: =IFERROR(__xludf.DUMMYFUNCTION("""COMPUTED_VALUE"""),1706.0) -> 1706 | O10: =IFERROR(__xludf.DUMMYFUNCTION("""COMPUTED_VALUE"""),1748.0) -> 1748 | P10: =IFERROR(__xludf.DUMMYFUNCTION("""COMPUTED_VALUE"""),0.0) -> 0 | Q10: =IFERROR(__xludf.DUMMYFUNCTION("""COMPUTED_VALUE"""),1.0) -> 1 | R10: =IFERROR(__xludf.DUMMYFUNCTION("""COMPUTED_VALUE"""),1.0) -> 1 | S10: =IFERROR(__xludf.DUMMYFUNCTION("""COMPUTED_VALUE"""),0.0) -> 0 | T10: =IFERROR(__xludf.DUMMYFUNCTION("""COMPUTED_VALUE"""),1706.0) -> 1706 | U10: =IFERROR(__xludf.DUMMYFUNCTION("""COMPUTED_VALUE"""),1748.0) -> 1748 | V10: =if(W10>0,W10,SUM(R10:T10)+X10) -> 1707
A11: =if(E11="","", CONCAT("2026-",E11)) -> 2026-W19 | B11: =IFERROR(__xludf.DUMMYFUNCTION("""COMPUTED_VALUE"""),"FE0970B") -> FE0970B | C11: =IFERROR(__xludf.DUMMYFUNCTION("""COMPUTED_VALUE"""),"Keto") -> Keto | D11: =IFERROR(__xludf.DUMMYFUNCTION("""COMPUTED_VALUE"""),"Caramelized Onion & Emmental Fondue Chicken") -> Caramelized Onion & Emmental Fondue Chicken | E11: =IFERROR(__xludf.DUMMYFUNCTION("""COMPUTED_VALUE"""),"W19") -> W19 | F11: =IFERROR(__xludf.DUMMYFUNCTION("""COMPUTED_VALUE"""),407.0) -> 407 | G11: =IFERROR(__xludf.DUMMYFUNCTION("""COMPUTED_VALUE"""),607.0) -> 607 | H11: =IFERROR(__xludf.DUMMYFUNCTION("""COMPUTED_VALUE"""),307.0) -> 307 | I11: =IFERROR(__xludf.DUMMYFUNCTION("""COMPUTED_VALUE"""),2593.0) -> 2593 | J11: =IFERROR(__xludf.DUMMYFUNCTION("""COMPUTED_VALUE"""),1390.0) -> 1390 | K11: =IFERROR(__xludf.DUMMYFUNCTION("""COMPUTED_VALUE"""),1527.0) -> 1527 | M11: =IFERROR(__xludf.DUMMYFUNCTION("""COMPUTED_VALUE"""),2613.0) -> 2613 | N11: =IFERROR(__xludf.DUMMYFUNCTION("""COMPUTED_VALUE"""),1410.0) -> 1410 | O11: =IFERROR(__xludf.DUMMYFUNCTION("""COMPUTED_VALUE"""),1547.0) -> 1547 | P11: =IFERROR(__xludf.DUMMYFUNCTION("""COMPUTED_VALUE"""),0.0) -> 0 | Q11: =IFERROR(__xludf.DUMMYFUNCTION("""COMPUTED_VALUE"""),1.0) -> 1 | R11: =IFERROR(__xludf.DUMMYFUNCTION("""COMPUTED_VALUE"""),1.0) -> 1 | S11: =IFERROR(__xludf.DUMMYFUNCTION("""COMPUTED_VALUE"""),0.0) -> 0 | T11: =IFERROR(__xludf.DUMMYFUNCTION("""COMPUTED_VALUE"""),1410.0) -> 1410 | U11: =IFERROR(__xludf.DUMMYFUNCTION("""COMPUTED_VALUE"""),1547.0) -> 1547 | V11: =if(W11>0,W11,SUM(R11:T11)+X11) -> 1411
A12: =if(E12="","", CONCAT("2026-",E12)) -> 2026-W20 | B12: =IFERROR(__xludf.DUMMYFUNCTION("""COMPUTED_VALUE"""),"FE0035F") -> FE0035F | C12: =IFERROR(__xludf.DUMMYFUNCTION("""COMPUTED_VALUE"""),"Keto") -> Keto | D12: =IFERROR(__xludf.DUMMYFUNCTION("""COMPUTED_VALUE"""),"Salmon with pesto") -> Salmon with pesto | E12: =IFERROR(__xludf.DUMMYFUNCTION("""COMPUTED_VALUE"""),"W20") -> W20 | F12: =IFERROR(__xludf.DUMMYFUNCTION("""COMPUTED_VALUE"""),406.0) -> 406 | G12: =IFERROR(__xludf.DUMMYFUNCTION("""COMPUTED_VALUE"""),606.0) -> 606 | H12: =IFERROR(__xludf.DUMMYFUNCTION("""COMPUTED_VALUE"""),306.0) -> 306 | I12: =IFERROR(__xludf.DUMMYFUNCTION("""COMPUTED_VALUE"""),2718.0) -> 2718 | J12: =IFERROR(__xludf.DUMMYFUNCTION("""COMPUTED_VALUE"""),1645.0) -> 1645 | K12: =IFERROR(__xludf.DUMMYFUNCTION("""COMPUTED_VALUE"""),1546.0) -> 1546 | L12: =IFERROR(__xludf.DUMMYFUNCTION("""COMPUTED_VALUE"""),0.0) -> 0 | M12: =IFERROR(__xludf.DUMMYFUNCTION("""COMPUTED_VALUE"""),2738.0) -> 2738 | N12: =IFERROR(__xludf.DUMMYFUNCTION("""COMPUTED_VALUE"""),1665.0) -> 1665 | O12: =IFERROR(__xludf.DUMMYFUNCTION("""COMPUTED_VALUE"""),1566.0) -> 1566 | P12: =IFERROR(__xludf.DUMMYFUNCTION("""COMPUTED_VALUE"""),1.0) -> 1 | Q12: =IFERROR(__xludf.DUMMYFUNCTION("""COMPUTED_VALUE"""),1.0) -> 1 | R12: =IFERROR(__xludf.DUMMYFUNCTION("""COMPUTED_VALUE"""),1.0) -> 1 | S12: =IFERROR(__xludf.DUMMYFUNCTION("""COMPUTED_VALUE"""),2738.0) -> 2738 | T12: =IFERROR(__xludf.DUMMYFUNCTION("""COMPUTED_VALUE"""),1665.0) -> 1665 | U12: =IFERROR(__xludf.DUMMYFUNCTION("""COMPUTED_VALUE"""),1566.0) -> 1566 | V12: =if(W12>0,W12,SUM(R12:T12)+X12) -> 4404
A13: =if(E13="","", CONCAT("2026-",E13)) -> 2026-W20 | B13: =IFERROR(__xludf.DUMMYFUNCTION("""COMPUTED_VALUE"""),"FE0472B") -> FE0472B | C13: =IFERROR(__xludf.DUMMYFUNCTION("""COMPUTED_VALUE"""),"Keto") -> Keto | D13: =IFERROR(__xludf.DUMMYFUNCTION("""COMPUTED_VALUE"""),"Indian style butter chicken") -> Indian style butter chicken | E13: =IFERROR(__xludf.DUMMYFUNCTION("""COMPUTED_VALUE"""),"W20") -> W20 | F13: =IFERROR(__xludf.DUMMYFUNCTION("""COMPUTED_VALUE"""),407.0) -> 407 | G13: =IFERROR(__xludf.DUMMYFUNCTION("""COMPUTED_VALUE"""),607.0) -> 607 | H13: =IFERROR(__xludf.DUMMYFUNCTION("""COMPUTED_VALUE"""),307.0) -> 307 | I13: =IFERROR(__xludf.DUMMYFUNCTION("""COMPUTED_VALUE"""),2363.0) -> 2363 | J13: =IFERROR(__xludf.DUMMYFUNCTION("""COMPUTED_VALUE"""),1485.0) -> 1485 | K13: =IFERROR(__xludf.DUMMYFUNCTION("""COMPUTED_VALUE"""),1274.0) -> 1274 | L13: =IFERROR(__xludf.DUMMYFUNCTION("""COMPUTED_VALUE"""),0.0) -> 0 | M13: =IFERROR(__xludf.DUMMYFUNCTION("""COMPUTED_VALUE"""),2383.0) -> 2383 | N13: =IFERROR(__xludf.DUMMYFUNCTION("""COMPUTED_VALUE"""),1505.0) -> 1505 | O13: =IFERROR(__xludf.DUMMYFUNCTION("""COMPUTED_VALUE"""),1294.0) -> 1294 | P13: =IFERROR(__xludf.DUMMYFUNCTION("""COMPUTED_VALUE"""),1.0) -> 1 | Q13: =IFERROR(__xludf.DUMMYFUNCTION("""COMPUTED_VALUE"""),1.0) -> 1 | R13: =IFERROR(__xludf.DUMMYFUNCTION("""COMPUTED_VALUE"""),1.0) -> 1 | S13: =IFERROR(__xludf.DUMMYFUNCTION("""COMPUTED_VALUE"""),2383.0) -> 2383 | T13: =IFERROR(__xludf.DUMMYFUNCTION("""COMPUTED_VALUE"""),1505.0) -> 1505 | U13: =IFERROR(__xludf.DUMMYFUNCTION("""COMPUTED_VALUE"""),1294.0) -> 1294 | V13: =if(W13>0,W13,SUM(R13:T13)+X13) -> 3889
A14: =if(E14="","", CONCAT("2026-",E14)) -> 2026-W20 | B14: =IFERROR(__xludf.DUMMYFUNCTION("""COMPUTED_VALUE"""),"FE0281E") -> FE0281E | C14: =IFERROR(__xludf.DUMMYFUNCTION("""COMPUTED_VALUE"""),"P+") -> P+ | D14: =IFERROR(__xludf.DUMMYFUNCTION("""COMPUTED_VALUE"""),"Spicy citrus salmon") -> Spicy citrus salmon | E14: =IFERROR(__xludf.DUMMYFUNCTION("""COMPUTED_VALUE"""),"W20") -> W20 | F14: =IFERROR(__xludf.DUMMYFUNCTION("""COMPUTED_VALUE"""),412.0) -> 412 | G14: =IFERROR(__xludf.DUMMYFUNCTION("""COMPUTED_VALUE"""),612.0) -> 612 | H14: =IFERROR(__xludf.DUMMYFUNCTION("""COMPUTED_VALUE"""),312.0) -> 312 | I14: =IFERROR(__xludf.DUMMYFUNCTION("""COMPUTED_VALUE"""),3127.0) -> 3127 | J14: =IFERROR(__xludf.DUMMYFUNCTION("""COMPUTED_VALUE"""),1419.0) -> 1419 | K14: =IFERROR(__xludf.DUMMYFUNCTION("""COMPUTED_VALUE"""),1159.0) -> 1159 | L14: =IFERROR(__xludf.DUMMYFUNCTION("""COMPUTED_VALUE"""),0.0) -> 0 | M14: =IFERROR(__xludf.DUMMYFUNCTION("""COMPUTED_VALUE"""),3147.0) -> 3147 | N14: =IFERROR(__xludf.DUMMYFUNCTION("""COMPUTED_VALUE"""),1439.0) -> 1439 | O14: =IFERROR(__xludf.DUMMYFUNCTION("""COMPUTED_VALUE"""),1179.0) -> 1179 | P14: =IFERROR(__xludf.DUMMYFUNCTION("""COMPUTED_VALUE"""),1.0) -> 1 | Q14: =IFERROR(__xludf.DUMMYFUNCTION("""COMPUTED_VALUE"""),1.0) -> 1 | R14: =IFERROR(__xludf.DUMMYFUNCTION("""COMPUTED_VALUE"""),1.0) -> 1 | S14: =IFERROR(__xludf.DUMMYFUNCTION("""COMPUTED_VALUE"""),3147.0) -> 3147 | T14: =IFERROR(__xludf.DUMMYFUNCTION("""COMPUTED_VALUE"""),1439.0) -> 1439 | U14: =IFERROR(__xludf.DUMMYFUNCTION("""COMPUTED_VALUE"""),1179.0) -> 1179 | V14: =if(W14>0,W14,SUM(R14:T14)+X14) -> 4587
A15: =if(E15="","", CONCAT("2026-",E15)) -> 2026-W20 | B15: =IFERROR(__xludf.DUMMYFUNCTION("""COMPUTED_VALUE"""),"FE1646A") -> FE1646A | C15: =IFERROR(__xludf.DUMMYFUNCTION("""COMPUTED_VALUE"""),"Flexible") -> Flexible | D15: =IFERROR(__xludf.DUMMYFUNCTION("""COMPUTED_VALUE"""),"Shrimp with Lemon Garlic Sauce & Spanakopita Style Rice") -> Shrimp with Lemon Garlic Sauce & Spanakopita Style Rice | E15: =IFERROR(__xludf.DUMMYFUNCTION("""COMPUTED_VALUE"""),"W20") -> W20 | F15: =IFERROR(__xludf.DUMMYFUNCTION("""COMPUTED_VALUE"""),414.0) -> 414 | G15: =IFERROR(__xludf.DUMMYFUNCTION("""COMPUTED_VALUE"""),614.0) -> 614 | H15: =IFERROR(__xludf.DUMMYFUNCTION("""COMPUTED_VALUE"""),314.0) -> 314 | I15: =IFERROR(__xludf.DUMMYFUNCTION("""COMPUTED_VALUE"""),1191.0) -> 1191 | J15: =IFERROR(__xludf.DUMMYFUNCTION("""COMPUTED_VALUE"""),644.0) -> 644 | K15: =IFERROR(__xludf.DUMMYFUNCTION("""COMPUTED_VALUE"""),655.0) -> 655 | L15: =IFERROR(__xludf.DUMMYFUNCTION("""COMPUTED_VALUE"""),0.0) -> 0 | M15: =IFERROR(__xludf.DUMMYFUNCTION("""COMPUTED_VALUE"""),1211.0) -> 1211 | N15: =IFERROR(__xludf.DUMMYFUNCTION("""COMPUTED_VALUE"""),664.0) -> 664 | O15: =IFERROR(__xludf.DUMMYFUNCTION("""COMPUTED_VALUE"""),675.0) -> 675 | P15: =IFERROR(__xludf.DUMMYFUNCTION("""COMPUTED_VALUE"""),1.0) -> 1 | Q15: =IFERROR(__xludf.DUMMYFUNCTION("""COMPUTED_VALUE"""),1.0) -> 1 | R15: =IFERROR(__xludf.DUMMYFUNCTION("""COMPUTED_VALUE"""),1.0) -> 1 | S15: =IFERROR(__xludf.DUMMYFUNCTION("""COMPUTED_VALUE"""),1211.0) -> 1211 | T15: =IFERROR(__xludf.DUMMYFUNCTION("""COMPUTED_VALUE"""),664.0) -> 664 | U15: =IFERROR(__xludf.DUMMYFUNCTION("""COMPUTED_VALUE"""),675.0) -> 675 | V15: =if(W15>0,W15,SUM(R15:T15)+X15) -> 1876
A16: =if(E16="","", CONCAT("2026-",E16)) -> 2026-W20 | B16: =IFERROR(__xludf.DUMMYFUNCTION("""COMPUTED_VALUE"""),"FV0846A") -> FV0846A | C16: =IFERROR(__xludf.DUMMYFUNCTION("""COMPUTED_VALUE"""),"Keto") -> Keto | D16: =IFERROR(__xludf.DUMMYFUNCTION("""COMPUTED_VALUE"""),"Stroganoff-Style Beef Burger") -> Stroganoff-Style Beef Burger | E16: =IFERROR(__xludf.DUMMYFUNCTION("""COMPUTED_VALUE"""),"W20") -> W20 | F16: =IFERROR(__xludf.DUMMYFUNCTION("""COMPUTED_VALUE"""),415.0) -> 415 | G16: =IFERROR(__xludf.DUMMYFUNCTION("""COMPUTED_VALUE"""),615.0) -> 615 | H16: =IFERROR(__xludf.DUMMYFUNCTION("""COMPUTED_VALUE"""),315.0) -> 315 | I16: =IFERROR(__xludf.DUMMYFUNCTION("""COMPUTED_VALUE"""),1087.0) -> 1087 | J16: =IFERROR(__xludf.DUMMYFUNCTION("""COMPUTED_VALUE"""),644.0) -> 644 | K16: =IFERROR(__xludf.DUMMYFUNCTION("""COMPUTED_VALUE"""),625.0) -> 625 | L16: =IFERROR(__xludf.DUMMYFUNCTION("""COMPUTED_VALUE"""),0.0) -> 0 | M16: =IFERROR(__xludf.DUMMYFUNCTION("""COMPUTED_VALUE"""),1107.0) -> 1107 | N16: =IFERROR(__xludf.DUMMYFUNCTION("""COMPUTED_VALUE"""),664.0) -> 664 | O16: =IFERROR(__xludf.DUMMYFUNCTION("""COMPUTED_VALUE"""),645.0) -> 645 | P16: =IFERROR(__xludf.DUMMYFUNCTION("""COMPUTED_VALUE"""),1.0) -> 1 | Q16: =IFERROR(__xludf.DUMMYFUNCTION("""COMPUTED_VALUE"""),1.0) -> 1 | R16: =IFERROR(__xludf.DUMMYFUNCTION("""COMPUTED_VALUE"""),1.0) -> 1 | S16: =IFERROR(__xludf.DUMMYFUNCTION("""COMPUTED_VALUE"""),1107.0) -> 1107 | T16: =IFERROR(__xludf.DUMMYFUNCTION("""COMPUTED_VALUE"""),664.0) -> 664 | U16: =IFERROR(__xludf.DUMMYFUNCTION("""COMPUTED_VALUE"""),645.0) -> 645 | V16: =if(W16>0,W16,SUM(R16:T16)+X16) -> 1772
A17: =if(E17="","", CONCAT("2026-",E17)) -> 2026-W21 | B17: =IFERROR(__xludf.DUMMYFUNCTION("""COMPUTED_VALUE"""),"FV0426A") -> FV0426A | C17: =IFERROR(__xludf.DUMMYFUNCTION("""COMPUTED_VALUE"""),"CS") -> CS | D17: =IFERROR(__xludf.DUMMYFUNCTION("""COMPUTED_VALUE"""),"Grilled chicken fillet and potato leek mash") -> Grilled chicken fillet and potato leek mash | E17: =IFERROR(__xludf.DUMMYFUNCTION("""COMPUTED_VALUE"""),"W21") -> W21 | F17: =IFERROR(__xludf.DUMMYFUNCTION("""COMPUTED_VALUE"""),402.0) -> 402 | G17: =IFERROR(__xludf.DUMMYFUNCTION("""COMPUTED_VALUE"""),602.0) -> 602 | H17: =IFERROR(__xludf.DUMMYFUNCTION("""COMPUTED_VALUE"""),302.0) -> 302 | I17: =IFERROR(__xludf.DUMMYFUNCTION("""COMPUTED_VALUE"""),3331.0) -> 3331 | J17: =IFERROR(__xludf.DUMMYFUNCTION("""COMPUTED_VALUE"""),2096.0) -> 2096 | K17: =IFERROR(__xludf.DUMMYFUNCTION("""COMPUTED_VALUE"""),1428.0) -> 1428 | L17: =IFERROR(__xludf.DUMMYFUNCTION("""COMPUTED_VALUE"""),0.0) -> 0 | M17: =IFERROR(__xludf.DUMMYFUNCTION("""COMPUTED_VALUE"""),3351.0) -> 3351 | N17: =IFERROR(__xludf.DUMMYFUNCTION("""COMPUTED_VALUE"""),2116.0) -> 2116 | O17: =IFERROR(__xludf.DUMMYFUNCTION("""COMPUTED_VALUE"""),1448.0) -> 1448 | P17: =IFERROR(__xludf.DUMMYFUNCTION("""COMPUTED_VALUE"""),1.0) -> 1 | Q17: =IFERROR(__xludf.DUMMYFUNCTION("""COMPUTED_VALUE"""),1.0) -> 1 | R17: =IFERROR(__xludf.DUMMYFUNCTION("""COMPUTED_VALUE"""),1.0) -> 1 | S17: =IFERROR(__xludf.DUMMYFUNCTION("""COMPUTED_VALUE"""),3351.0) -> 3351 | T17: =IFERROR(__xludf.DUMMYFUNCTION("""COMPUTED_VALUE"""),2116.0) -> 2116 | U17: =IFERROR(__xludf.DUMMYFUNCTION("""COMPUTED_VALUE"""),1448.0) -> 1448 | V17: =if(W17>0,W17,SUM(R17:T17)+X17) -> 5468
A18: =if(E18="","", CONCAT("2026-",E18)) -> 2026-W21 | B18: =IFERROR(__xludf.DUMMYFUNCTION("""COMPUTED_VALUE"""),"FE0322O") -> FE0322O | C18: =IFERROR(__xludf.DUMMYFUNCTION("""COMPUTED_VALUE"""),"CS") -> CS | D18: =IFERROR(__xludf.DUMMYFUNCTION("""COMPUTED_VALUE"""),"Sour Cream & Chive Chicken") -> Sour Cream & Chive Chicken | E18: =IFERROR(__xludf.DUMMYFUNCTION("""COMPUTED_VALUE"""),"W21") -> W21 | F18: =IFERROR(__xludf.DUMMYFUNCTION("""COMPUTED_VALUE"""),405.0) -> 405 | G18: =IFERROR(__xludf.DUMMYFUNCTION("""COMPUTED_VALUE"""),605.0) -> 605 | H18: =IFERROR(__xludf.DUMMYFUNCTION("""COMPUTED_VALUE"""),305.0) -> 305 | I18: =IFERROR(__xludf.DUMMYFUNCTION("""COMPUTED_VALUE"""),2304.0) -> 2304 | J18: =IFERROR(__xludf.DUMMYFUNCTION("""COMPUTED_VALUE"""),1563.0) -> 1563 | K18: =IFERROR(__xludf.DUMMYFUNCTION("""COMPUTED_VALUE"""),1331.0) -> 1331 | L18: =IFERROR(__xludf.DUMMYFUNCTION("""COMPUTED_VALUE"""),0.0) -> 0 | M18: =IFERROR(__xludf.DUMMYFUNCTION("""COMPUTED_VALUE"""),2324.0) -> 2324 | N18: =IFERROR(__xludf.DUMMYFUNCTION("""COMPUTED_VALUE"""),1583.0) -> 1583 | O18: =IFERROR(__xludf.DUMMYFUNCTION("""COMPUTED_VALUE"""),1351.0) -> 1351 | P18: =IFERROR(__xludf.DUMMYFUNCTION("""COMPUTED_VALUE"""),0.0) -> 0 | Q18: =IFERROR(__xludf.DUMMYFUNCTION("""COMPUTED_VALUE"""),1.0) -> 1 | R18: =IFERROR(__xludf.DUMMYFUNCTION("""COMPUTED_VALUE"""),1.0) -> 1 | S18: =IFERROR(__xludf.DUMMYFUNCTION("""COMPUTED_VALUE"""),0.0) -> 0 | T18: =IFERROR(__xludf.DUMMYFUNCTION("""COMPUTED_VALUE"""),1583.0) -> 1583 | U18: =IFERROR(__xludf.DUMMYFUNCTION("""COMPUTED_VALUE"""),1351.0) -> 1351 | V18: =if(W18>0,W18,SUM(R18:T18)+X18) -> 1584
A19: =if(E19="","", CONCAT("2026-",E19)) -> 2026-W21 | B19: =IFERROR(__xludf.DUMMYFUNCTION("""COMPUTED_VALUE"""),"FE4039C") -> FE4039C | C19: =IFERROR(__xludf.DUMMYFUNCTION("""COMPUTED_VALUE"""),"Keto") -> Keto | D19: =IFERROR(__xludf.DUMMYFUNCTION("""COMPUTED_VALUE"""),"Salmon in creamy gochugaru sauce") -> Salmon in creamy gochugaru sauce | E19: =IFERROR(__xludf.DUMMYFUNCTION("""COMPUTED_VALUE"""),"W21") -> W21 | F19: =IFERROR(__xludf.DUMMYFUNCTION("""COMPUTED_VALUE"""),406.0) -> 406 | G19: =IFERROR(__xludf.DUMMYFUNCTION("""COMPUTED_VALUE"""),606.0) -> 606 | H19: =IFERROR(__xludf.DUMMYFUNCTION("""COMPUTED_VALUE"""),306.0) -> 306 | I19: =IFERROR(__xludf.DUMMYFUNCTION("""COMPUTED_VALUE"""),2579.0) -> 2579 | J19: =IFERROR(__xludf.DUMMYFUNCTION("""COMPUTED_VALUE"""),1565.0) -> 1565 | K19: =IFERROR(__xludf.DUMMYFUNCTION("""COMPUTED_VALUE"""),1514.0) -> 1514 | L19: =IFERROR(__xludf.DUMMYFUNCTION("""COMPUTED_VALUE"""),0.0) -> 0 | M19: =IFERROR(__xludf.DUMMYFUNCTION("""COMPUTED_VALUE"""),2599.0) -> 2599 | N19: =IFERROR(__xludf.DUMMYFUNCTION("""COMPUTED_VALUE"""),1585.0) -> 1585 | O19: =IFERROR(__xludf.DUMMYFUNCTION("""COMPUTED_VALUE"""),1534.0) -> 1534 | P19: =IFERROR(__xludf.DUMMYFUNCTION("""COMPUTED_VALUE"""),0.0) -> 0 | Q19: =IFERROR(__xludf.DUMMYFUNCTION("""COMPUTED_VALUE"""),1.0) -> 1 | R19: =IFERROR(__xludf.DUMMYFUNCTION("""COMPUTED_VALUE"""),1.0) -> 1 | S19: =IFERROR(__xludf.DUMMYFUNCTION("""COMPUTED_VALUE"""),0.0) -> 0 | T19: =IFERROR(__xludf.DUMMYFUNCTION("""COMPUTED_VALUE"""),1585.0) -> 1585 | U19: =IFERROR(__xludf.DUMMYFUNCTION("""COMPUTED_VALUE"""),1534.0) -> 1534 | V19: =if(W19>0,W19,SUM(R19:T19)+X19) -> 1586
A20: =if(E20="","", CONCAT("2026-",E20)) -> 2026-W21 | B20: =IFERROR(__xludf.DUMMYFUNCTION("""COMPUTED_VALUE"""),"FE0090C") -> FE0090C | C20: =IFERROR(__xludf.DUMMYFUNCTION("""COMPUTED_VALUE"""),"Veggie") -> Veggie | D20: =IFERROR(__xludf.DUMMYFUNCTION("""COMPUTED_VALUE"""),"Ratatouille of zucchini and pepper") -> Ratatouille of zucchini and pepper | E20: =IFERROR(__xludf.DUMMYFUNCTION("""COMPUTED_VALUE"""),"W21") -> W21 | F20: =IFERROR(__xludf.DUMMYFUNCTION("""COMPUTED_VALUE"""),409.0) -> 409 | G20: =IFERROR(__xludf.DUMMYFUNCTION("""COMPUTED_VALUE"""),609.0) -> 609 | H20: =IFERROR(__xludf.DUMMYFUNCTION("""COMPUTED_VALUE"""),309.0) -> 309 | I20: =IFERROR(__xludf.DUMMYFUNCTION("""COMPUTED_VALUE"""),409.0) -> 409 | J20: =IFERROR(__xludf.DUMMYFUNCTION("""COMPUTED_VALUE"""),181.0) -> 181 | K20: =IFERROR(__xludf.DUMMYFUNCTION("""COMPUTED_VALUE"""),209.0) -> 209 | L20: =IFERROR(__xludf.DUMMYFUNCTION("""COMPUTED_VALUE"""),0.0) -> 0 | M20: =IFERROR(__xludf.DUMMYFUNCTION("""COMPUTED_VALUE"""),429.0) -> 429 | N20: =IFERROR(__xludf.DUMMYFUNCTION("""COMPUTED_VALUE"""),201.0) -> 201 | O20: =IFERROR(__xludf.DUMMYFUNCTION("""COMPUTED_VALUE"""),229.0) -> 229 | P20: =IFERROR(__xludf.DUMMYFUNCTION("""COMPUTED_VALUE"""),1.0) -> 1 | Q20: =IFERROR(__xludf.DUMMYFUNCTION("""COMPUTED_VALUE"""),1.0) -> 1 | R20: =IFERROR(__xludf.DUMMYFUNCTION("""COMPUTED_VALUE"""),1.0) -> 1 | S20: =IFERROR(__xludf.DUMMYFUNCTION("""COMPUTED_VALUE"""),429.0) -> 429 | T20: =IFERROR(__xludf.DUMMYFUNCTION("""COMPUTED_VALUE"""),201.0) -> 201 | U20: =IFERROR(__xludf.DUMMYFUNCTION("""COMPUTED_VALUE"""),229.0) -> 229 | V20: =if(W20>0,W20,SUM(R20:T20)+X20) -> 631
A21: =if(E21="","", CONCAT("2026-",E21)) -> 2026-W21 | B21: =IFERROR(__xludf.DUMMYFUNCTION("""COMPUTED_VALUE"""),"FE1439A") -> FE1439A | C21: =IFERROR(__xludf.DUMMYFUNCTION("""COMPUTED_VALUE"""),"P+") -> P+ | D21: =IFERROR(__xludf.DUMMYFUNCTION("""COMPUTED_VALUE"""),"Tzatziki Salmon & Lemon Rice") -> Tzatziki Salmon & Lemon Rice | E21: =IFERROR(__xludf.DUMMYFUNCTION("""COMPUTED_VALUE"""),"W21") -> W21 | F21: =IFERROR(__xludf.DUMMYFUNCTION("""COMPUTED_VALUE"""),412.0) -> 412 | G21: =IFERROR(__xludf.DUMMYFUNCTION("""COMPUTED_VALUE"""),612.0) -> 612 | H21: =IFERROR(__xludf.DUMMYFUNCTION("""COMPUTED_VALUE"""),312.0) -> 312 | I21: =IFERROR(__xludf.DUMMYFUNCTION("""COMPUTED_VALUE"""),2963.0) -> 2963 | J21: =IFERROR(__xludf.DUMMYFUNCTION("""COMPUTED_VALUE"""),1345.0) -> 1345 | K21: =IFERROR(__xludf.DUMMYFUNCTION("""COMPUTED_VALUE"""),1134.0) -> 1134 | L21: =IFERROR(__xludf.DUMMYFUNCTION("""COMPUTED_VALUE"""),0.0) -> 0 | M21: =IFERROR(__xludf.DUMMYFUNCTION("""COMPUTED_VALUE"""),2983.0) -> 2983 | N21: =IFERROR(__xludf.DUMMYFUNCTION("""COMPUTED_VALUE"""),1365.0) -> 1365 | O21: =IFERROR(__xludf.DUMMYFUNCTION("""COMPUTED_VALUE"""),1154.0) -> 1154 | P21: =IFERROR(__xludf.DUMMYFUNCTION("""COMPUTED_VALUE"""),1.0) -> 1 | Q21: =IFERROR(__xludf.DUMMYFUNCTION("""COMPUTED_VALUE"""),1.0) -> 1 | R21: =IFERROR(__xludf.DUMMYFUNCTION("""COMPUTED_VALUE"""),1.0) -> 1 | S21: =IFERROR(__xludf.DUMMYFUNCTION("""COMPUTED_VALUE"""),2983.0) -> 2983 | T21: =IFERROR(__xludf.DUMMYFUNCTION("""COMPUTED_VALUE"""),1365.0) -> 1365 | U21: =IFERROR(__xludf.DUMMYFUNCTION("""COMPUTED_VALUE"""),1154.0) -> 1154 | V21: =if(W21>0,W21,SUM(R21:T21)+X21) -> 4349
A22: =if(E22="","", CONCAT("2026-",E22)) -> 2026-W21 | B22: =IFERROR(__xludf.DUMMYFUNCTION("""COMPUTED_VALUE"""),"FV0601A") -> FV0601A | C22: =IFERROR(__xludf.DUMMYFUNCTION("""COMPUTED_VALUE"""),"Keto") -> Keto | D22: =IFERROR(__xludf.DUMMYFUNCTION("""COMPUTED_VALUE"""),"Mozzarella Burger & Roasted Potatoes") -> Mozzarella Burger & Roasted Potatoes | E22: =IFERROR(__xludf.DUMMYFUNCTION("""COMPUTED_VALUE"""),"W21") -> W21 | F22: =IFERROR(__xludf.DUMMYFUNCTION("""COMPUTED_VALUE"""),415.0) -> 415 | G22: =IFERROR(__xludf.DUMMYFUNCTION("""COMPUTED_VALUE"""),615.0) -> 615 | H22: =IFERROR(__xludf.DUMMYFUNCTION("""COMPUTED_VALUE"""),315.0) -> 315 | I22: =IFERROR(__xludf.DUMMYFUNCTION("""COMPUTED_VALUE"""),1029.0) -> 1029 | J22: =IFERROR(__xludf.DUMMYFUNCTION("""COMPUTED_VALUE"""),613.0) -> 613 | K22: =IFERROR(__xludf.DUMMYFUNCTION("""COMPUTED_VALUE"""),612.0) -> 612 | L22: =IFERROR(__xludf.DUMMYFUNCTION("""COMPUTED_VALUE"""),0.0) -> 0 | M22: =IFERROR(__xludf.DUMMYFUNCTION("""COMPUTED_VALUE"""),1049.0) -> 1049 | N22: =IFERROR(__xludf.DUMMYFUNCTION("""COMPUTED_VALUE"""),633.0) -> 633 | O22: =IFERROR(__xludf.DUMMYFUNCTION("""COMPUTED_VALUE"""),632.0) -> 632 | P22: =IFERROR(__xludf.DUMMYFUNCTION("""COMPUTED_VALUE"""),1.0) -> 1 | Q22: =IFERROR(__xludf.DUMMYFUNCTION("""COMPUTED_VALUE"""),1.0) -> 1 | R22: =IFERROR(__xludf.DUMMYFUNCTION("""COMPUTED_VALUE"""),1.0) -> 1 | S22: =IFERROR(__xludf.DUMMYFUNCTION("""COMPUTED_VALUE"""),1049.0) -> 1049 | T22: =IFERROR(__xludf.DUMMYFUNCTION("""COMPUTED_VALUE"""),633.0) -> 633 | U22: =IFERROR(__xludf.DUMMYFUNCTION("""COMPUTED_VALUE"""),632.0) -> 632 | V22: =if(W22>0,W22,SUM(R22:T22)+X22) -> 1683
A23: =if(E23="","", CONCAT("2026-",E23)) -> 2026-W21 | B23: =IFERROR(__xludf.DUMMYFUNCTION("""COMPUTED_VALUE"""),"FV0333A") -> FV0333A | C23: =IFERROR(__xludf.DUMMYFUNCTION("""COMPUTED_VALUE"""),"CS") -> CS | D23: =IFERROR(__xludf.DUMMYFUNCTION("""COMPUTED_VALUE"""),"Tuscan Shrimp") -> Tuscan Shrimp | E23: =IFERROR(__xludf.DUMMYFUNCTION("""COMPUTED_VALUE"""),"W21") -> W21 | F23: =IFERROR(__xludf.DUMMYFUNCTION("""COMPUTED_VALUE"""),419.0) -> 419 | G23: =IFERROR(__xludf.DUMMYFUNCTION("""COMPUTED_VALUE"""),619.0) -> 619 | H23: =IFERROR(__xludf.DUMMYFUNCTION("""COMPUTED_VALUE"""),319.0) -> 319 | I23: =IFERROR(__xludf.DUMMYFUNCTION("""COMPUTED_VALUE"""),2116.0) -> 2116 | J23: =IFERROR(__xludf.DUMMYFUNCTION("""COMPUTED_VALUE"""),1206.0) -> 1206 | K23: =IFERROR(__xludf.DUMMYFUNCTION("""COMPUTED_VALUE"""),999.0) -> 999 | L23: =IFERROR(__xludf.DUMMYFUNCTION("""COMPUTED_VALUE"""),0.0) -> 0 | M23: =IFERROR(__xludf.DUMMYFUNCTION("""COMPUTED_VALUE"""),2136.0) -> 2136 | N23: =IFERROR(__xludf.DUMMYFUNCTION("""COMPUTED_VALUE"""),1226.0) -> 1226 | O23: =IFERROR(__xludf.DUMMYFUNCTION("""COMPUTED_VALUE"""),1019.0) -> 1019 | P23: =IFERROR(__xludf.DUMMYFUNCTION("""COMPUTED_VALUE"""),1.0) -> 1 | Q23: =IFERROR(__xludf.DUMMYFUNCTION("""COMPUTED_VALUE"""),1.0) -> 1 | R23: =IFERROR(__xludf.DUMMYFUNCTION("""COMPUTED_VALUE"""),1.0) -> 1 | S23: =IFERROR(__xludf.DUMMYFUNCTION("""COMPUTED_VALUE"""),2136.0) -> 2136 | T23: =IFERROR(__xludf.DUMMYFUNCTION("""COMPUTED_VALUE"""),1226.0) -> 1226 | U23: =IFERROR(__xludf.DUMMYFUNCTION("""COMPUTED_VALUE"""),1019.0) -> 1019 | V23: =if(W23>0,W23,SUM(R23:T23)+X23) -> 3363
A24: =if(E24="","", CONCAT("2026-",E24)) -> 2026-W21 | B24: =IFERROR(__xludf.DUMMYFUNCTION("""COMPUTED_VALUE"""),"FV0232A") -> FV0232A | C24: =IFERROR(__xludf.DUMMYFUNCTION("""COMPUTED_VALUE"""),"Perf") -> Perf | D24: =IFERROR(__xludf.DUMMYFUNCTION("""COMPUTED_VALUE"""),"Herb Crusted chicken and Parmesan cheese ") -> Herb Crusted chicken and Parmesan cheese | E24: =IFERROR(__xludf.DUMMYFUNCTION("""COMPUTED_VALUE"""),"W21") -> W21 | F24: =IFERROR(__xludf.DUMMYFUNCTION("""COMPUTED_VALUE"""),420.0) -> 420 | G24: =IFERROR(__xludf.DUMMYFUNCTION("""COMPUTED_VALUE"""),620.0) -> 620 | H24: =IFERROR(__xludf.DUMMYFUNCTION("""COMPUTED_VALUE"""),320.0) -> 320 | I24: =IFERROR(__xludf.DUMMYFUNCTION("""COMPUTED_VALUE"""),970.0) -> 970 | J24: =IFERROR(__xludf.DUMMYFUNCTION("""COMPUTED_VALUE"""),553.0) -> 553 | K24: =IFERROR(__xludf.DUMMYFUNCTION("""COMPUTED_VALUE"""),458.0) -> 458 | L24: =IFERROR(__xludf.DUMMYFUNCTION("""COMPUTED_VALUE"""),0.0) -> 0 | M24: =IFERROR(__xludf.DUMMYFUNCTION("""COMPUTED_VALUE"""),990.0) -> 990 | N24: =IFERROR(__xludf.DUMMYFUNCTION("""COMPUTED_VALUE"""),573.0) -> 573 | O24: =IFERROR(__xludf.DUMMYFUNCTION("""COMPUTED_VALUE"""),478.0) -> 478 | P24: =IFERROR(__xludf.DUMMYFUNCTION("""COMPUTED_VALUE"""),1.0) -> 1 | Q24: =IFERROR(__xludf.DUMMYFUNCTION("""COMPUTED_VALUE"""),1.0) -> 1 | R24: =IFERROR(__xludf.DUMMYFUNCTION("""COMPUTED_VALUE"""),1.0) -> 1 | S24: =IFERROR(__xludf.DUMMYFUNCTION("""COMPUTED_VALUE"""),990.0) -> 990 | T24: =IFERROR(__xludf.DUMMYFUNCTION("""COMPUTED_VALUE"""),573.0) -> 573 | U24: =IFERROR(__xludf.DUMMYFUNCTION("""COMPUTED_VALUE"""),478.0) -> 478 | V24: =if(W24>0,W24,SUM(R24:T24)+X24) -> 1564
A25: =if(E25="","", CONCAT("2026-",E25)) -> 2026-W22 | B25: =IFERROR(__xludf.DUMMYFUNCTION("""COMPUTED_VALUE"""),"FE0713B") -> FE0713B | C25: =IFERROR(__xludf.DUMMYFUNCTION("""COMPUTED_VALUE"""),"Keto") -> Keto | D25: =IFERROR(__xludf.DUMMYFUNCTION("""COMPUTED_VALUE"""),"Cabbage in cheese sauce with minced beef") -> Cabbage in cheese sauce with minced beef | E25: =IFERROR(__xludf.DUMMYFUNCTION("""COMPUTED_VALUE"""),"W22") -> W22 | F25: =IFERROR(__xludf.DUMMYFUNCTION("""COMPUTED_VALUE"""),403.0) -> 403 | G25: =IFERROR(__xludf.DUMMYFUNCTION("""COMPUTED_VALUE"""),603.0) -> 603 | H25: =IFERROR(__xludf.DUMMYFUNCTION("""COMPUTED_VALUE"""),303.0) -> 303 | I25: =IFERROR(__xludf.DUMMYFUNCTION("""COMPUTED_VALUE"""),3247.0) -> 3247 | J25: =IFERROR(__xludf.DUMMYFUNCTION("""COMPUTED_VALUE"""),2027.0) -> 2027 | K25: =IFERROR(__xludf.DUMMYFUNCTION("""COMPUTED_VALUE"""),1640.0) -> 1640 | L25: =IFERROR(__xludf.DUMMYFUNCTION("""COMPUTED_VALUE"""),0.0) -> 0 | M25: =IFERROR(__xludf.DUMMYFUNCTION("""COMPUTED_VALUE"""),3267.0) -> 3267 | N25: =IFERROR(__xludf.DUMMYFUNCTION("""COMPUTED_VALUE"""),2047.0) -> 2047 | O25: =IFERROR(__xludf.DUMMYFUNCTION("""COMPUTED_VALUE"""),1660.0) -> 1660 | P25: =IFERROR(__xludf.DUMMYFUNCTION("""COMPUTED_VALUE"""),1.0) -> 1 | Q25: =IFERROR(__xludf.DUMMYFUNCTION("""COMPUTED_VALUE"""),1.0) -> 1 | R25: =IFERROR(__xludf.DUMMYFUNCTION("""COMPUTED_VALUE"""),1.0) -> 1 | S25: =IFERROR(__xludf.DUMMYFUNCTION("""COMPUTED_VALUE"""),3267.0) -> 3267 | T25: =IFERROR(__xludf.DUMMYFUNCTION("""COMPUTED_VALUE"""),2047.0) -> 2047 | U25: =IFERROR(__xludf.DUMMYFUNCTION("""COMPUTED_VALUE"""),1660.0) -> 1660 | V25: =if(W25>0,W25,SUM(R25:T25)+X25) -> 5315
A26: =if(E26="","", CONCAT("2026-",E26)) -> 2026-W22 | B26: =IFERROR(__xludf.DUMMYFUNCTION("""COMPUTED_VALUE"""),"FE0281E") -> FE0281E | C26: =IFERROR(__xludf.DUMMYFUNCTION("""COMPUTED_VALUE"""),"P+") -> P+ | D26: =IFERROR(__xludf.DUMMYFUNCTION("""COMPUTED_VALUE"""),"Spicy citrus salmon") -> Spicy citrus salmon | E26: =IFERROR(__xludf.DUMMYFUNCTION("""COMPUTED_VALUE"""),"W22") -> W22 | F26: =IFERROR(__xludf.DUMMYFUNCTION("""COMPUTED_VALUE"""),404.0) -> 404 | G26: =IFERROR(__xludf.DUMMYFUNCTION("""COMPUTED_VALUE"""),604.0) -> 604 | H26: =IFERROR(__xludf.DUMMYFUNCTION("""COMPUTED_VALUE"""),304.0) -> 304 | I26: =IFERROR(__xludf.DUMMYFUNCTION("""COMPUTED_VALUE"""),5301.0) -> 5301 | J26: =IFERROR(__xludf.DUMMYFUNCTION("""COMPUTED_VALUE"""),2968.0) -> 2968 | K26: =IFERROR(__xludf.DUMMYFUNCTION("""COMPUTED_VALUE"""),2263.0) -> 2263 | L26: =IFERROR(__xludf.DUMMYFUNCTION("""COMPUTED_VALUE"""),0.0) -> 0 | M26: =IFERROR(__xludf.DUMMYFUNCTION("""COMPUTED_VALUE"""),5321.0) -> 5321 | N26: =IFERROR(__xludf.DUMMYFUNCTION("""COMPUTED_VALUE"""),2988.0) -> 2988 | O26: =IFERROR(__xludf.DUMMYFUNCTION("""COMPUTED_VALUE"""),2283.0) -> 2283 | P26: =IFERROR(__xludf.DUMMYFUNCTION("""COMPUTED_VALUE"""),1.0) -> 1 | Q26: =IFERROR(__xludf.DUMMYFUNCTION("""COMPUTED_VALUE"""),1.0) -> 1 | R26: =IFERROR(__xludf.DUMMYFUNCTION("""COMPUTED_VALUE"""),1.0) -> 1 | S26: =IFERROR(__xludf.DUMMYFUNCTION("""COMPUTED_VALUE"""),5321.0) -> 5321 | T26: =IFERROR(__xludf.DUMMYFUNCTION("""COMPUTED_VALUE"""),2988.0) -> 2988 | U26: =IFERROR(__xludf.DUMMYFUNCTION("""COMPUTED_VALUE"""),2283.0) -> 2283 | V26: =if(W26>0,W26,SUM(R26:T26)+X26) -> 8310
A27: =if(E27="","", CONCAT("2026-",E27)) -> 2026-W22 | B27: =IFERROR(__xludf.DUMMYFUNCTION("""COMPUTED_VALUE"""),"FE0972B") -> FE0972B | C27: =IFERROR(__xludf.DUMMYFUNCTION("""COMPUTED_VALUE"""),"Keto") -> Keto | D27: =IFERROR(__xludf.DUMMYFUNCTION("""COMPUTED_VALUE"""),"Salmon Piccata") -> Salmon Piccata | E27: =IFERROR(__xludf.DUMMYFUNCTION("""COMPUTED_VALUE"""),"W22") -> W22 | F27: =IFERROR(__xludf.DUMMYFUNCTION("""COMPUTED_VALUE"""),406.0) -> 406 | G27: =IFERROR(__xludf.DUMMYFUNCTION("""COMPUTED_VALUE"""),606.0) -> 606 | H27: =IFERROR(__xludf.DUMMYFUNCTION("""COMPUTED_VALUE"""),306.0) -> 306 | I27: =IFERROR(__xludf.DUMMYFUNCTION("""COMPUTED_VALUE"""),2873.0) -> 2873 | J27: =IFERROR(__xludf.DUMMYFUNCTION("""COMPUTED_VALUE"""),1741.0) -> 1741 | K27: =IFERROR(__xludf.DUMMYFUNCTION("""COMPUTED_VALUE"""),1703.0) -> 1703 | L27: =IFERROR(__xludf.DUMMYFUNCTION("""COMPUTED_VALUE"""),0.0) -> 0 | M27: =IFERROR(__xludf.DUMMYFUNCTION("""COMPUTED_VALUE"""),2893.0) -> 2893 | N27: =IFERROR(__xludf.DUMMYFUNCTION("""COMPUTED_VALUE"""),1761.0) -> 1761 | O27: =IFERROR(__xludf.DUMMYFUNCTION("""COMPUTED_VALUE"""),1723.0) -> 1723 | P27: =IFERROR(__xludf.DUMMYFUNCTION("""COMPUTED_VALUE"""),1.0) -> 1 | Q27: =IFERROR(__xludf.DUMMYFUNCTION("""COMPUTED_VALUE"""),1.0) -> 1 | R27: =IFERROR(__xludf.DUMMYFUNCTION("""COMPUTED_VALUE"""),1.0) -> 1 | S27: =IFERROR(__xludf.DUMMYFUNCTION("""COMPUTED_VALUE"""),2893.0) -> 2893 | T27: =IFERROR(__xludf.DUMMYFUNCTION("""COMPUTED_VALUE"""),1761.0) -> 1761 | U27: =IFERROR(__xludf.DUMMYFUNCTION("""COMPUTED_VALUE"""),1723.0) -> 1723 | V27: =if(W27>0,W27,SUM(R27:T27)+X27) -> 4655
A28: =if(E28="","", CONCAT("2026-",E28)) -> 2026-W22 | B28: =IFERROR(__xludf.DUMMYFUNCTION("""COMPUTED_VALUE"""),"FE0794D") -> FE0794D | C28: =IFERROR(__xludf.DUMMYFUNCTION("""COMPUTED_VALUE"""),"Keto") -> Keto | D28: =IFERROR(__xludf.DUMMYFUNCTION("""COMPUTED_VALUE"""),"Loaded Bacon Shredded Chicken") -> Loaded Bacon Shredded Chicken | E28: =IFERROR(__xludf.DUMMYFUNCTION("""COMPUTED_VALUE"""),"W22") -> W22 | F28: =IFERROR(__xludf.DUMMYFUNCTION("""COMPUTED_VALUE"""),407.0) -> 407 | G28: =IFERROR(__xludf.DUMMYFUNCTION("""COMPUTED_VALUE"""),607.0) -> 607 | H28: =IFERROR(__xludf.DUMMYFUNCTION("""COMPUTED_VALUE"""),307.0) -> 307 | I28: =IFERROR(__xludf.DUMMYFUNCTION("""COMPUTED_VALUE"""),2499.0) -> 2499 | J28: =IFERROR(__xludf.DUMMYFUNCTION("""COMPUTED_VALUE"""),1574.0) -> 1574 | K28: =IFERROR(__xludf.DUMMYFUNCTION("""COMPUTED_VALUE"""),1402.0) -> 1402 | L28: =IFERROR(__xludf.DUMMYFUNCTION("""COMPUTED_VALUE"""),0.0) -> 0 | M28: =IFERROR(__xludf.DUMMYFUNCTION("""COMPUTED_VALUE"""),2519.0) -> 2519 | N28: =IFERROR(__xludf.DUMMYFUNCTION("""COMPUTED_VALUE"""),1594.0) -> 1594 | O28: =IFERROR(__xludf.DUMMYFUNCTION("""COMPUTED_VALUE"""),1422.0) -> 1422 | P28: =IFERROR(__xludf.DUMMYFUNCTION("""COMPUTED_VALUE"""),1.0) -> 1 | Q28: =IFERROR(__xludf.DUMMYFUNCTION("""COMPUTED_VALUE"""),1.0) -> 1 | R28: =IFERROR(__xludf.DUMMYFUNCTION("""COMPUTED_VALUE"""),1.0) -> 1 | S28: =IFERROR(__xludf.DUMMYFUNCTION("""COMPUTED_VALUE"""),2519.0) -> 2519 | T28: =IFERROR(__xludf.DUMMYFUNCTION("""COMPUTED_VALUE"""),1594.0) -> 1594 | U28: =IFERROR(__xludf.DUMMYFUNCTION("""COMPUTED_VALUE"""),1422.0) -> 1422 | V28: =if(W28>0,W28,SUM(R28:T28)+X28) -> 4114
A29: =if(E29="","", CONCAT("2026-",E29)) -> 2026-W22 | B29: =IFERROR(__xludf.DUMMYFUNCTION("""COMPUTED_VALUE"""),"FE0121C") -> FE0121C | C29: =IFERROR(__xludf.DUMMYFUNCTION("""COMPUTED_VALUE"""),"Veggie") -> Veggie | D29: =IFERROR(__xludf.DUMMYFUNCTION("""COMPUTED_VALUE"""),"Mexican style corn cake") -> Mexican style corn cake | E29: =IFERROR(__xludf.DUMMYFUNCTION("""COMPUTED_VALUE"""),"W22") -> W22 | F29: =IFERROR(__xludf.DUMMYFUNCTION("""COMPUTED_VALUE"""),409.0) -> 409 | G29: =IFERROR(__xludf.DUMMYFUNCTION("""COMPUTED_VALUE"""),609.0) -> 609 | H29: =IFERROR(__xludf.DUMMYFUNCTION("""COMPUTED_VALUE"""),309.0) -> 309 | I29: =IFERROR(__xludf.DUMMYFUNCTION("""COMPUTED_VALUE"""),451.0) -> 451 | J29: =IFERROR(__xludf.DUMMYFUNCTION("""COMPUTED_VALUE"""),202.0) -> 202 | K29: =IFERROR(__xludf.DUMMYFUNCTION("""COMPUTED_VALUE"""),236.0) -> 236 | L29: =IFERROR(__xludf.DUMMYFUNCTION("""COMPUTED_VALUE"""),0.0) -> 0 | M29: =IFERROR(__xludf.DUMMYFUNCTION("""COMPUTED_VALUE"""),471.0) -> 471 | N29: =IFERROR(__xludf.DUMMYFUNCTION("""COMPUTED_VALUE"""),222.0) -> 222 | O29: =IFERROR(__xludf.DUMMYFUNCTION("""COMPUTED_VALUE"""),256.0) -> 256 | P29: =IFERROR(__xludf.DUMMYFUNCTION("""COMPUTED_VALUE"""),1.0) -> 1 | Q29: =IFERROR(__xludf.DUMMYFUNCTION("""COMPUTED_VALUE"""),1.0) -> 1 | R29: =IFERROR(__xludf.DUMMYFUNCTION("""COMPUTED_VALUE"""),1.0) -> 1 | S29: =IFERROR(__xludf.DUMMYFUNCTION("""COMPUTED_VALUE"""),471.0) -> 471 | T29: =IFERROR(__xludf.DUMMYFUNCTION("""COMPUTED_VALUE"""),222.0) -> 222 | U29: =IFERROR(__xludf.DUMMYFUNCTION("""COMPUTED_VALUE"""),256.0) -> 256 | V29: =if(W29>0,W29,SUM(R29:T29)+X29) -> 694
A30: =if(E30="","", CONCAT("2026-",E30)) -> 2026-W22 | B30: =IFERROR(__xludf.DUMMYFUNCTION("""COMPUTED_VALUE"""),"FE0131C") -> FE0131C | C30: =IFERROR(__xludf.DUMMYFUNCTION("""COMPUTED_VALUE"""),"Veggie") -> Veggie | D30: =IFERROR(__xludf.DUMMYFUNCTION("""COMPUTED_VALUE"""),"Black bean bowl and enchilada sauce") -> Black bean bowl and enchilada sauce | E30: =IFERROR(__xludf.DUMMYFUNCTION("""COMPUTED_VALUE"""),"W22") -> W22 | F30: =IFERROR(__xludf.DUMMYFUNCTION("""COMPUTED_VALUE"""),410.0) -> 410 | G30: =IFERROR(__xludf.DUMMYFUNCTION("""COMPUTED_VALUE"""),610.0) -> 610 | H30: =IFERROR(__xludf.DUMMYFUNCTION("""COMPUTED_VALUE"""),310.0) -> 310 | I30: =IFERROR(__xludf.DUMMYFUNCTION("""COMPUTED_VALUE"""),593.0) -> 593 | J30: =IFERROR(__xludf.DUMMYFUNCTION("""COMPUTED_VALUE"""),271.0) -> 271 | K30: =IFERROR(__xludf.DUMMYFUNCTION("""COMPUTED_VALUE"""),284.0) -> 284 | L30: =IFERROR(__xludf.DUMMYFUNCTION("""COMPUTED_VALUE"""),0.0) -> 0 | M30: =IFERROR(__xludf.DUMMYFUNCTION("""COMPUTED_VALUE"""),613.0) -> 613 | N30: =IFERROR(__xludf.DUMMYFUNCTION("""COMPUTED_VALUE"""),291.0) -> 291 | O30: =IFERROR(__xludf.DUMMYFUNCTION("""COMPUTED_VALUE"""),304.0) -> 304 | P30: =IFERROR(__xludf.DUMMYFUNCTION("""COMPUTED_VALUE"""),1.0) -> 1 | Q30: =IFERROR(__xludf.DUMMYFUNCTION("""COMPUTED_VALUE"""),1.0) -> 1 | R30: =IFERROR(__xludf.DUMMYFUNCTION("""COMPUTED_VALUE"""),1.0) -> 1 | S30: =IFERROR(__xludf.DUMMYFUNCTION("""COMPUTED_VALUE"""),613.0) -> 613 | T30: =IFERROR(__xludf.DUMMYFUNCTION("""COMPUTED_VALUE"""),291.0) -> 291 | U30: =IFERROR(__xludf.DUMMYFUNCTION("""COMPUTED_VALUE"""),304.0) -> 304 | V30: =if(W30>0,W30,SUM(R30:T30)+X30) -> 905
A31: =if(E31="","", CONCAT("2026-",E31)) -> 2026-W22 | B31: =IFERROR(__xludf.DUMMYFUNCTION("""COMPUTED_VALUE"""),"FV4009A") -> FV4009A | C31: =IFERROR(__xludf.DUMMYFUNCTION("""COMPUTED_VALUE"""),"P+") -> P+ | D31: =IFERROR(__xludf.DUMMYFUNCTION("""COMPUTED_VALUE"""),"Salmon with a mustard dill sauce") -> Salmon with a mustard dill sauce | E31: =IFERROR(__xludf.DUMMYFUNCTION("""COMPUTED_VALUE"""),"W22") -> W22 | F31: =IFERROR(__xludf.DUMMYFUNCTION("""COMPUTED_VALUE"""),412.0) -> 412 | G31: =IFERROR(__xludf.DUMMYFUNCTION("""COMPUTED_VALUE"""),612.0) -> 612 | H31: =IFERROR(__xludf.DUMMYFUNCTION("""COMPUTED_VALUE"""),312.0) -> 312 | I31: =IFERROR(__xludf.DUMMYFUNCTION("""COMPUTED_VALUE"""),3296.0) -> 3296 | J31: =IFERROR(__xludf.DUMMYFUNCTION("""COMPUTED_VALUE"""),1499.0) -> 1499 | K31: =IFERROR(__xludf.DUMMYFUNCTION("""COMPUTED_VALUE"""),1276.0) -> 1276 | L31: =IFERROR(__xludf.DUMMYFUNCTION("""COMPUTED_VALUE"""),0.0) -> 0 | M31: =IFERROR(__xludf.DUMMYFUNCTION("""COMPUTED_VALUE"""),3316.0) -> 3316 | N31: =IFERROR(__xludf.DUMMYFUNCTION("""COMPUTED_VALUE"""),1519.0) -> 1519 | O31: =IFERROR(__xludf.DUMMYFUNCTION("""COMPUTED_VALUE"""),1296.0) -> 1296 | P31: =IFERROR(__xludf.DUMMYFUNCTION("""COMPUTED_VALUE"""),1.0) -> 1 | Q31: =IFERROR(__xludf.DUMMYFUNCTION("""COMPUTED_VALUE"""),1.0) -> 1 | R31: =IFERROR(__xludf.DUMMYFUNCTION("""COMPUTED_VALUE"""),1.0) -> 1 | S31: =IFERROR(__xludf.DUMMYFUNCTION("""COMPUTED_VALUE"""),3316.0) -> 3316 | T31: =IFERROR(__xludf.DUMMYFUNCTION("""COMPUTED_VALUE"""),1519.0) -> 1519 | U31: =IFERROR(__xludf.DUMMYFUNCTION("""COMPUTED_VALUE"""),1296.0) -> 1296 | V31: =if(W31>0,W31,SUM(R31:T31)+X31) -> 4836
A32: =if(E32="","", CONCAT("2026-",E32)) -> 2026-W22 | B32: =IFERROR(__xludf.DUMMYFUNCTION("""COMPUTED_VALUE"""),"FE1068A") -> FE1068A | C32: =IFERROR(__xludf.DUMMYFUNCTION("""COMPUTED_VALUE"""),"Flexible") -> Flexible | D32: =IFERROR(__xludf.DUMMYFUNCTION("""COMPUTED_VALUE"""),"Moroccan-style chicken thighs & tomato sauce") -> Moroccan-style chicken thighs & tomato sauce | E32: =IFERROR(__xludf.DUMMYFUNCTION("""COMPUTED_VALUE"""),"W22") -> W22 | F32: =IFERROR(__xludf.DUMMYFUNCTION("""COMPUTED_VALUE"""),414.0) -> 414 | G32: =IFERROR(__xludf.DUMMYFUNCTION("""COMPUTED_VALUE"""),614.0) -> 614 | H32: =IFERROR(__xludf.DUMMYFUNCTION("""COMPUTED_VALUE"""),314.0) -> 314 | I32: =IFERROR(__xludf.DUMMYFUNCTION("""COMPUTED_VALUE"""),1254.0) -> 1254 | J32: =IFERROR(__xludf.DUMMYFUNCTION("""COMPUTED_VALUE"""),681.0) -> 681 | K32: =IFERROR(__xludf.DUMMYFUNCTION("""COMPUTED_VALUE"""),722.0) -> 722 | L32: =IFERROR(__xludf.DUMMYFUNCTION("""COMPUTED_VALUE"""),0.0) -> 0 | M32: =IFERROR(__xludf.DUMMYFUNCTION("""COMPUTED_VALUE"""),1274.0) -> 1274 | N32: =IFERROR(__xludf.DUMMYFUNCTION("""COMPUTED_VALUE"""),701.0) -> 701 | O32: =IFERROR(__xludf.DUMMYFUNCTION("""COMPUTED_VALUE"""),742.0) -> 742 | P32: =IFERROR(__xludf.DUMMYFUNCTION("""COMPUTED_VALUE"""),1.0) -> 1 | Q32: =IFERROR(__xludf.DUMMYFUNCTION("""COMPUTED_VALUE"""),1.0) -> 1 | R32: =IFERROR(__xludf.DUMMYFUNCTION("""COMPUTED_VALUE"""),1.0) -> 1 | S32: =IFERROR(__xludf.DUMMYFUNCTION("""COMPUTED_VALUE"""),1274.0) -> 1274 | T32: =IFERROR(__xludf.DUMMYFUNCTION("""COMPUTED_VALUE"""),701.0) -> 701 | U32: =IFERROR(__xludf.DUMMYFUNCTION("""COMPUTED_VALUE"""),742.0) -> 742 | V32: =if(W32>0,W32,SUM(R32:T32)+X32) -> 1976
A33: =if(E33="","", CONCAT("2026-",E33)) -> 2026-W22 | B33: =IFERROR(__xludf.DUMMYFUNCTION("""COMPUTED_VALUE"""),"FV0345A") -> FV0345A | C33: =IFERROR(__xludf.DUMMYFUNCTION("""COMPUTED_VALUE"""),"Keto") -> Keto | D33: =IFERROR(__xludf.DUMMYFUNCTION("""COMPUTED_VALUE"""),"Beef Stroganoff Meatballs") -> Beef Stroganoff Meatballs | E33: =IFERROR(__xludf.DUMMYFUNCTION("""COMPUTED_VALUE"""),"W22") -> W22 | F33: =IFERROR(__xludf.DUMMYFUNCTION("""COMPUTED_VALUE"""),415.0) -> 415 | G33: =IFERROR(__xludf.DUMMYFUNCTION("""COMPUTED_VALUE"""),615.0) -> 615 | H33: =IFERROR(__xludf.DUMMYFUNCTION("""COMPUTED_VALUE"""),315.0) -> 315 | I33: =IFERROR(__xludf.DUMMYFUNCTION("""COMPUTED_VALUE"""),1147.0) -> 1147 | J33: =IFERROR(__xludf.DUMMYFUNCTION("""COMPUTED_VALUE"""),683.0) -> 683 | K33: =IFERROR(__xludf.DUMMYFUNCTION("""COMPUTED_VALUE"""),689.0) -> 689 | L33: =IFERROR(__xludf.DUMMYFUNCTION("""COMPUTED_VALUE"""),0.0) -> 0 | M33: =IFERROR(__xludf.DUMMYFUNCTION("""COMPUTED_VALUE"""),1167.0) -> 1167 | N33: =IFERROR(__xludf.DUMMYFUNCTION("""COMPUTED_VALUE"""),703.0) -> 703 | O33: =IFERROR(__xludf.DUMMYFUNCTION("""COMPUTED_VALUE"""),709.0) -> 709 | P33: =IFERROR(__xludf.DUMMYFUNCTION("""COMPUTED_VALUE"""),1.0) -> 1 | Q33: =IFERROR(__xludf.DUMMYFUNCTION("""COMPUTED_VALUE"""),1.0) -> 1 | R33: =IFERROR(__xludf.DUMMYFUNCTION("""COMPUTED_VALUE"""),1.0) -> 1 | S33: =IFERROR(__xludf.DUMMYFUNCTION("""COMPUTED_VALUE"""),1167.0) -> 1167 | T33: =IFERROR(__xludf.DUMMYFUNCTION("""COMPUTED_VALUE"""),703.0) -> 703 | U33: =IFERROR(__xludf.DUMMYFUNCTION("""COMPUTED_VALUE"""),709.0) -> 709 | V33: =if(W33>0,W33,SUM(R33:T33)+X33) -> 1871
A34: =if(E34="","", CONCAT("2026-",E34)) -> 2026-W22 | B34: =IFERROR(__xludf.DUMMYFUNCTION("""COMPUTED_VALUE"""),"FE0472B") -> FE0472B | C34: =IFERROR(__xludf.DUMMYFUNCTION("""COMPUTED_VALUE"""),"P+") -> P+ | D34: =IFERROR(__xludf.DUMMYFUNCTION("""COMPUTED_VALUE"""),"Indian style butter chicken") -> Indian style butter chicken | E34: =IFERROR(__xludf.DUMMYFUNCTION("""COMPUTED_VALUE"""),"W22") -> W22 | F34: =IFERROR(__xludf.DUMMYFUNCTION("""COMPUTED_VALUE"""),417.0) -> 417 | G34: =IFERROR(__xludf.DUMMYFUNCTION("""COMPUTED_VALUE"""),617.0) -> 617 | H34: =IFERROR(__xludf.DUMMYFUNCTION("""COMPUTED_VALUE"""),317.0) -> 317 | I34: =IFERROR(__xludf.DUMMYFUNCTION("""COMPUTED_VALUE"""),1939.0) -> 1939 | J34: =IFERROR(__xludf.DUMMYFUNCTION("""COMPUTED_VALUE"""),1040.0) -> 1040 | K34: =IFERROR(__xludf.DUMMYFUNCTION("""COMPUTED_VALUE"""),919.0) -> 919 | L34: =IFERROR(__xludf.DUMMYFUNCTION("""COMPUTED_VALUE"""),0.0) -> 0 | M34: =IFERROR(__xludf.DUMMYFUNCTION("""COMPUTED_VALUE"""),1959.0) -> 1959 | N34: =IFERROR(__xludf.DUMMYFUNCTION("""COMPUTED_VALUE"""),1060.0) -> 1060 | O34: =IFERROR(__xludf.DUMMYFUNCTION("""COMPUTED_VALUE"""),939.0) -> 939 | P34: =IFERROR(__xludf.DUMMYFUNCTION("""COMPUTED_VALUE"""),1.0) -> 1 | Q34: =IFERROR(__xludf.DUMMYFUNCTION("""COMPUTED_VALUE"""),1.0) -> 1 | R34: =IFERROR(__xludf.DUMMYFUNCTION("""COMPUTED_VALUE"""),1.0) -> 1 | S34: =IFERROR(__xludf.DUMMYFUNCTION("""COMPUTED_VALUE"""),1959.0) -> 1959 | T34: =IFERROR(__xludf.DUMMYFUNCTION("""COMPUTED_VALUE"""),1060.0) -> 1060 | U34: =IFERROR(__xludf.DUMMYFUNCTION("""COMPUTED_VALUE"""),939.0) -> 939 | V34: =if(W34>0,W34,SUM(R34:T34)+X34) -> 3020
A35: =if(E35="","", CONCAT("2026-",E35)) -> 2026-W22 | B35: =IFERROR(__xludf.DUMMYFUNCTION("""COMPUTED_VALUE"""),"FE1646A") -> FE1646A | C35: =IFERROR(__xludf.DUMMYFUNCTION("""COMPUTED_VALUE"""),"CS") -> CS | D35: =IFERROR(__xludf.DUMMYFUNCTION("""COMPUTED_VALUE"""),"Shrimp with Lemon Garlic Sauce & Spanakopita Style Rice") -> Shrimp with Lemon Garlic Sauce & Spanakopita Style Rice | E35: =IFERROR(__xludf.DUMMYFUNCTION("""COMPUTED_VALUE"""),"W22") -> W22 | F35: =IFERROR(__xludf.DUMMYFUNCTION("""COMPUTED_VALUE"""),419.0) -> 419 | G35: =IFERROR(__xludf.DUMMYFUNCTION("""COMPUTED_VALUE"""),619.0) -> 619 | H35: =IFERROR(__xludf.DUMMYFUNCTION("""COMPUTED_VALUE"""),319.0) -> 319 | I35: =IFERROR(__xludf.DUMMYFUNCTION("""COMPUTED_VALUE"""),2356.0) -> 2356 | J35: =IFERROR(__xludf.DUMMYFUNCTION("""COMPUTED_VALUE"""),1343.0) -> 1343 | K35: =IFERROR(__xludf.DUMMYFUNCTION("""COMPUTED_VALUE"""),1123.0) -> 1123 | L35: =IFERROR(__xludf.DUMMYFUNCTION("""COMPUTED_VALUE"""),0.0) -> 0 | M35: =IFERROR(__xludf.DUMMYFUNCTION("""COMPUTED_VALUE"""),2376.0) -> 2376 | N35: =IFERROR(__xludf.DUMMYFUNCTION("""COMPUTED_VALUE"""),1363.0) -> 1363 | O35: =IFERROR(__xludf.DUMMYFUNCTION("""COMPUTED_VALUE"""),1143.0) -> 1143 | P35: =IFERROR(__xludf.DUMMYFUNCTION("""COMPUTED_VALUE"""),1.0) -> 1 | Q35: =IFERROR(__xludf.DUMMYFUNCTION("""COMPUTED_VALUE"""),1.0) -> 1 | R35: =IFERROR(__xludf.DUMMYFUNCTION("""COMPUTED_VALUE"""),1.0) -> 1 | S35: =IFERROR(__xludf.DUMMYFUNCTION("""COMPUTED_VALUE"""),2376.0) -> 2376 | T35: =IFERROR(__xludf.DUMMYFUNCTION("""COMPUTED_VALUE"""),1363.0) -> 1363 | U35: =IFERROR(__xludf.DUMMYFUNCTION("""COMPUTED_VALUE"""),1143.0) -> 1143 | V35: =if(W35>0,W35,SUM(R35:T35)+X35) -> 3740
A36: =if(E36="","", CONCAT("2026-",E36)) -> 2026-W22 | B36: =IFERROR(__xludf.DUMMYFUNCTION("""COMPUTED_VALUE"""),"FE4065A") -> FE4065A | C36: =IFERROR(__xludf.DUMMYFUNCTION("""COMPUTED_VALUE"""),"Perf") -> Perf | D36: =IFERROR(__xludf.DUMMYFUNCTION("""COMPUTED_VALUE"""),"Spicy Beef & Black Bean Chili") -> Spicy Beef & Black Bean Chili | E36: =IFERROR(__xludf.DUMMYFUNCTION("""COMPUTED_VALUE"""),"W22") -> W22 | F36: =IFERROR(__xludf.DUMMYFUNCTION("""COMPUTED_VALUE"""),421.0) -> 421 | G36: =IFERROR(__xludf.DUMMYFUNCTION("""COMPUTED_VALUE"""),621.0) -> 621 | H36: =IFERROR(__xludf.DUMMYFUNCTION("""COMPUTED_VALUE"""),321.0) -> 321 | I36: =IFERROR(__xludf.DUMMYFUNCTION("""COMPUTED_VALUE"""),1472.0) -> 1472 | J36: =IFERROR(__xludf.DUMMYFUNCTION("""COMPUTED_VALUE"""),839.0) -> 839 | K36: =IFERROR(__xludf.DUMMYFUNCTION("""COMPUTED_VALUE"""),702.0) -> 702 | L36: =IFERROR(__xludf.DUMMYFUNCTION("""COMPUTED_VALUE"""),0.0) -> 0 | M36: =IFERROR(__xludf.DUMMYFUNCTION("""COMPUTED_VALUE"""),1492.0) -> 1492 | N36: =IFERROR(__xludf.DUMMYFUNCTION("""COMPUTED_VALUE"""),859.0) -> 859 | O36: =IFERROR(__xludf.DUMMYFUNCTION("""COMPUTED_VALUE"""),722.0) -> 722 | P36: =IFERROR(__xludf.DUMMYFUNCTION("""COMPUTED_VALUE"""),1.0) -> 1 | Q36: =IFERROR(__xludf.DUMMYFUNCTION("""COMPUTED_VALUE"""),1.0) -> 1 | R36: =IFERROR(__xludf.DUMMYFUNCTION("""COMPUTED_VALUE"""),1.0) -> 1 | S36: =IFERROR(__xludf.DUMMYFUNCTION("""COMPUTED_VALUE"""),1492.0) -> 1492 | T36: =IFERROR(__xludf.DUMMYFUNCTION("""COMPUTED_VALUE"""),859.0) -> 859 | U36: =IFERROR(__xludf.DUMMYFUNCTION("""COMPUTED_VALUE"""),722.0) -> 722 | V36: =if(W36>0,W36,SUM(R36:T36)+X36) -> 2352
A37: =if(E37="","", CONCAT("2026-",E37)) -> 2026-W23 | B37: =IFERROR(__xludf.DUMMYFUNCTION("""COMPUTED_VALUE"""),"FE0322O") -> FE0322O | C37: =IFERROR(__xludf.DUMMYFUNCTION("""COMPUTED_VALUE"""),"CS") -> CS | D37: =IFERROR(__xludf.DUMMYFUNCTION("""COMPUTED_VALUE"""),"Sour Cream & Chive Chicken") -> Sour Cream & Chive Chicken | E37: =IFERROR(__xludf.DUMMYFUNCTION("""COMPUTED_VALUE"""),"W23") -> W23 | F37: =IFERROR(__xludf.DUMMYFUNCTION("""COMPUTED_VALUE"""),402.0) -> 402 | G37: =IFERROR(__xludf.DUMMYFUNCTION("""COMPUTED_VALUE"""),602.0) -> 602 | H37: =IFERROR(__xludf.DUMMYFUNCTION("""COMPUTED_VALUE"""),302.0) -> 302 | I37: =IFERROR(__xludf.DUMMYFUNCTION("""COMPUTED_VALUE"""),3709.0) -> 3709 | J37: =IFERROR(__xludf.DUMMYFUNCTION("""COMPUTED_VALUE"""),2335.0) -> 2335 | K37: =IFERROR(__xludf.DUMMYFUNCTION("""COMPUTED_VALUE"""),1606.0) -> 1606 | L37: =IFERROR(__xludf.DUMMYFUNCTION("""COMPUTED_VALUE"""),0.0) -> 0 | M37: =IFERROR(__xludf.DUMMYFUNCTION("""COMPUTED_VALUE"""),3729.0) -> 3729 | N37: =IFERROR(__xludf.DUMMYFUNCTION("""COMPUTED_VALUE"""),2355.0) -> 2355 | O37: =IFERROR(__xludf.DUMMYFUNCTION("""COMPUTED_VALUE"""),1626.0) -> 1626 | P37: =IFERROR(__xludf.DUMMYFUNCTION("""COMPUTED_VALUE"""),1.0) -> 1 | Q37: =IFERROR(__xludf.DUMMYFUNCTION("""COMPUTED_VALUE"""),1.0) -> 1 | R37: =IFERROR(__xludf.DUMMYFUNCTION("""COMPUTED_VALUE"""),1.0) -> 1 | S37: =IFERROR(__xludf.DUMMYFUNCTION("""COMPUTED_VALUE"""),3729.0) -> 3729 | T37: =IFERROR(__xludf.DUMMYFUNCTION("""COMPUTED_VALUE"""),2355.0) -> 2355 | U37: =IFERROR(__xludf.DUMMYFUNCTION("""COMPUTED_VALUE"""),1626.0) -> 1626 | V37: =if(W37>0,W37,SUM(R37:T37)+X37) -> 6085
A38: =if(E38="","", CONCAT("2026-",E38)) -> 2026-W23 | B38: =IFERROR(__xludf.DUMMYFUNCTION("""COMPUTED_VALUE"""),"FV4063A") -> FV4063A | C38: =IFERROR(__xludf.DUMMYFUNCTION("""COMPUTED_VALUE"""),"Keto") -> Keto | D38: =IFERROR(__xludf.DUMMYFUNCTION("""COMPUTED_VALUE"""),"Cheddar pulled beef") -> Cheddar pulled beef | E38: =IFERROR(__xludf.DUMMYFUNCTION("""COMPUTED_VALUE"""),"W23") -> W23 | F38: =IFERROR(__xludf.DUMMYFUNCTION("""COMPUTED_VALUE"""),403.0) -> 403 | G38: =IFERROR(__xludf.DUMMYFUNCTION("""COMPUTED_VALUE"""),603.0) -> 603 | H38: =IFERROR(__xludf.DUMMYFUNCTION("""COMPUTED_VALUE"""),303.0) -> 303 | I38: =IFERROR(__xludf.DUMMYFUNCTION("""COMPUTED_VALUE"""),3247.0) -> 3247 | J38: =IFERROR(__xludf.DUMMYFUNCTION("""COMPUTED_VALUE"""),2027.0) -> 2027 | K38: =IFERROR(__xludf.DUMMYFUNCTION("""COMPUTED_VALUE"""),1640.0) -> 1640 | L38: =IFERROR(__xludf.DUMMYFUNCTION("""COMPUTED_VALUE"""),0.0) -> 0 | M38: =IFERROR(__xludf.DUMMYFUNCTION("""COMPUTED_VALUE"""),3267.0) -> 3267 | N38: =IFERROR(__xludf.DUMMYFUNCTION("""COMPUTED_VALUE"""),2047.0) -> 2047 | O38: =IFERROR(__xludf.DUMMYFUNCTION("""COMPUTED_VALUE"""),1660.0) -> 1660 | P38: =IFERROR(__xludf.DUMMYFUNCTION("""COMPUTED_VALUE"""),1.0) -> 1 | Q38: =IFERROR(__xludf.DUMMYFUNCTION("""COMPUTED_VALUE"""),1.0) -> 1 | R38: =IFERROR(__xludf.DUMMYFUNCTION("""COMPUTED_VALUE"""),1.0) -> 1 | S38: =IFERROR(__xludf.DUMMYFUNCTION("""COMPUTED_VALUE"""),3267.0) -> 3267 | T38: =IFERROR(__xludf.DUMMYFUNCTION("""COMPUTED_VALUE"""),2047.0) -> 2047 | U38: =IFERROR(__xludf.DUMMYFUNCTION("""COMPUTED_VALUE"""),1660.0) -> 1660 | V38: =if(W38>0,W38,SUM(R38:T38)+X38) -> 5315
A39: =if(E39="","", CONCAT("2026-",E39)) -> 2026-W23 | B39: =IFERROR(__xludf.DUMMYFUNCTION("""COMPUTED_VALUE"""),"FV1320A") -> FV1320A | C39: =IFERROR(__xludf.DUMMYFUNCTION("""COMPUTED_VALUE"""),"P+") -> P+ | D39: =IFERROR(__xludf.DUMMYFUNCTION("""COMPUTED_VALUE"""),"Ají Verde Salmon") -> Ají Verde Salmon | E39: =IFERROR(__xludf.DUMMYFUNCTION("""COMPUTED_VALUE"""),"W23") -> W23 | F39: =IFERROR(__xludf.DUMMYFUNCTION("""COMPUTED_VALUE"""),404.0) -> 404 | G39: =IFERROR(__xludf.DUMMYFUNCTION("""COMPUTED_VALUE"""),604.0) -> 604 | H39: =IFERROR(__xludf.DUMMYFUNCTION("""COMPUTED_VALUE"""),304.0) -> 304 | I39: =IFERROR(__xludf.DUMMYFUNCTION("""COMPUTED_VALUE"""),5301.0) -> 5301 | J39: =IFERROR(__xludf.DUMMYFUNCTION("""COMPUTED_VALUE"""),2968.0) -> 2968 | K39: =IFERROR(__xludf.DUMMYFUNCTION("""COMPUTED_VALUE"""),2263.0) -> 2263 | L39: =IFERROR(__xludf.DUMMYFUNCTION("""COMPUTED_VALUE"""),0.0) -> 0 | M39: =IFERROR(__xludf.DUMMYFUNCTION("""COMPUTED_VALUE"""),5321.0) -> 5321 | N39: =IFERROR(__xludf.DUMMYFUNCTION("""COMPUTED_VALUE"""),2988.0) -> 2988 | O39: =IFERROR(__xludf.DUMMYFUNCTION("""COMPUTED_VALUE"""),2283.0) -> 2283 | P39: =IFERROR(__xludf.DUMMYFUNCTION("""COMPUTED_VALUE"""),1.0) -> 1 | Q39: =IFERROR(__xludf.DUMMYFUNCTION("""COMPUTED_VALUE"""),1.0) -> 1 | R39: =IFERROR(__xludf.DUMMYFUNCTION("""COMPUTED_VALUE"""),1.0) -> 1 | S39: =IFERROR(__xludf.DUMMYFUNCTION("""COMPUTED_VALUE"""),5321.0) -> 5321 | T39: =IFERROR(__xludf.DUMMYFUNCTION("""COMPUTED_VALUE"""),2988.0) -> 2988 | U39: =IFERROR(__xludf.DUMMYFUNCTION("""COMPUTED_VALUE"""),2283.0) -> 2283 | V39: =if(W39>0,W39,SUM(R39:T39)+X39) -> 8310
A40: =if(E40="","", CONCAT("2026-",E40)) -> 2026-W23 | B40: =IFERROR(__xludf.DUMMYFUNCTION("""COMPUTED_VALUE"""),"FV0035A") -> FV0035A | C40: =IFERROR(__xludf.DUMMYFUNCTION("""COMPUTED_VALUE"""),"Keto") -> Keto | D40: =IFERROR(__xludf.DUMMYFUNCTION("""COMPUTED_VALUE"""),"Salmon with spinach pesto") -> Salmon with spinach pesto | E40: =IFERROR(__xludf.DUMMYFUNCTION("""COMPUTED_VALUE"""),"W23") -> W23 | F40: =IFERROR(__xludf.DUMMYFUNCTION("""COMPUTED_VALUE"""),406.0) -> 406 | G40: =IFERROR(__xludf.DUMMYFUNCTION("""COMPUTED_VALUE"""),606.0) -> 606 | H40: =IFERROR(__xludf.DUMMYFUNCTION("""COMPUTED_VALUE"""),306.0) -> 306 | I40: =IFERROR(__xludf.DUMMYFUNCTION("""COMPUTED_VALUE"""),2873.0) -> 2873 | J40: =IFERROR(__xludf.DUMMYFUNCTION("""COMPUTED_VALUE"""),1741.0) -> 1741 | K40: =IFERROR(__xludf.DUMMYFUNCTION("""COMPUTED_VALUE"""),1703.0) -> 1703 | L40: =IFERROR(__xludf.DUMMYFUNCTION("""COMPUTED_VALUE"""),0.0) -> 0 | M40: =IFERROR(__xludf.DUMMYFUNCTION("""COMPUTED_VALUE"""),2893.0) -> 2893 | N40: =IFERROR(__xludf.DUMMYFUNCTION("""COMPUTED_VALUE"""),1761.0) -> 1761 | O40: =IFERROR(__xludf.DUMMYFUNCTION("""COMPUTED_VALUE"""),1723.0) -> 1723 | P40: =IFERROR(__xludf.DUMMYFUNCTION("""COMPUTED_VALUE"""),1.0) -> 1 | Q40: =IFERROR(__xludf.DUMMYFUNCTION("""COMPUTED_VALUE"""),1.0) -> 1 | R40: =IFERROR(__xludf.DUMMYFUNCTION("""COMPUTED_VALUE"""),1.0) -> 1 | S40: =IFERROR(__xludf.DUMMYFUNCTION("""COMPUTED_VALUE"""),2893.0) -> 2893 | T40: =IFERROR(__xludf.DUMMYFUNCTION("""COMPUTED_VALUE"""),1761.0) -> 1761 | U40: =IFERROR(__xludf.DUMMYFUNCTION("""COMPUTED_VALUE"""),1723.0) -> 1723 | V40: =if(W40>0,W40,SUM(R40:T40)+X40) -> 4655
A41: =if(E41="","", CONCAT("2026-",E41)) -> 2026-W23 | B41: =IFERROR(__xludf.DUMMYFUNCTION("""COMPUTED_VALUE"""),"FV0401A") -> FV0401A | C41: =IFERROR(__xludf.DUMMYFUNCTION("""COMPUTED_VALUE"""),"Keto") -> Keto | D41: =IFERROR(__xludf.DUMMYFUNCTION("""COMPUTED_VALUE"""),"Pulled chicken with cheddar and bacon") -> Pulled chicken with cheddar and bacon | E41: =IFERROR(__xludf.DUMMYFUNCTION("""COMPUTED_VALUE"""),"W23") -> W23 | F41: =IFERROR(__xludf.DUMMYFUNCTION("""COMPUTED_VALUE"""),407.0) -> 407 | G41: =IFERROR(__xludf.DUMMYFUNCTION("""COMPUTED_VALUE"""),607.0) -> 607 | H41: =IFERROR(__xludf.DUMMYFUNCTION("""COMPUTED_VALUE"""),307.0) -> 307 | I41: =IFERROR(__xludf.DUMMYFUNCTION("""COMPUTED_VALUE"""),2499.0) -> 2499 | J41: =IFERROR(__xludf.DUMMYFUNCTION("""COMPUTED_VALUE"""),1574.0) -> 1574 | K41: =IFERROR(__xludf.DUMMYFUNCTION("""COMPUTED_VALUE"""),1402.0) -> 1402 | L41: =IFERROR(__xludf.DUMMYFUNCTION("""COMPUTED_VALUE"""),0.0) -> 0 | M41: =IFERROR(__xludf.DUMMYFUNCTION("""COMPUTED_VALUE"""),2519.0) -> 2519 | N41: =IFERROR(__xludf.DUMMYFUNCTION("""COMPUTED_VALUE"""),1594.0) -> 1594 | O41: =IFERROR(__xludf.DUMMYFUNCTION("""COMPUTED_VALUE"""),1422.0) -> 1422 | P41: =IFERROR(__xludf.DUMMYFUNCTION("""COMPUTED_VALUE"""),1.0) -> 1 | Q41: =IFERROR(__xludf.DUMMYFUNCTION("""COMPUTED_VALUE"""),1.0) -> 1 | R41: =IFERROR(__xludf.DUMMYFUNCTION("""COMPUTED_VALUE"""),1.0) -> 1 | S41: =IFERROR(__xludf.DUMMYFUNCTION("""COMPUTED_VALUE"""),2519.0) -> 2519 | T41: =IFERROR(__xludf.DUMMYFUNCTION("""COMPUTED_VALUE"""),1594.0) -> 1594 | U41: =IFERROR(__xludf.DUMMYFUNCTION("""COMPUTED_VALUE"""),1422.0) -> 1422 | V41: =if(W41>0,W41,SUM(R41:T41)+X41) -> 4114
A42: =if(E42="","", CONCAT("2026-",E42)) -> 2026-W23 | B42: =IFERROR(__xludf.DUMMYFUNCTION("""COMPUTED_VALUE"""),"FE0121C") -> FE0121C | C42: =IFERROR(__xludf.DUMMYFUNCTION("""COMPUTED_VALUE"""),"Veggie") -> Veggie | D42: =IFERROR(__xludf.DUMMYFUNCTION("""COMPUTED_VALUE"""),"Mexican style corn cake") -> Mexican style corn cake | E42: =IFERROR(__xludf.DUMMYFUNCTION("""COMPUTED_VALUE"""),"W23") -> W23 | F42: =IFERROR(__xludf.DUMMYFUNCTION("""COMPUTED_VALUE"""),409.0) -> 409 | G42: =IFERROR(__xludf.DUMMYFUNCTION("""COMPUTED_VALUE"""),609.0) -> 609 | H42: =IFERROR(__xludf.DUMMYFUNCTION("""COMPUTED_VALUE"""),309.0) -> 309 | I42: =IFERROR(__xludf.DUMMYFUNCTION("""COMPUTED_VALUE"""),451.0) -> 451 | J42: =IFERROR(__xludf.DUMMYFUNCTION("""COMPUTED_VALUE"""),202.0) -> 202 | K42: =IFERROR(__xludf.DUMMYFUNCTION("""COMPUTED_VALUE"""),236.0) -> 236 | L42: =IFERROR(__xludf.DUMMYFUNCTION("""COMPUTED_VALUE"""),0.0) -> 0 | M42: =IFERROR(__xludf.DUMMYFUNCTION("""COMPUTED_VALUE"""),471.0) -> 471 | N42: =IFERROR(__xludf.DUMMYFUNCTION("""COMPUTED_VALUE"""),222.0) -> 222 | O42: =IFERROR(__xludf.DUMMYFUNCTION("""COMPUTED_VALUE"""),256.0) -> 256 | P42: =IFERROR(__xludf.DUMMYFUNCTION("""COMPUTED_VALUE"""),1.0) -> 1 | Q42: =IFERROR(__xludf.DUMMYFUNCTION("""COMPUTED_VALUE"""),1.0) -> 1 | R42: =IFERROR(__xludf.DUMMYFUNCTION("""COMPUTED_VALUE"""),1.0) -> 1 | S42: =IFERROR(__xludf.DUMMYFUNCTION("""COMPUTED_VALUE"""),471.0) -> 471 | T42: =IFERROR(__xludf.DUMMYFUNCTION("""COMPUTED_VALUE"""),222.0) -> 222 | U42: =IFERROR(__xludf.DUMMYFUNCTION("""COMPUTED_VALUE"""),256.0) -> 256 | V42: =if(W42>0,W42,SUM(R42:T42)+X42) -> 694
A43: =if(E43="","", CONCAT("2026-",E43)) -> 2026-W23 | B43: =IFERROR(__xludf.DUMMYFUNCTION("""COMPUTED_VALUE"""),"FE0131C") -> FE0131C | C43: =IFERROR(__xludf.DUMMYFUNCTION("""COMPUTED_VALUE"""),"Veggie") -> Veggie | D43: =IFERROR(__xludf.DUMMYFUNCTION("""COMPUTED_VALUE"""),"Black bean bowl and enchilada sauce") -> Black bean bowl and enchilada sauce | E43: =IFERROR(__xludf.DUMMYFUNCTION("""COMPUTED_VALUE"""),"W23") -> W23 | F43: =IFERROR(__xludf.DUMMYFUNCTION("""COMPUTED_VALUE"""),410.0) -> 410 | G43: =IFERROR(__xludf.DUMMYFUNCTION("""COMPUTED_VALUE"""),610.0) -> 610 | H43: =IFERROR(__xludf.DUMMYFUNCTION("""COMPUTED_VALUE"""),310.0) -> 310 | I43: =IFERROR(__xludf.DUMMYFUNCTION("""COMPUTED_VALUE"""),593.0) -> 593 | J43: =IFERROR(__xludf.DUMMYFUNCTION("""COMPUTED_VALUE"""),271.0) -> 271 | K43: =IFERROR(__xludf.DUMMYFUNCTION("""COMPUTED_VALUE"""),284.0) -> 284 | L43: =IFERROR(__xludf.DUMMYFUNCTION("""COMPUTED_VALUE"""),0.0) -> 0 | M43: =IFERROR(__xludf.DUMMYFUNCTION("""COMPUTED_VALUE"""),613.0) -> 613 | N43: =IFERROR(__xludf.DUMMYFUNCTION("""COMPUTED_VALUE"""),291.0) -> 291 | O43: =IFERROR(__xludf.DUMMYFUNCTION("""COMPUTED_VALUE"""),304.0) -> 304 | P43: =IFERROR(__xludf.DUMMYFUNCTION("""COMPUTED_VALUE"""),1.0) -> 1 | Q43: =IFERROR(__xludf.DUMMYFUNCTION("""COMPUTED_VALUE"""),1.0) -> 1 | R43: =IFERROR(__xludf.DUMMYFUNCTION("""COMPUTED_VALUE"""),1.0) -> 1 | S43: =IFERROR(__xludf.DUMMYFUNCTION("""COMPUTED_VALUE"""),613.0) -> 613 | T43: =IFERROR(__xludf.DUMMYFUNCTION("""COMPUTED_VALUE"""),291.0) -> 291 | U43: =IFERROR(__xludf.DUMMYFUNCTION("""COMPUTED_VALUE"""),304.0) -> 304 | V43: =if(W43>0,W43,SUM(R43:T43)+X43) -> 905
A44: =if(E44="","", CONCAT("2026-",E44)) -> 2026-W23 | B44: =IFERROR(__xludf.DUMMYFUNCTION("""COMPUTED_VALUE"""),"FV1145A") -> FV1145A | C44: =IFERROR(__xludf.DUMMYFUNCTION("""COMPUTED_VALUE"""),"P+") -> P+ | D44: =IFERROR(__xludf.DUMMYFUNCTION("""COMPUTED_VALUE"""),"Roasted Salmon & Dill Yogurt") -> Roasted Salmon & Dill Yogurt | E44: =IFERROR(__xludf.DUMMYFUNCTION("""COMPUTED_VALUE"""),"W23") -> W23 | F44: =IFERROR(__xludf.DUMMYFUNCTION("""COMPUTED_VALUE"""),412.0) -> 412 | G44: =IFERROR(__xludf.DUMMYFUNCTION("""COMPUTED_VALUE"""),612.0) -> 612 | H44: =IFERROR(__xludf.DUMMYFUNCTION("""COMPUTED_VALUE"""),312.0) -> 312 | I44: =IFERROR(__xludf.DUMMYFUNCTION("""COMPUTED_VALUE"""),3296.0) -> 3296 | J44: =IFERROR(__xludf.DUMMYFUNCTION("""COMPUTED_VALUE"""),1499.0) -> 1499 | K44: =IFERROR(__xludf.DUMMYFUNCTION("""COMPUTED_VALUE"""),1276.0) -> 1276 | L44: =IFERROR(__xludf.DUMMYFUNCTION("""COMPUTED_VALUE"""),0.0) -> 0 | M44: =IFERROR(__xludf.DUMMYFUNCTION("""COMPUTED_VALUE"""),3316.0) -> 3316 | N44: =IFERROR(__xludf.DUMMYFUNCTION("""COMPUTED_VALUE"""),1519.0) -> 1519 | O44: =IFERROR(__xludf.DUMMYFUNCTION("""COMPUTED_VALUE"""),1296.0) -> 1296 | P44: =IFERROR(__xludf.DUMMYFUNCTION("""COMPUTED_VALUE"""),1.0) -> 1 | Q44: =IFERROR(__xludf.DUMMYFUNCTION("""COMPUTED_VALUE"""),1.0) -> 1 | R44: =IFERROR(__xludf.DUMMYFUNCTION("""COMPUTED_VALUE"""),1.0) -> 1 | S44: =IFERROR(__xludf.DUMMYFUNCTION("""COMPUTED_VALUE"""),3316.0) -> 3316 | T44: =IFERROR(__xludf.DUMMYFUNCTION("""COMPUTED_VALUE"""),1519.0) -> 1519 | U44: =IFERROR(__xludf.DUMMYFUNCTION("""COMPUTED_VALUE"""),1296.0) -> 1296 | V44: =if(W44>0,W44,SUM(R44:T44)+X44) -> 4836
A45: =if(E45="","", CONCAT("2026-",E45)) -> 2026-W23 | B45: =IFERROR(__xludf.DUMMYFUNCTION("""COMPUTED_VALUE"""),"FE0890B") -> FE0890B | C45: =IFERROR(__xludf.DUMMYFUNCTION("""COMPUTED_VALUE"""),"CS") -> CS | D45: =IFERROR(__xludf.DUMMYFUNCTION("""COMPUTED_VALUE"""),"Pork tenderloin with apple-mustard sauce") -> Pork tenderloin with apple-mustard sauce | E45: =IFERROR(__xludf.DUMMYFUNCTION("""COMPUTED_VALUE"""),"W23") -> W23 | F45: =IFERROR(__xludf.DUMMYFUNCTION("""COMPUTED_VALUE"""),413.0) -> 413 | G45: =IFERROR(__xludf.DUMMYFUNCTION("""COMPUTED_VALUE"""),613.0) -> 613 | H45: =IFERROR(__xludf.DUMMYFUNCTION("""COMPUTED_VALUE"""),313.0) -> 313 | I45: =IFERROR(__xludf.DUMMYFUNCTION("""COMPUTED_VALUE"""),4121.0) -> 4121 | J45: =IFERROR(__xludf.DUMMYFUNCTION("""COMPUTED_VALUE"""),1998.0) -> 1998 | K45: =IFERROR(__xludf.DUMMYFUNCTION("""COMPUTED_VALUE"""),1576.0) -> 1576 | L45: =IFERROR(__xludf.DUMMYFUNCTION("""COMPUTED_VALUE"""),0.0) -> 0 | M45: =IFERROR(__xludf.DUMMYFUNCTION("""COMPUTED_VALUE"""),4141.0) -> 4141 | N45: =IFERROR(__xludf.DUMMYFUNCTION("""COMPUTED_VALUE"""),2018.0) -> 2018 | O45: =IFERROR(__xludf.DUMMYFUNCTION("""COMPUTED_VALUE"""),1596.0) -> 1596 | P45: =IFERROR(__xludf.DUMMYFUNCTION("""COMPUTED_VALUE"""),1.0) -> 1 | Q45: =IFERROR(__xludf.DUMMYFUNCTION("""COMPUTED_VALUE"""),1.0) -> 1 | R45: =IFERROR(__xludf.DUMMYFUNCTION("""COMPUTED_VALUE"""),1.0) -> 1 | S45: =IFERROR(__xludf.DUMMYFUNCTION("""COMPUTED_VALUE"""),4141.0) -> 4141 | T45: =IFERROR(__xludf.DUMMYFUNCTION("""COMPUTED_VALUE"""),2018.0) -> 2018 | U45: =IFERROR(__xludf.DUMMYFUNCTION("""COMPUTED_VALUE"""),1596.0) -> 1596 | V45: =if(W45>0,W45,SUM(R45:T45)+X45) -> 6160
A46: =if(E46="","", CONCAT("2026-",E46)) -> 2026-W23 | B46: =IFERROR(__xludf.DUMMYFUNCTION("""COMPUTED_VALUE"""),"FE1068A") -> FE1068A | C46: =IFERROR(__xludf.DUMMYFUNCTION("""COMPUTED_VALUE"""),"Flexible") -> Flexible | D46: =IFERROR(__xludf.DUMMYFUNCTION("""COMPUTED_VALUE"""),"Moroccan-style chicken thighs & tomato sauce") -> Moroccan-style chicken thighs & tomato sauce | E46: =IFERROR(__xludf.DUMMYFUNCTION("""COMPUTED_VALUE"""),"W23") -> W23 | F46: =IFERROR(__xludf.DUMMYFUNCTION("""COMPUTED_VALUE"""),414.0) -> 414 | G46: =IFERROR(__xludf.DUMMYFUNCTION("""COMPUTED_VALUE"""),614.0) -> 614 | H46: =IFERROR(__xludf.DUMMYFUNCTION("""COMPUTED_VALUE"""),314.0) -> 314 | I46: =IFERROR(__xludf.DUMMYFUNCTION("""COMPUTED_VALUE"""),1254.0) -> 1254 | J46: =IFERROR(__xludf.DUMMYFUNCTION("""COMPUTED_VALUE"""),681.0) -> 681 | K46: =IFERROR(__xludf.DUMMYFUNCTION("""COMPUTED_VALUE"""),722.0) -> 722 | L46: =IFERROR(__xludf.DUMMYFUNCTION("""COMPUTED_VALUE"""),0.0) -> 0 | M46: =IFERROR(__xludf.DUMMYFUNCTION("""COMPUTED_VALUE"""),1274.0) -> 1274 | N46: =IFERROR(__xludf.DUMMYFUNCTION("""COMPUTED_VALUE"""),701.0) -> 701 | O46: =IFERROR(__xludf.DUMMYFUNCTION("""COMPUTED_VALUE"""),742.0) -> 742 | P46: =IFERROR(__xludf.DUMMYFUNCTION("""COMPUTED_VALUE"""),1.0) -> 1 | Q46: =IFERROR(__xludf.DUMMYFUNCTION("""COMPUTED_VALUE"""),1.0) -> 1 | R46: =IFERROR(__xludf.DUMMYFUNCTION("""COMPUTED_VALUE"""),1.0) -> 1 | S46: =IFERROR(__xludf.DUMMYFUNCTION("""COMPUTED_VALUE"""),1274.0) -> 1274 | T46: =IFERROR(__xludf.DUMMYFUNCTION("""COMPUTED_VALUE"""),701.0) -> 701 | U46: =IFERROR(__xludf.DUMMYFUNCTION("""COMPUTED_VALUE"""),742.0) -> 742
A47: =if(E47="","", CONCAT("2026-",E47)) -> 2026-W23 | B47: =IFERROR(__xludf.DUMMYFUNCTION("""COMPUTED_VALUE"""),"FE1404B") -> FE1404B | C47: =IFERROR(__xludf.DUMMYFUNCTION("""COMPUTED_VALUE"""),"Flexible") -> Flexible | D47: =IFERROR(__xludf.DUMMYFUNCTION("""COMPUTED_VALUE"""),"Bulgogi Pulled Beef Bowl") -> Bulgogi Pulled Beef Bowl | E47: =IFERROR(__xludf.DUMMYFUNCTION("""COMPUTED_VALUE"""),"W23") -> W23 | F47: =IFERROR(__xludf.DUMMYFUNCTION("""COMPUTED_VALUE"""),416.0) -> 416 | G47: =IFERROR(__xludf.DUMMYFUNCTION("""COMPUTED_VALUE"""),616.0) -> 616 | H47: =IFERROR(__xludf.DUMMYFUNCTION("""COMPUTED_VALUE"""),316.0) -> 316 | I47: =IFERROR(__xludf.DUMMYFUNCTION("""COMPUTED_VALUE"""),971.0) -> 971 | J47: =IFERROR(__xludf.DUMMYFUNCTION("""COMPUTED_VALUE"""),497.0) -> 497 | K47: =IFERROR(__xludf.DUMMYFUNCTION("""COMPUTED_VALUE"""),514.0) -> 514 | L47: =IFERROR(__xludf.DUMMYFUNCTION("""COMPUTED_VALUE"""),0.0) -> 0 | M47: =IFERROR(__xludf.DUMMYFUNCTION("""COMPUTED_VALUE"""),991.0) -> 991 | N47: =IFERROR(__xludf.DUMMYFUNCTION("""COMPUTED_VALUE"""),517.0) -> 517 | O47: =IFERROR(__xludf.DUMMYFUNCTION("""COMPUTED_VALUE"""),534.0) -> 534 | P47: =IFERROR(__xludf.DUMMYFUNCTION("""COMPUTED_VALUE"""),1.0) -> 1 | Q47: =IFERROR(__xludf.DUMMYFUNCTION("""COMPUTED_VALUE"""),1.0) -> 1 | R47: =IFERROR(__xludf.DUMMYFUNCTION("""COMPUTED_VALUE"""),1.0) -> 1 | S47: =IFERROR(__xludf.DUMMYFUNCTION("""COMPUTED_VALUE"""),991.0) -> 991 | T47: =IFERROR(__xludf.DUMMYFUNCTION("""COMPUTED_VALUE"""),517.0) -> 517 | U47: =IFERROR(__xludf.DUMMYFUNCTION("""COMPUTED_VALUE"""),534.0) -> 534
A48: =if(E48="","", CONCAT("2026-",E48)) -> 2026-W23 | B48: =IFERROR(__xludf.DUMMYFUNCTION("""COMPUTED_VALUE"""),"FV4053A") -> FV4053A | C48: =IFERROR(__xludf.DUMMYFUNCTION("""COMPUTED_VALUE"""),"P+") -> P+ | D48: =IFERROR(__xludf.DUMMYFUNCTION("""COMPUTED_VALUE"""),"Gochugaru Chicken") -> Gochugaru Chicken | E48: =IFERROR(__xludf.DUMMYFUNCTION("""COMPUTED_VALUE"""),"W23") -> W23 | F48: =IFERROR(__xludf.DUMMYFUNCTION("""COMPUTED_VALUE"""),417.0) -> 417 | G48: =IFERROR(__xludf.DUMMYFUNCTION("""COMPUTED_VALUE"""),617.0) -> 617 | H48: =IFERROR(__xludf.DUMMYFUNCTION("""COMPUTED_VALUE"""),317.0) -> 317 | I48: =IFERROR(__xludf.DUMMYFUNCTION("""COMPUTED_VALUE"""),1939.0) -> 1939 | J48: =IFERROR(__xludf.DUMMYFUNCTION("""COMPUTED_VALUE"""),1040.0) -> 1040 | K48: =IFERROR(__xludf.DUMMYFUNCTION("""COMPUTED_VALUE"""),919.0) -> 919 | L48: =IFERROR(__xludf.DUMMYFUNCTION("""COMPUTED_VALUE"""),0.0) -> 0 | M48: =IFERROR(__xludf.DUMMYFUNCTION("""COMPUTED_VALUE"""),1959.0) -> 1959 | N48: =IFERROR(__xludf.DUMMYFUNCTION("""COMPUTED_VALUE"""),1060.0) -> 1060 | O48: =IFERROR(__xludf.DUMMYFUNCTION("""COMPUTED_VALUE"""),939.0) -> 939 | P48: =IFERROR(__xludf.DUMMYFUNCTION("""COMPUTED_VALUE"""),1.0) -> 1 | Q48: =IFERROR(__xludf.DUMMYFUNCTION("""COMPUTED_VALUE"""),1.0) -> 1 | R48: =IFERROR(__xludf.DUMMYFUNCTION("""COMPUTED_VALUE"""),1.0) -> 1 | S48: =IFERROR(__xludf.DUMMYFUNCTION("""COMPUTED_VALUE"""),1959.0) -> 1959 | T48: =IFERROR(__xludf.DUMMYFUNCTION("""COMPUTED_VALUE"""),1060.0) -> 1060 | U48: =IFERROR(__xludf.DUMMYFUNCTION("""COMPUTED_VALUE"""),939.0) -> 939
A49: =if(E49="","", CONCAT("2026-",E49)) -> 2026-W23 | B49: =IFERROR(__xludf.DUMMYFUNCTION("""COMPUTED_VALUE"""),"FE4042A") -> FE4042A | C49: =IFERROR(__xludf.DUMMYFUNCTION("""COMPUTED_VALUE"""),"CS") -> CS | D49: =IFERROR(__xludf.DUMMYFUNCTION("""COMPUTED_VALUE"""),"Pork tenderloin and Mediterranean mash") -> Pork tenderloin and Mediterranean mash | E49: =IFERROR(__xludf.DUMMYFUNCTION("""COMPUTED_VALUE"""),"W23") -> W23 | F49: =IFERROR(__xludf.DUMMYFUNCTION("""COMPUTED_VALUE"""),418.0) -> 418 | G49: =IFERROR(__xludf.DUMMYFUNCTION("""COMPUTED_VALUE"""),618.0) -> 618 | H49: =IFERROR(__xludf.DUMMYFUNCTION("""COMPUTED_VALUE"""),318.0) -> 318 | I49: =IFERROR(__xludf.DUMMYFUNCTION("""COMPUTED_VALUE"""),976.0) -> 976 | J49: =IFERROR(__xludf.DUMMYFUNCTION("""COMPUTED_VALUE"""),663.0) -> 663 | K49: =IFERROR(__xludf.DUMMYFUNCTION("""COMPUTED_VALUE"""),451.0) -> 451 | L49: =IFERROR(__xludf.DUMMYFUNCTION("""COMPUTED_VALUE"""),0.0) -> 0 | M49: =IFERROR(__xludf.DUMMYFUNCTION("""COMPUTED_VALUE"""),996.0) -> 996 | N49: =IFERROR(__xludf.DUMMYFUNCTION("""COMPUTED_VALUE"""),683.0) -> 683 | O49: =IFERROR(__xludf.DUMMYFUNCTION("""COMPUTED_VALUE"""),471.0) -> 471 | P49: =IFERROR(__xludf.DUMMYFUNCTION("""COMPUTED_VALUE"""),1.0) -> 1 | Q49: =IFERROR(__xludf.DUMMYFUNCTION("""COMPUTED_VALUE"""),1.0) -> 1 | R49: =IFERROR(__xludf.DUMMYFUNCTION("""COMPUTED_VALUE"""),1.0) -> 1 | S49: =IFERROR(__xludf.DUMMYFUNCTION("""COMPUTED_VALUE"""),996.0) -> 996 | T49: =IFERROR(__xludf.DUMMYFUNCTION("""COMPUTED_VALUE"""),683.0) -> 683 | U49: =IFERROR(__xludf.DUMMYFUNCTION("""COMPUTED_VALUE"""),471.0) -> 471
A50: =if(E50="","", CONCAT("2026-",E50)) -> 2026-W23 | B50: =IFERROR(__xludf.DUMMYFUNCTION("""COMPUTED_VALUE"""),"FV0601A") -> FV0601A | C50: =IFERROR(__xludf.DUMMYFUNCTION("""COMPUTED_VALUE"""),"Perf") -> Perf | D50: =IFERROR(__xludf.DUMMYFUNCTION("""COMPUTED_VALUE"""),"Mozzarella Burger & Roasted Potatoes") -> Mozzarella Burger & Roasted Potatoes | E50: =IFERROR(__xludf.DUMMYFUNCTION("""COMPUTED_VALUE"""),"W23") -> W23 | F50: =IFERROR(__xludf.DUMMYFUNCTION("""COMPUTED_VALUE"""),421.0) -> 421 | G50: =IFERROR(__xludf.DUMMYFUNCTION("""COMPUTED_VALUE"""),621.0) -> 621 | H50: =IFERROR(__xludf.DUMMYFUNCTION("""COMPUTED_VALUE"""),321.0) -> 321 | I50: =IFERROR(__xludf.DUMMYFUNCTION("""COMPUTED_VALUE"""),1472.0) -> 1472 | J50: =IFERROR(__xludf.DUMMYFUNCTION("""COMPUTED_VALUE"""),839.0) -> 839 | K50: =IFERROR(__xludf.DUMMYFUNCTION("""COMPUTED_VALUE"""),702.0) -> 702 | L50: =IFERROR(__xludf.DUMMYFUNCTION("""COMPUTED_VALUE"""),0.0) -> 0 | M50: =IFERROR(__xludf.DUMMYFUNCTION("""COMPUTED_VALUE"""),1492.0) -> 1492 | N50: =IFERROR(__xludf.DUMMYFUNCTION("""COMPUTED_VALUE"""),859.0) -> 859 | O50: =IFERROR(__xludf.DUMMYFUNCTION("""COMPUTED_VALUE"""),722.0) -> 722 | P50: =IFERROR(__xludf.DUMMYFUNCTION("""COMPUTED_VALUE"""),1.0) -> 1 | Q50: =IFERROR(__xludf.DUMMYFUNCTION("""COMPUTED_VALUE"""),1.0) -> 1 | R50: =IFERROR(__xludf.DUMMYFUNCTION("""COMPUTED_VALUE"""),1.0) -> 1 | S50: =IFERROR(__xludf.DUMMYFUNCTION("""COMPUTED_VALUE"""),1492.0) -> 1492 | T50: =IFERROR(__xludf.DUMMYFUNCTION("""COMPUTED_VALUE"""),859.0) -> 859 | U50: =IFERROR(__xludf.DUMMYFUNCTION("""COMPUTED_VALUE"""),722.0) -> 722
A51: =if(E51="","", CONCAT("2026-",E51))
A52: =if(E52="","", CONCAT("2026-",E52))
A53: =if(E53="","", CONCAT("2026-",E53))
A54: =if(E54="","", CONCAT("2026-",E54))
A55: =if(E55="","", CONCAT("2026-",E55))
A56: =if(E56="","", CONCAT("2026-",E56))
A57: =if(E57="","", CONCAT("2026-",E57))
A58: =if(E58="","", CONCAT("2026-",E58))
A59: =if(E59="","", CONCAT("2026-",E59))
A60: =if(E60="","", CONCAT("2026-",E60))
A61: =if(E61="","", CONCAT("2026-",E61))
A62: =if(E62="","", CONCAT("2026-",E62))
... A92: =if(E92="","", CONCAT("2026-",E92))

Sheet Volume Split Up-To-Date
A1: Source | C1: Source | H1: Source | I1: Source | J1: Source | K1: Source | O1: Verden Share | R1: Verden Absolute | U1: Maitre Absolute
A2: Recipe Code | B2: Meal Pref | C2: Recipe Name | D2: Week | E2: Slot BENL | F2: Slot DKSE | G2: Slot DE | H2: BENL Volume | I2: DKSE Volume | J2: DE Volume | K2: Convini DE | L2: BENL Volume + Buffer | M2: DKSE Volume + Buffer | N2: DE Volume + Buffer | O2: BENL Volume | P2: DKSE Volume | Q2: DE Volume | R2: BENL Volume | S2: DKSE Volume | T2: DE Volume | U2: BENL Volume | V2: DKSE Volume | W2: DE Volume
A3: =IFERROR(__xludf.DUMMYFUNCTION("if(E3=506,""FEA006A"",INDEX(IMPORTRANGE(""https://docs.google.com/spreadsheets/d/1WbE6HOh_eG5_DM53SVfuckYm0VQnhNvuwjql7Tw1FX0/edit?gid=660406182#gid=660406182"", ""'""&D3&""'!H2:H45""),match(E3,IMPORTRANGE(""https://docs.google.com/spreadsheets/d/1WbE6HOh"&"_eG5_DM53SVfuckYm0VQnhNvuwjql7Tw1FX0/edit?gid=660406182#gid=660406182"", ""'""&D3&""'!B2:B45""),0),1))"),"FE4014B") -> FE4014B | B3: =IFERROR(__xludf.DUMMYFUNCTION("if(E3=506,""-"",INDEX(IMPORTRANGE(""https://docs.google.com/spreadsheets/d/1WbE6HOh_eG5_DM53SVfuckYm0VQnhNvuwjql7Tw1FX0/edit?gid=660406182#gid=660406182"", ""'""&D3&""'!D2:D45""),match(E3,IMPORTRANGE(""https://docs.google.com/spreadsheets/d/1WbE6HOh_eG5_D"&"M53SVfuckYm0VQnhNvuwjql7Tw1FX0/edit?gid=660406182#gid=660406182"", ""'""&D3&""'!B2:B45""),0),1))"),"CS") -> CS | C3: =IFERROR(__xludf.DUMMYFUNCTION("if(A3=""FEA006A"",""Garlic Herb Grilled Chicken"", ifna(INDEX(IMPORTRANGE(""https://docs.google.com/spreadsheets/d/1mnGm3iYGkB4FyqAD-LwwVYksgBMX_SY4qHQa16KgMiw/edit?gid=1956920866#gid=1956920866"", ""'EU Meal Database'!$E$2:$E""),MATCH(A3,IMPORTRANGE(""ht"&"tps://docs.google.com/spreadsheets/d/1mnGm3iYGkB4FyqAD-LwwVYksgBMX_SY4qHQa16KgMiw/edit?gid=1956920866#gid=1956920866"", ""'EU Meal Database'!$A$2:$A""),0)),INDEX(IMPORTRANGE(""https://docs.google.com/spreadsheets/d/1n4t_JF5P_MLd0hMmhjv1A2rgLKdyee_-mrZZmdZ"&"r9G4/edit?gid=670402169#gid=670402169"", ""'Meal DB_Product'!$B$2:$B""),MATCH(A3,IMPORTRANGE(""https://docs.google.com/spreadsheets/d/1n4t_JF5P_MLd0hMmhjv1A2rgLKdyee_-mrZZmdZr9G4/edit?gid=670402169#gid=670402169"", ""'Meal DB_Product'!$A$2:$A""),0))))"),"Creamy basil risotto with chicken") -> Creamy basil risotto with chicken | D3: W17 | E3: 401 | F3: 601 | G3: 301 | H3: =IFERROR(__xludf.DUMMYFUNCTION("IMPORTRANGE(""https://docs.google.com/spreadsheets/d/1NX4ccmp9EHgjcQcZPt2RVC4dGZm-Lhq_XEIxgs3iBP4/edit?gid=535876848#gid=535876848"", ""'Running Forecast - All Markets'!$E$1298:$G"")"),7385.0) -> 7385 | I3: =IFERROR(__xludf.DUMMYFUNCTION("""COMPUTED_VALUE"""),3806.0) -> 3806 | J3: =IFERROR(__xludf.DUMMYFUNCTION("""COMPUTED_VALUE"""),3024.0) -> 3024 | K3: =IFERROR(__xludf.DUMMYFUNCTION("IMPORTRANGE(""https://docs.google.com/spreadsheets/d/1NX4ccmp9EHgjcQcZPt2RVC4dGZm-Lhq_XEIxgs3iBP4/edit?gid=535876848#gid=535876848"", ""'Running Forecast - All Markets'!$k$1298:$k"")"),"") | L3: =H3+20 -> 7405 | M3: =I3+20 -> 3826 | N3: =J3+20+K3 -> 3044 | O3: 0 | P3: 0 | Q3: 0 | R3: =L3*O3 -> 0 | S3: =M3*P3 -> 0 | T3: =N3*Q3 -> 0 | U3: =L3-R3 -> 7405 | V3: =M3-S3 -> 3826 | W3: =N3-T3 -> 3044
A4: =IFERROR(__xludf.DUMMYFUNCTION("if(E4=506,""FEA006A"",INDEX(IMPORTRANGE(""https://docs.google.com/spreadsheets/d/1WbE6HOh_eG5_DM53SVfuckYm0VQnhNvuwjql7Tw1FX0/edit?gid=660406182#gid=660406182"", ""'""&D4&""'!H2:H45""),match(E4,IMPORTRANGE(""https://docs.google.com/spreadsheets/d/1WbE6HOh"&"_eG5_DM53SVfuckYm0VQnhNvuwjql7Tw1FX0/edit?gid=660406182#gid=660406182"", ""'""&D4&""'!B2:B45""),0),1))"),"FE0322O") -> FE0322O | B4: =IFERROR(__xludf.DUMMYFUNCTION("if(E4=506,""-"",INDEX(IMPORTRANGE(""https://docs.google.com/spreadsheets/d/1WbE6HOh_eG5_DM53SVfuckYm0VQnhNvuwjql7Tw1FX0/edit?gid=660406182#gid=660406182"", ""'""&D4&""'!D2:D45""),match(E4,IMPORTRANGE(""https://docs.google.com/spreadsheets/d/1WbE6HOh_eG5_D"&"M53SVfuckYm0VQnhNvuwjql7Tw1FX0/edit?gid=660406182#gid=660406182"", ""'""&D4&""'!B2:B45""),0),1))"),"CS") -> CS | C4: =IFERROR(__xludf.DUMMYFUNCTION("if(A4=""FEA006A"",""Garlic Herb Grilled Chicken"", ifna(INDEX(IMPORTRANGE(""https://docs.google.com/spreadsheets/d/1mnGm3iYGkB4FyqAD-LwwVYksgBMX_SY4qHQa16KgMiw/edit?gid=1956920866#gid=1956920866"", ""'EU Meal Database'!$E$2:$E""),MATCH(A4,IMPORTRANGE(""ht"&"tps://docs.google.com/spreadsheets/d/1mnGm3iYGkB4FyqAD-LwwVYksgBMX_SY4qHQa16KgMiw/edit?gid=1956920866#gid=1956920866"", ""'EU Meal Database'!$A$2:$A""),0)),INDEX(IMPORTRANGE(""https://docs.google.com/spreadsheets/d/1n4t_JF5P_MLd0hMmhjv1A2rgLKdyee_-mrZZmdZ"&"r9G4/edit?gid=670402169#gid=670402169"", ""'Meal DB_Product'!$B$2:$B""),MATCH(A4,IMPORTRANGE(""https://docs.google.com/spreadsheets/d/1n4t_JF5P_MLd0hMmhjv1A2rgLKdyee_-mrZZmdZr9G4/edit?gid=670402169#gid=670402169"", ""'Meal DB_Product'!$A$2:$A""),0))))"),"Sour Cream & Chive Chicken") -> Sour Cream & Chive Chicken | D4: W17 | E4: 402 | F4: 602 | G4: 302 | H4: =IFERROR(__xludf.DUMMYFUNCTION("""COMPUTED_VALUE"""),3290.0) -> 3290 | I4: =IFERROR(__xludf.DUMMYFUNCTION("""COMPUTED_VALUE"""),2384.0) -> 2384 | J4: =IFERROR(__xludf.DUMMYFUNCTION("""COMPUTED_VALUE"""),1662.0) -> 1662 | L4: =H4+20 -> 3310 | M4: =I4+20 -> 2404 | N4: =J4+20+K4 -> 1682 | O4: 0 | P4: 0 | Q4: 0 | R4: =L4*O4 -> 0 | S4: =M4*P4 -> 0 | T4: =N4*Q4 -> 0 | U4: =L4-R4 -> 3310 | V4: =M4-S4 -> 2404 | W4: =N4-T4 -> 1682
A5: =IFERROR(__xludf.DUMMYFUNCTION("if(E5=506,""FEA006A"",INDEX(IMPORTRANGE(""https://docs.google.com/spreadsheets/d/1WbE6HOh_eG5_DM53SVfuckYm0VQnhNvuwjql7Tw1FX0/edit?gid=660406182#gid=660406182"", ""'""&D5&""'!H2:H45""),match(E5,IMPORTRANGE(""https://docs.google.com/spreadsheets/d/1WbE6HOh"&"_eG5_DM53SVfuckYm0VQnhNvuwjql7Tw1FX0/edit?gid=660406182#gid=660406182"", ""'""&D5&""'!B2:B45""),0),1))"),"FE0849B") -> FE0849B | B5: =IFERROR(__xludf.DUMMYFUNCTION("if(E5=506,""-"",INDEX(IMPORTRANGE(""https://docs.google.com/spreadsheets/d/1WbE6HOh_eG5_DM53SVfuckYm0VQnhNvuwjql7Tw1FX0/edit?gid=660406182#gid=660406182"", ""'""&D5&""'!D2:D45""),match(E5,IMPORTRANGE(""https://docs.google.com/spreadsheets/d/1WbE6HOh_eG5_D"&"M53SVfuckYm0VQnhNvuwjql7Tw1FX0/edit?gid=660406182#gid=660406182"", ""'""&D5&""'!B2:B45""),0),1))"),"Keto") -> Keto | C5: =IFERROR(__xludf.DUMMYFUNCTION("if(A5=""FEA006A"",""Garlic Herb Grilled Chicken"", ifna(INDEX(IMPORTRANGE(""https://docs.google.com/spreadsheets/d/1mnGm3iYGkB4FyqAD-LwwVYksgBMX_SY4qHQa16KgMiw/edit?gid=1956920866#gid=1956920866"", ""'EU Meal Database'!$E$2:$E""),MATCH(A5,IMPORTRANGE(""ht"&"tps://docs.google.com/spreadsheets/d/1mnGm3iYGkB4FyqAD-LwwVYksgBMX_SY4qHQa16KgMiw/edit?gid=1956920866#gid=1956920866"", ""'EU Meal Database'!$A$2:$A""),0)),INDEX(IMPORTRANGE(""https://docs.google.com/spreadsheets/d/1n4t_JF5P_MLd0hMmhjv1A2rgLKdyee_-mrZZmdZ"&"r9G4/edit?gid=670402169#gid=670402169"", ""'Meal DB_Product'!$B$2:$B""),MATCH(A5,IMPORTRANGE(""https://docs.google.com/spreadsheets/d/1n4t_JF5P_MLd0hMmhjv1A2rgLKdyee_-mrZZmdZr9G4/edit?gid=670402169#gid=670402169"", ""'Meal DB_Product'!$A$2:$A""),0))))"),"Courgette-spaghetti bolognese") -> Courgette-spaghetti bolognese | D5: W17 | E5: 403 | F5: 603 | G5: 303 | H5: =IFERROR(__xludf.DUMMYFUNCTION("""COMPUTED_VALUE"""),3590.0) -> 3590 | I5: =IFERROR(__xludf.DUMMYFUNCTION("""COMPUTED_VALUE"""),2147.0) -> 2147 | J5: =IFERROR(__xludf.DUMMYFUNCTION("""COMPUTED_VALUE"""),1724.0) -> 1724 | K5: =IFERROR(__xludf.DUMMYFUNCTION("""COMPUTED_VALUE"""),16.0) -> 16 | L5: =H5+20 -> 3610 | M5: =I5+20 -> 2167 | N5: =J5+20+K5 -> 1760 | O5: 0 | P5: 0 | Q5: 0 | R5: =L5*O5 -> 0 | S5: =M5*P5 -> 0 | T5: =N5*Q5 -> 0 | U5: =L5-R5 -> 3610 | V5: =M5-S5 -> 2167 | W5: =N5-T5 -> 1760
A6: =IFERROR(__xludf.DUMMYFUNCTION("if(E6=506,""FEA006A"",INDEX(IMPORTRANGE(""https://docs.google.com/spreadsheets/d/1WbE6HOh_eG5_DM53SVfuckYm0VQnhNvuwjql7Tw1FX0/edit?gid=660406182#gid=660406182"", ""'""&D6&""'!H2:H45""),match(E6,IMPORTRANGE(""https://docs.google.com/spreadsheets/d/1WbE6HOh"&"_eG5_DM53SVfuckYm0VQnhNvuwjql7Tw1FX0/edit?gid=660406182#gid=660406182"", ""'""&D6&""'!B2:B45""),0),1))"),"FE1346B") -> FE1346B | B6: =IFERROR(__xludf.DUMMYFUNCTION("if(E6=506,""-"",INDEX(IMPORTRANGE(""https://docs.google.com/spreadsheets/d/1WbE6HOh_eG5_DM53SVfuckYm0VQnhNvuwjql7Tw1FX0/edit?gid=660406182#gid=660406182"", ""'""&D6&""'!D2:D45""),match(E6,IMPORTRANGE(""https://docs.google.com/spreadsheets/d/1WbE6HOh_eG5_D"&"M53SVfuckYm0VQnhNvuwjql7Tw1FX0/edit?gid=660406182#gid=660406182"", ""'""&D6&""'!B2:B45""),0),1))"),"P+") -> P+ | C6: =IFERROR(__xludf.DUMMYFUNCTION("if(A6=""FEA006A"",""Garlic Herb Grilled Chicken"", ifna(INDEX(IMPORTRANGE(""https://docs.google.com/spreadsheets/d/1mnGm3iYGkB4FyqAD-LwwVYksgBMX_SY4qHQa16KgMiw/edit?gid=1956920866#gid=1956920866"", ""'EU Meal Database'!$E$2:$E""),MATCH(A6,IMPORTRANGE(""ht"&"tps://docs.google.com/spreadsheets/d/1mnGm3iYGkB4FyqAD-LwwVYksgBMX_SY4qHQa16KgMiw/edit?gid=1956920866#gid=1956920866"", ""'EU Meal Database'!$A$2:$A""),0)),INDEX(IMPORTRANGE(""https://docs.google.com/spreadsheets/d/1n4t_JF5P_MLd0hMmhjv1A2rgLKdyee_-mrZZmdZ"&"r9G4/edit?gid=670402169#gid=670402169"", ""'Meal DB_Product'!$B$2:$B""),MATCH(A6,IMPORTRANGE(""https://docs.google.com/spreadsheets/d/1n4t_JF5P_MLd0hMmhjv1A2rgLKdyee_-mrZZmdZr9G4/edit?gid=670402169#gid=670402169"", ""'Meal DB_Product'!$A$2:$A""),0))))"),"Parmesan & Garlic Cream Pulled Beef") -> Parmesan & Garlic Cream Pulled Beef | D6: W17 | E6: 404 | F6: 604 | G6: 304 | H6: =IFERROR(__xludf.DUMMYFUNCTION("""COMPUTED_VALUE"""),6272.0) -> 6272 | I6: =IFERROR(__xludf.DUMMYFUNCTION("""COMPUTED_VALUE"""),3388.0) -> 3388 | J6: =IFERROR(__xludf.DUMMYFUNCTION("""COMPUTED_VALUE"""),2796.0) -> 2796 | L6: =H6+20 -> 6292 | M6: =I6+20 -> 3408 | N6: =J6+20+K6 -> 2816 | O6: 0 | P6: 0.9 | Q6: 0.9 | R6: =L6*O6 -> 0 | S6: =M6*P6 -> 3067.2 | T6: =N6*Q6 -> 2534.4 | U6: =L6-R6 -> 6292 | V6: =M6-S6 -> 340.8 | W6: =N6-T6 -> 281.6
